Workbook
Name ListaDisciplinas: tbDisciplinas[DISCIPLINA]
Name ListaFornecedores: tbFornecedores[FORNECEDOR]
Name ListaObras: tbObras[CÓDIGO]
Name ListaStatusMedição: tbStatusMedição[]
Name ListaStatusOrçamento: tbStatusOrçamento[Status orçamento]
Name ListaSubdisciplinas: tbSubdisciplinas[SUBDISCIPLINA]
Name SegmentaçãodeDados_CÓDIGO: #N/A
Name SegmentaçãodeDados_OBRA1: #N/A

Sheet Resumo
F2: ORÇADO | G2: CONTRATADO | H2: A CONTRATAR | I2: MEDIDO | J2: SALDO A MEDIR
F3: =GETPIVOTDATA("[Measures].[Soma de ORÇAMENTO BASE]",Cálculos!$B$1) -> 871259.2 | G3: =GETPIVOTDATA("[Measures].[Soma de VALOR CONTRATADO]",Cálculos!$B$1) -> 748921.2 | H3: =GETPIVOTDATA("[Measures].[Soma de SALDO A CONTRATAR]",Cálculos!$B$1) -> 122338 | I3: =GETPIVOTDATA("[Measures].[Soma de VALOR MEDIDO]",Cálculos!$B$1) -> 170452.99 | J3: =GETPIVOTDATA("[Measures].[Soma de SALDO MEDIÇÃO]",Cálculos!$B$1) -> 578468.21

Sheet Listas
A1: OBRA_ID | B1: CC | C1: CÓDIGO | D1: NOME | E1: ENDEREÇO | G1: DISCIPLINA_ID | H1: DISCIPLINA | I1: COD_DISCIPLINA | K1: DISCIPLINA_ID | L1: DISCIPLINA | M1: COD_DISCIPLINA | N1: SUBDISCIPLINA | O1: COD_SUBDISCIPLINA | Q1: FORNECEDOR_ID | R1: ID SIENGE | S1: FORNECEDOR | T1: TIPO | X1: Status orçamento | Z1: Status medições
A2: OBR001 | B2: 29 | C2: PAI3 | D2: Paineiras 3 | G2: DIS001 | H2: ARQUITETURA | I2: ARQ | K2: SUB001 | L2: ARQUITETURA | M2: ARQ | N2: ARQUITERURA LEGAL | O2: ARQ_LEGAL | Q2: FOR001 | R2: 2306 | S2: SOMA | T2: ARQUITETURA | X2: A contratar | Z2: A medir
A3: OBR002 | B3: 33 | C3: OTI | D3: Otília | G3: DIS002 | H3: ESTRUTURA | I3: EST | K3: SUB002 | L3: ARQUITETURA | M3: ARQ | N3: ARQUITETURA EXECUTIVA | O3: ARQ_EXE | Q3: FOR002 | R3: 27 | S3: MBUIATE | T3: ESTRUTURA | X3: Em cotação | Z3: Medido
A4: OBR003 | B4: 47 | C4: ALT | D4: Altamira | G4: DIS003 | H4: COMPLEMENTARES | I4: COMP | K4: SUB003 | L4: ESTRUTURA | M4: EST | N4: ESTRUTURA DE CONCRETO | O4: EST_CON | Q4: FOR003 | R4: 1532 | S4: ARCIS | T4: COMPLEMENTARES | X4: Em cotratação | Z4: Pago
A5: OBR004 | B5: 53 | C5: MON | D5: Monterré | G5: DIS004 | H5: PLANIALTIMÉTRICO | I5: PLAN | K5: SUB004 | L5: ESTRUTURA | M5: EST | N5: ESTRUTURA DE AÇO | O5: EST_MET | Q5: FOR004 | R5: 2665 | S5: VERTICAL | T5: ORÇAMENTO | X5: Contratado | Z5: Cancelada
A6: OBR005 | B6: 65 | C6: GAL | D6: Galassi | G6: DIS005 | H6: SONDAGEM | I6: SON | K6: SUB005 | L6: ESTRUTURA | M6: EST | N6: ESTRUTURA DE MADEIRA | O6: EST_MAD | Q6: FOR005 | R6: 2859 | S6: DALTON | T6: INTERIORES | X6: Cancelado
A7: OBR006 | B7: 71 | C7: PQSUL | D7: Parque Sul | G7: DIS006 | H7: FUNDAÇÃO | I7: FUN | K7: SUB006 | L7: ESTRUTURA | M7: EST | N7: ESCORAMENTO | O7: EST_ESC | Q7: FOR006 | R7: 2712 | S7: KARINA | T7: INTERIORES
A8: OBR007 | B8: 77 | C8: LIB | D8: Liberdade | G8: DIS007 | H8: INTERIORES | I8: INT | K8: SUB007 | L8: ESTRUTURA | M8: EST | N8: FUNDAÇÃO SUPERFICIAL | O8: EST_FUN | Q8: FOR007 | R8: 125 | S8: GEOMETA | T8: SONDAGEM
A9: OBR008 | B9: 82 | C9: UNA | D9: UNA | G9: DIS008 | H9: FACHADA | I9: FCH | K9: SUB008 | L9: ESTRUTURA | M9: EST | N9: CONTENÇÕES | O9: EST_CON | Q9: FOR008 | R9: 1763 | S9: GEOMETRIA | T9: FUNDAÇÃO
A10: OBR009 | B10: 84 | C10: STM | D10: Santa Mônica | G10: DIS009 | H10: ESQUADRIAS | I10: ESQ | K10: SUB025 | L10: ESTRUTURA | M10: EST | N10: PISO SUBSOLO | O10: EST_PISO | Q10: FOR009 | R10: 2691 | S10: EMMIG | T10: ESTRUTURA
A11: OBR010 | B11: 85 | C11: SEFAZ | D11: Galassi SEFAZ | G11: DIS010 | H11: IMPERMEABILIZAÇÃO | I11: IMP | K11: SUB009 | L11: COMPLEMENTARES | M11: COMP | N11: COMPLEMENTARES | O11: COMP | Q11: FOR010 | R11: 2739 | S11: BINV | T11: COMPLEMENTARES
G12: DIS011 | H12: SEGURANÇA | I12: SEG | K12: SUB010 | L12: COMPLEMENTARES | M12: COMP | N12: HIDROSSANITÁRIO | O12: HID | Q12: FOR011 | R12: 2637 | S12: DOMANI | T12: DESEMPENHO
G13: DIS012 | H13: DESEMPENHO | I13: DES | K13: SUB011 | L13: COMPLEMENTARES | M13: COMP | N13: ELÉTRICO | O13: ELE | Q13: FOR012 | R13: 447 | S13: VANIA | T13: SONDAGEM
G14: DIS013 | H14: INFRAESTRUTURA | I14: INF | K14: SUB012 | L14: COMPLEMENTARES | M14: COMP | N14: COMUNICAÇÃO | O14: COM | Q14: FOR013 | R14: 475 | S14: JP SERVIÇOS | T14: SONDAGEM
G15: DIS014 | H15: LEGALIZAÇÃO | I15: LEG | K15: SUB013 | L15: COMPLEMENTARES | M15: COMP | N15: SPDA | O15: SPDA | Q15: FOR014 | R15: 1062 | S15: GÊMEAS | T15: ARQUITETURA
G16: DIS015 | H16: ORÇAMENTO | I16: ORC | K16: SUB014 | L16: COMPLEMENTARES | M16: COMP | N16: GÁS | O16: GLP | Q16: FOR015 | R16: 663 | S16: IDEAL | T16: PLANIALTIMÉTRICO
G17: DIS016 | H17: PLANEJAMENTO | I17: PLA | K17: SUB015 | L17: COMPLEMENTARES | M17: COMP | N17: CLIMATIZAÇÃO | O17: CLI | Q17: FOR016 | R17: 2740 | S17: GEOMAP | T17: PLANIALTIMÉTRICO
K18: SUB016 | L18: COMPLEMENTARES | M18: COMP | N18: INCÊNDIO | O18: PCI | Q18: FOR017 | R18: 2778 | S18: THAIS | T18: LEGALIZAÇÃO
K19: SUB017 | L19: COMPLEMENTARES | M19: COMP | N19: PRESSURIZAÇÃO | O19: PRE | Q19: FOR018 | R19: 844 | S19: COSTA | T19: LEGALIZAÇÃO
K20: SUB018 | L20: COMPLEMENTARES | M20: COMP | N20: MARKUP | O20: MKP | Q20: FOR019 | R20: 60 | S20: CARTÓRIO | T20: LEGALIZAÇÃO
K21: SUB019 | L21: COMPLEMENTARES | M21: COMP | N21: PISCINA | O21: PIS | Q21: FOR020 | R21: 370 | S21: CREA | T21: LEGALIZAÇÃO
K22: SUB020 | L22: COMPLEMENTARES | M22: COMP | N22: COMPATIBILIZAÇÃO | O22: MOD | Q22: FOR021 | R22: 1942 | S22: CRT | T22: LEGALIZAÇÃO
K23: SUB021 | L23: PLANIALTIMÉTRICO | M23: PLAN | N23: PLANIALTIMÉTRICO | O23: PLAN | Q23: FOR022 | R23: 1653 | S23: PMU | T23: LEGALIZAÇÃO
K24: SUB022 | L24: SONDAGEM | M24: SON | N24: SONDAGEM | O24: SON | Q24: FOR023 | R24: 2 | S24: RECEITA | T24: LEGALIZAÇÃO
K25: SUB023 | L25: FUNDAÇÃO | M25: FUN | N25: FUNDAÇÃO PROFUNDA | O25: FUN_PRO | Q25: FOR024 | S25: TAXAS | T25: LEGALIZAÇÃO
K26: SUB026 | L26: INTERIORES | M26: INT | N26: INTERIORES | O26: INT
K27: SUB027 | L27: INTERIORES | M27: INT | N27: PAISAGISMO | O27: PSG
K28: SUB028 | L28: FACHADA | M28: FCH | N28: FACHADA | O28: FCH
K29: SUB029 | L29: ESQUADRIAS | M29: ESQ | N29: ESQUADRIAS | O29: ESQ
K30: SUB030 | L30: IMPERMEABILIZAÇÃO | M30: IMP | N30: IMPERMEABILIZAÇÃO | O30: IMP
K31: SUB031 | L31: SEGURANÇA | M31: SEG | N31: SEGURANÇA | O31: CFTV
K32: SUB032 | L32: DESEMPENHO | M32: DES | N32: DESEMPENHO | O32: DES
K33: SUB033 | L33: DESEMPENHO | M33: DES | N33: LAUDO DE RUÍDO | O33: RUI
K34: SUB034 | L34: INFRAESTRUTURA | M34: INF | N34: INTERLIGAÇÃO ÁGUA | O34: INF_DMAE
K35: SUB035 | L35: INFRAESTRUTURA | M35: INF | N35: INTERLIGAÇÃO ELÉTRICA | O35: INF_CEMIG
K36: SUB036 | L36: INFRAESTRUTURA | M36: INF | N36: INTERLIGAÇÃO ESGOTO | O36: INF_DMAE
K37: SUB037 | L37: INFRAESTRUTURA | M37: INF | N37: INTERLIGAÇÃO DRENAGEM PLUVIAL | O37: INF_DMAE
... K60: SUB060 | L60: PLANEJAMENTO | M60: PLA | N60: EXECUTIVO | O60: EXE

Sheet Cálculos
B1: Soma de ORÇAMENTO BASE | C1: Soma de VALOR CONTRATADO | D1: Soma de SALDO A CONTRATAR | E1: Soma de VALOR MEDIDO | F1: Soma de SALDO MEDIÇÃO
B2: 871259.2 | C2: 748921.2 | D2: 122338 | E2: 170452.99 | F2: 578468.21
B7: Rótulos de Linha | C7: DESEMBOLSO | D7: ACUMULADO
B8: 26/01 | C8: 45000 | D8: 45000
B9: 26/02 | C9: 2850 | D9: 47850
B10: 26/03 | C10: 9993 | D10: 57843
B11: 26/04 | C11: 9993 | D11: 67836
B12: 26/05 | C12: 3399.66 | D12: 71235.66
B13: 26/06 | C13: 65138.71 | D13: 136374.37
B14: 26/07 | C14: 79078.62 | D14: 215452.99
B15: 26/08 | C15: 34661 | D15: 250113.99
B16: 26/09 | C16: 55953 | D16: 306066.99
B17: 26/10 | C17: 58037.23 | D17: 364104.22
B18: 26/11 | C18: 39179 | D18: 403283.22
B19: 26/12 | C19: 41915 | D19: 445198.22
B20: 27/01 | C20: 6490 | D20: 451688.22
B21: Total Geral | C21: 451688.22

Sheet tbOrçamento
A1: OBRA | B1: NOME OBRA | C1: DISCIPLINA | D1: SUBDISCIPLINA | E1: ORÇAMENTO BASE | F1: VALOR CONTRATADO | G1: SALDO A CONTRATAR | H1: VALOR MEDIDO | I1: SALDO MEDIÇÃO | J1: STATUS
A2: ALT | B2: =_xlfn.XLOOKUP(tbOrçamento[[#This Row],[OBRA]],tbObras[CÓDIGO],tbObras[NOME],"Não encontrado",0) -> Altamira | C2: SONDAGEM | D2: SONDAGEM | E2: 56000 | F2: =SUMIFS(tbContratos[VALOR CONTRATO],tbContratos[OBRA],tbOrçamento[[#This Row],[OBRA]],tbContratos[SUBDISCIPLINA],tbOrçamento[[#This Row],[SUBDISCIPLINA]]) -> 21880.65 | G2: =tbOrçamento[[#This Row],[ORÇAMENTO BASE ]]-tbOrçamento[[#This Row],[VALOR CONTRATADO]] -> 34119.35 | H2: =SUMIFS(tbContratos[VALOR MEDIDO],tbContratos[OBRA],tbOrçamento[[#This Row],[OBRA]],tbContratos[SUBDISCIPLINA],tbOrçamento[[#This Row],[SUBDISCIPLINA]]) -> 21880.65 | I2: =tbOrçamento[[#This Row],[VALOR CONTRATADO]]-tbOrçamento[[#This Row],[VALOR MEDIDO]] -> 0 | J2: Contratado
A3: ALT | B3: =_xlfn.XLOOKUP(tbOrçamento[[#This Row],[OBRA]],tbObras[CÓDIGO],tbObras[NOME],"Não encontrado",0) -> Altamira | C3: PLANIALTIMÉTRICO | D3: PLANIALTIMÉTRICO | E3: 5000 | F3: =SUMIFS(tbContratos[VALOR CONTRATO],tbContratos[OBRA],tbOrçamento[[#This Row],[OBRA]],tbContratos[SUBDISCIPLINA],tbOrçamento[[#This Row],[SUBDISCIPLINA]]) -> 4550 | G3: =tbOrçamento[[#This Row],[ORÇAMENTO BASE ]]-tbOrçamento[[#This Row],[VALOR CONTRATADO]] -> 450 | H3: =SUMIFS(tbContratos[VALOR MEDIDO],tbContratos[OBRA],tbOrçamento[[#This Row],[OBRA]],tbContratos[SUBDISCIPLINA],tbOrçamento[[#This Row],[SUBDISCIPLINA]]) -> 4550 | I3: =tbOrçamento[[#This Row],[VALOR CONTRATADO]]-tbOrçamento[[#This Row],[VALOR MEDIDO]] -> 0 | J3: Contratado
A4: ALT | B4: =_xlfn.XLOOKUP(tbOrçamento[[#This Row],[OBRA]],tbObras[CÓDIGO],tbObras[NOME],"Não encontrado",0) -> Altamira | C4: ARQUITETURA | D4: ARQUITERURA LEGAL | E4: 108000 | F4: =SUMIFS(tbContratos[VALOR CONTRATO],tbContratos[OBRA],tbOrçamento[[#This Row],[OBRA]],tbContratos[SUBDISCIPLINA],tbOrçamento[[#This Row],[SUBDISCIPLINA]]) -> 108000 | G4: =tbOrçamento[[#This Row],[ORÇAMENTO BASE ]]-tbOrçamento[[#This Row],[VALOR CONTRATADO]] -> 0 | H4: =SUMIFS(tbContratos[VALOR MEDIDO],tbContratos[OBRA],tbOrçamento[[#This Row],[OBRA]],tbContratos[SUBDISCIPLINA],tbOrçamento[[#This Row],[SUBDISCIPLINA]]) -> 102600 | I4: =tbOrçamento[[#This Row],[VALOR CONTRATADO]]-tbOrçamento[[#This Row],[VALOR MEDIDO]] -> 5400 | J4: Contratado
A5: ALT | B5: =_xlfn.XLOOKUP(tbOrçamento[[#This Row],[OBRA]],tbObras[CÓDIGO],tbObras[NOME],"Não encontrado",0) -> Altamira | C5: ARQUITETURA | D5: ARQUITETURA EXECUTIVA | E5: 108000 | F5: =SUMIFS(tbContratos[VALOR CONTRATO],tbContratos[OBRA],tbOrçamento[[#This Row],[OBRA]],tbContratos[SUBDISCIPLINA],tbOrçamento[[#This Row],[SUBDISCIPLINA]]) -> 0 | G5: =tbOrçamento[[#This Row],[ORÇAMENTO BASE ]]-tbOrçamento[[#This Row],[VALOR CONTRATADO]] -> 108000 | H5: =SUMIFS(tbContratos[VALOR MEDIDO],tbContratos[OBRA],tbOrçamento[[#This Row],[OBRA]],tbContratos[SUBDISCIPLINA],tbOrçamento[[#This Row],[SUBDISCIPLINA]]) -> 0 | I5: =tbOrçamento[[#This Row],[VALOR CONTRATADO]]-tbOrçamento[[#This Row],[VALOR MEDIDO]] -> 0 | J5: A contratar
A6: ALT | B6: =_xlfn.XLOOKUP(tbOrçamento[[#This Row],[OBRA]],tbObras[CÓDIGO],tbObras[NOME],"Não encontrado",0) -> Altamira | C6: ESTRUTURA | D6: ESTRUTURA DE CONCRETO | E6: 90000 | F6: =SUMIFS(tbContratos[VALOR CONTRATO],tbContratos[OBRA],tbOrçamento[[#This Row],[OBRA]],tbContratos[SUBDISCIPLINA],tbOrçamento[[#This Row],[SUBDISCIPLINA]]) -> 90000 | G6: =tbOrçamento[[#This Row],[ORÇAMENTO BASE ]]-tbOrçamento[[#This Row],[VALOR CONTRATADO]] -> 0 | H6: =SUMIFS(tbContratos[VALOR MEDIDO],tbContratos[OBRA],tbOrçamento[[#This Row],[OBRA]],tbContratos[SUBDISCIPLINA],tbOrçamento[[#This Row],[SUBDISCIPLINA]]) -> 18000 | I6: =tbOrçamento[[#This Row],[VALOR CONTRATADO]]-tbOrçamento[[#This Row],[VALOR MEDIDO]] -> 72000 | J6: Contratado
A7: ALT | B7: =_xlfn.XLOOKUP(tbOrçamento[[#This Row],[OBRA]],tbObras[CÓDIGO],tbObras[NOME],"Não encontrado",0) -> Altamira | C7: FUNDAÇÃO | D7: FUNDAÇÃO PROFUNDA | E7: 25000 | F7: =SUMIFS(tbContratos[VALOR CONTRATO],tbContratos[OBRA],tbOrçamento[[#This Row],[OBRA]],tbContratos[SUBDISCIPLINA],tbOrçamento[[#This Row],[SUBDISCIPLINA]]) -> 25000 | G7: =tbOrçamento[[#This Row],[ORÇAMENTO BASE ]]-tbOrçamento[[#This Row],[VALOR CONTRATADO]] -> 0 | H7: =SUMIFS(tbContratos[VALOR MEDIDO],tbContratos[OBRA],tbOrçamento[[#This Row],[OBRA]],tbContratos[SUBDISCIPLINA],tbOrçamento[[#This Row],[SUBDISCIPLINA]]) -> 0 | I7: =tbOrçamento[[#This Row],[VALOR CONTRATADO]]-tbOrçamento[[#This Row],[VALOR MEDIDO]] -> 25000 | J7: Contratado
A8: ALT | B8: =_xlfn.XLOOKUP(tbOrçamento[[#This Row],[OBRA]],tbObras[CÓDIGO],tbObras[NOME],"Não encontrado",0) -> Altamira | C8: FUNDAÇÃO | D8: PISO SUBSOLO | E8: 5000 | F8: =SUMIFS(tbContratos[VALOR CONTRATO],tbContratos[OBRA],tbOrçamento[[#This Row],[OBRA]],tbContratos[SUBDISCIPLINA],tbOrçamento[[#This Row],[SUBDISCIPLINA]]) -> 0 | G8: =tbOrçamento[[#This Row],[ORÇAMENTO BASE ]]-tbOrçamento[[#This Row],[VALOR CONTRATADO]] -> 5000 | H8: =SUMIFS(tbContratos[VALOR MEDIDO],tbContratos[OBRA],tbOrçamento[[#This Row],[OBRA]],tbContratos[SUBDISCIPLINA],tbOrçamento[[#This Row],[SUBDISCIPLINA]]) -> 0 | I8: =tbOrçamento[[#This Row],[VALOR CONTRATADO]]-tbOrçamento[[#This Row],[VALOR MEDIDO]] -> 0 | J8: A contratar
A9: ALT | B9: =_xlfn.XLOOKUP(tbOrçamento[[#This Row],[OBRA]],tbObras[CÓDIGO],tbObras[NOME],"Não encontrado",0) -> Altamira | C9: COMPLEMENTARES | D9: COMPLEMENTARES | E9: 150000 | F9: =SUMIFS(tbContratos[VALOR CONTRATO],tbContratos[OBRA],tbOrçamento[[#This Row],[OBRA]],tbContratos[SUBDISCIPLINA],tbOrçamento[[#This Row],[SUBDISCIPLINA]]) -> 290000 | G9: =tbOrçamento[[#This Row],[ORÇAMENTO BASE ]]-tbOrçamento[[#This Row],[VALOR CONTRATADO]] -> -140000 | H9: =SUMIFS(tbContratos[VALOR MEDIDO],tbContratos[OBRA],tbOrçamento[[#This Row],[OBRA]],tbContratos[SUBDISCIPLINA],tbOrçamento[[#This Row],[SUBDISCIPLINA]]) -> 109000 | I9: =tbOrçamento[[#This Row],[VALOR CONTRATADO]]-tbOrçamento[[#This Row],[VALOR MEDIDO]] -> 181000 | J9: Contratado
A10: ALT | B10: =_xlfn.XLOOKUP(tbOrçamento[[#This Row],[OBRA]],tbObras[CÓDIGO],tbObras[NOME],"Não encontrado",0) -> Altamira | C10: INTERIORES | D10: INTERIORES | E10: 34500 | F10: =SUMIFS(tbContratos[VALOR CONTRATO],tbContratos[OBRA],tbOrçamento[[#This Row],[OBRA]],tbContratos[SUBDISCIPLINA],tbOrçamento[[#This Row],[SUBDISCIPLINA]]) -> 39500 | G10: =tbOrçamento[[#This Row],[ORÇAMENTO BASE ]]-tbOrçamento[[#This Row],[VALOR CONTRATADO]] -> -5000 | H10: =SUMIFS(tbContratos[VALOR MEDIDO],tbContratos[OBRA],tbOrçamento[[#This Row],[OBRA]],tbContratos[SUBDISCIPLINA],tbOrçamento[[#This Row],[SUBDISCIPLINA]]) -> 20700 | I10: =tbOrçamento[[#This Row],[VALOR CONTRATADO]]-tbOrçamento[[#This Row],[VALOR MEDIDO]] -> 18800 | J10: Contratado
A11: ALT | B11: =_xlfn.XLOOKUP(tbOrçamento[[#This Row],[OBRA]],tbObras[CÓDIGO],tbObras[NOME],"Não encontrado",0) -> Altamira | C11: FACHADA | D11: FACHADA | E11: 15000 | F11: =SUMIFS(tbContratos[VALOR CONTRATO],tbContratos[OBRA],tbOrçamento[[#This Row],[OBRA]],tbContratos[SUBDISCIPLINA],tbOrçamento[[#This Row],[SUBDISCIPLINA]]) -> 0 | G11: =tbOrçamento[[#This Row],[ORÇAMENTO BASE ]]-tbOrçamento[[#This Row],[VALOR CONTRATADO]] -> 15000 | H11: =SUMIFS(tbContratos[VALOR MEDIDO],tbContratos[OBRA],tbOrçamento[[#This Row],[OBRA]],tbContratos[SUBDISCIPLINA],tbOrçamento[[#This Row],[SUBDISCIPLINA]]) -> 0 | I11: =tbOrçamento[[#This Row],[VALOR CONTRATADO]]-tbOrçamento[[#This Row],[VALOR MEDIDO]] -> 0 | J11: A contratar
A12: ALT | B12: =_xlfn.XLOOKUP(tbOrçamento[[#This Row],[OBRA]],tbObras[CÓDIGO],tbObras[NOME],"Não encontrado",0) -> Altamira | C12: ESQUADRIAS | D12: ESQUADRIAS | E12: 20000 | F12: =SUMIFS(tbContratos[VALOR CONTRATO],tbContratos[OBRA],tbOrçamento[[#This Row],[OBRA]],tbContratos[SUBDISCIPLINA],tbOrçamento[[#This Row],[SUBDISCIPLINA]]) -> 0 | G12: =tbOrçamento[[#This Row],[ORÇAMENTO BASE ]]-tbOrçamento[[#This Row],[VALOR CONTRATADO]] -> 20000 | H12: =SUMIFS(tbContratos[VALOR MEDIDO],tbContratos[OBRA],tbOrçamento[[#This Row],[OBRA]],tbContratos[SUBDISCIPLINA],tbOrçamento[[#This Row],[SUBDISCIPLINA]]) -> 0 | I12: =tbOrçamento[[#This Row],[VALOR CONTRATADO]]-tbOrçamento[[#This Row],[VALOR MEDIDO]] -> 0 | J12: A contratar
A13: ALT | B13: =_xlfn.XLOOKUP(tbOrçamento[[#This Row],[OBRA]],tbObras[CÓDIGO],tbObras[NOME],"Não encontrado",0) -> Altamira | C13: IMPERMEABILIZAÇÃO | D13: IMPERMEABILIZAÇÃO | E13: 15000 | F13: =SUMIFS(tbContratos[VALOR CONTRATO],tbContratos[OBRA],tbOrçamento[[#This Row],[OBRA]],tbContratos[SUBDISCIPLINA],tbOrçamento[[#This Row],[SUBDISCIPLINA]]) -> 0 | G13: =tbOrçamento[[#This Row],[ORÇAMENTO BASE ]]-tbOrçamento[[#This Row],[VALOR CONTRATADO]] -> 15000 | H13: =SUMIFS(tbContratos[VALOR MEDIDO],tbContratos[OBRA],tbOrçamento[[#This Row],[OBRA]],tbContratos[SUBDISCIPLINA],tbOrçamento[[#This Row],[SUBDISCIPLINA]]) -> 0 | I13: =tbOrçamento[[#This Row],[VALOR CONTRATADO]]-tbOrçamento[[#This Row],[VALOR MEDIDO]] -> 0 | J13: A contratar
... A40: GAL | B40: =_xlfn.XLOOKUP(tbOrçamento[[#This Row],[OBRA]],tbObras[CÓDIGO],tbObras[NOME],"Não encontrado",0) -> Galassi | C40: INFRAESTRUTURA | D40: INTERLIGAÇÃO ELÉTRICA | E40: 10000 | F40: =SUMIFS(tbContratos[VALOR CONTRATO],tbContratos[OBRA],tbOrçamento[[#This Row],[OBRA]],tbContratos[SUBDISCIPLINA],tbOrçamento[[#This Row],[SUBDISCIPLINA]]) -> 0 | G40: =tbOrçamento[[#This Row],[ORÇAMENTO BASE ]]-tbOrçamento[[#This Row],[VALOR CONTRATADO]] -> 10000 | H40: =SUMIFS(tbContratos[VALOR MEDIDO],tbContratos[OBRA],tbOrçamento[[#This Row],[OBRA]],tbContratos[SUBDISCIPLINA],tbOrçamento[[#This Row],[SUBDISCIPLINA]]) -> 0 | I40: =tbOrçamento[[#This Row],[VALOR CONTRATADO]]-tbOrçamento[[#This Row],[VALOR MEDIDO]] -> 0 | J40: A contratar
A41: GAL | B41: =_xlfn.XLOOKUP(tbOrçamento[[#This Row],[OBRA]],tbObras[CÓDIGO],tbObras[NOME],"Não encontrado",0) -> Galassi | C41: INFRAESTRUTURA | D41: PROLONGAMENTO REDE | F41: =SUMIFS(tbContratos[VALOR CONTRATO],tbContratos[OBRA],tbOrçamento[[#This Row],[OBRA]],tbContratos[SUBDISCIPLINA],tbOrçamento[[#This Row],[SUBDISCIPLINA]]) -> 0 | G41: =tbOrçamento[[#This Row],[ORÇAMENTO BASE ]]-tbOrçamento[[#This Row],[VALOR CONTRATADO]] -> 0 | H41: =SUMIFS(tbContratos[VALOR MEDIDO],tbContratos[OBRA],tbOrçamento[[#This Row],[OBRA]],tbContratos[SUBDISCIPLINA],tbOrçamento[[#This Row],[SUBDISCIPLINA]]) -> 0 | I41: =tbOrçamento[[#This Row],[VALOR CONTRATADO]]-tbOrçamento[[#This Row],[VALOR MEDIDO]] -> 0 | J41: A contratar
A42: GAL | B42: =_xlfn.XLOOKUP(tbOrçamento[[#This Row],[OBRA]],tbObras[CÓDIGO],tbObras[NOME],"Não encontrado",0) -> Galassi | C42: ORÇAMENTO | D42: PARAMÉTRICO | E42: 10000 | F42: =SUMIFS(tbContratos[VALOR CONTRATO],tbContratos[OBRA],tbOrçamento[[#This Row],[OBRA]],tbContratos[SUBDISCIPLINA],tbOrçamento[[#This Row],[SUBDISCIPLINA]]) -> 6248.31 | G42: =tbOrçamento[[#This Row],[ORÇAMENTO BASE ]]-tbOrçamento[[#This Row],[VALOR CONTRATADO]] -> 3751.69 | H42: =SUMIFS(tbContratos[VALOR MEDIDO],tbContratos[OBRA],tbOrçamento[[#This Row],[OBRA]],tbContratos[SUBDISCIPLINA],tbOrçamento[[#This Row],[SUBDISCIPLINA]]) -> 1874.493 | I42: =tbOrçamento[[#This Row],[VALOR CONTRATADO]]-tbOrçamento[[#This Row],[VALOR MEDIDO]] -> 4373.817 | J42: Contratado
A43: GAL | B43: =_xlfn.XLOOKUP(tbOrçamento[[#This Row],[OBRA]],tbObras[CÓDIGO],tbObras[NOME],"Não encontrado",0) -> Galassi | C43: ORÇAMENTO | D43: EXECUTIVO | E43: 25000 | F43: =SUMIFS(tbContratos[VALOR CONTRATO],tbContratos[OBRA],tbOrçamento[[#This Row],[OBRA]],tbContratos[SUBDISCIPLINA],tbOrçamento[[#This Row],[SUBDISCIPLINA]]) -> 0 | G43: =tbOrçamento[[#This Row],[ORÇAMENTO BASE ]]-tbOrçamento[[#This Row],[VALOR CONTRATADO]] -> 25000 | H43: =SUMIFS(tbContratos[VALOR MEDIDO],tbContratos[OBRA],tbOrçamento[[#This Row],[OBRA]],tbContratos[SUBDISCIPLINA],tbOrçamento[[#This Row],[SUBDISCIPLINA]]) -> 0 | I43: =tbOrçamento[[#This Row],[VALOR CONTRATADO]]-tbOrçamento[[#This Row],[VALOR MEDIDO]] -> 0 | J43: A contratar
A44: GAL | B44: =_xlfn.XLOOKUP(tbOrçamento[[#This Row],[OBRA]],tbObras[CÓDIGO],tbObras[NOME],"Não encontrado",0) -> Galassi | C44: PLANEJAMENTO | D44: EXECUTIVO | E44: 15000 | F44: =SUMIFS(tbContratos[VALOR CONTRATO],tbContratos[OBRA],tbOrçamento[[#This Row],[OBRA]],tbContratos[SUBDISCIPLINA],tbOrçamento[[#This Row],[SUBDISCIPLINA]]) -> 0 | G44: =tbOrçamento[[#This Row],[ORÇAMENTO BASE ]]-tbOrçamento[[#This Row],[VALOR CONTRATADO]] -> 15000 | H44: =SUMIFS(tbContratos[VALOR MEDIDO],tbContratos[OBRA],tbOrçamento[[#This Row],[OBRA]],tbContratos[SUBDISCIPLINA],tbOrçamento[[#This Row],[SUBDISCIPLINA]]) -> 0 | I44: =tbOrçamento[[#This Row],[VALOR CONTRATADO]]-tbOrçamento[[#This Row],[VALOR MEDIDO]] -> 0 | J44: A contratar
A45: GAL | B45: =_xlfn.XLOOKUP(tbOrçamento[[#This Row],[OBRA]],tbObras[CÓDIGO],tbObras[NOME],"Não encontrado",0) -> Galassi | C45: LEGALIZAÇÃO | D45: LEGALIZAÇÃO | E45: 304579.2 | F45: =SUMIFS(tbContratos[VALOR CONTRATO],tbContratos[OBRA],tbOrçamento[[#This Row],[OBRA]],tbContratos[SUBDISCIPLINA],tbOrçamento[[#This Row],[SUBDISCIPLINA]]) -> 304579.2 | G45: =tbOrçamento[[#This Row],[ORÇAMENTO BASE ]]-tbOrçamento[[#This Row],[VALOR CONTRATADO]] -> 0 | H45: =SUMIFS(tbContratos[VALOR MEDIDO],tbContratos[OBRA],tbOrçamento[[#This Row],[OBRA]],tbContratos[SUBDISCIPLINA],tbOrçamento[[#This Row],[SUBDISCIPLINA]]) -> 18111.22 | I45: =tbOrçamento[[#This Row],[VALOR CONTRATADO]]-tbOrçamento[[#This Row],[VALOR MEDIDO]] -> 286467.98 | J45: A contratar
A46: PQSUL | B46: =_xlfn.XLOOKUP(tbOrçamento[[#This Row],[OBRA]],tbObras[CÓDIGO],tbObras[NOME],"Não encontrado",0) -> Parque Sul | C46: SONDAGEM | D46: SONDAGEM | E46: 25000 | F46: =SUMIFS(tbContratos[VALOR CONTRATO],tbContratos[OBRA],tbOrçamento[[#This Row],[OBRA]],tbContratos[SUBDISCIPLINA],tbOrçamento[[#This Row],[SUBDISCIPLINA]]) -> 23556.1 | G46: =tbOrçamento[[#This Row],[ORÇAMENTO BASE ]]-tbOrçamento[[#This Row],[VALOR CONTRATADO]] -> 1443.9 | H46: =SUMIFS(tbContratos[VALOR MEDIDO],tbContratos[OBRA],tbOrçamento[[#This Row],[OBRA]],tbContratos[SUBDISCIPLINA],tbOrçamento[[#This Row],[SUBDISCIPLINA]]) -> 23556.1 | I46: =tbOrçamento[[#This Row],[VALOR CONTRATADO]]-tbOrçamento[[#This Row],[VALOR MEDIDO]] -> 0 | J46: Contratado
A47: PQSUL | B47: =_xlfn.XLOOKUP(tbOrçamento[[#This Row],[OBRA]],tbObras[CÓDIGO],tbObras[NOME],"Não encontrado",0) -> Parque Sul | C47: PLANIALTIMÉTRICO | D47: PLANIALTIMÉTRICO | E47: 5000 | F47: =SUMIFS(tbContratos[VALOR CONTRATO],tbContratos[OBRA],tbOrçamento[[#This Row],[OBRA]],tbContratos[SUBDISCIPLINA],tbOrçamento[[#This Row],[SUBDISCIPLINA]]) -> 1300 | G47: =tbOrçamento[[#This Row],[ORÇAMENTO BASE ]]-tbOrçamento[[#This Row],[VALOR CONTRATADO]] -> 3700 | H47: =SUMIFS(tbContratos[VALOR MEDIDO],tbContratos[OBRA],tbOrçamento[[#This Row],[OBRA]],tbContratos[SUBDISCIPLINA],tbOrçamento[[#This Row],[SUBDISCIPLINA]]) -> 1300 | I47: =tbOrçamento[[#This Row],[VALOR CONTRATADO]]-tbOrçamento[[#This Row],[VALOR MEDIDO]] -> 0 | J47: Contratado
A48: PQSUL | B48: =_xlfn.XLOOKUP(tbOrçamento[[#This Row],[OBRA]],tbObras[CÓDIGO],tbObras[NOME],"Não encontrado",0) -> Parque Sul | C48: ARQUITETURA | D48: ARQUITERURA LEGAL | E48: 160000 | F48: =SUMIFS(tbContratos[VALOR CONTRATO],tbContratos[OBRA],tbOrçamento[[#This Row],[OBRA]],tbContratos[SUBDISCIPLINA],tbOrçamento[[#This Row],[SUBDISCIPLINA]]) -> 160000 | G48: =tbOrçamento[[#This Row],[ORÇAMENTO BASE ]]-tbOrçamento[[#This Row],[VALOR CONTRATADO]] -> 0 | H48: =SUMIFS(tbContratos[VALOR MEDIDO],tbContratos[OBRA],tbOrçamento[[#This Row],[OBRA]],tbContratos[SUBDISCIPLINA],tbOrçamento[[#This Row],[SUBDISCIPLINA]]) -> 64000 | I48: =tbOrçamento[[#This Row],[VALOR CONTRATADO]]-tbOrçamento[[#This Row],[VALOR MEDIDO]] -> 96000 | J48: Contratado
A49: PQSUL | B49: =_xlfn.XLOOKUP(tbOrçamento[[#This Row],[OBRA]],tbObras[CÓDIGO],tbObras[NOME],"Não encontrado",0) -> Parque Sul | C49: ARQUITETURA | D49: ARQUITETURA EXECUTIVA | E49: 59800 | F49: =SUMIFS(tbContratos[VALOR CONTRATO],tbContratos[OBRA],tbOrçamento[[#This Row],[OBRA]],tbContratos[SUBDISCIPLINA],tbOrçamento[[#This Row],[SUBDISCIPLINA]]) -> 0 | G49: =tbOrçamento[[#This Row],[ORÇAMENTO BASE ]]-tbOrçamento[[#This Row],[VALOR CONTRATADO]] -> 59800 | H49: =SUMIFS(tbContratos[VALOR MEDIDO],tbContratos[OBRA],tbOrçamento[[#This Row],[OBRA]],tbContratos[SUBDISCIPLINA],tbOrçamento[[#This Row],[SUBDISCIPLINA]]) -> 0 | I49: =tbOrçamento[[#This Row],[VALOR CONTRATADO]]-tbOrçamento[[#This Row],[VALOR MEDIDO]] -> 0 | J49: Em cotação
A50: PQSUL | B50: =_xlfn.XLOOKUP(tbOrçamento[[#This Row],[OBRA]],tbObras[CÓDIGO],tbObras[NOME],"Não encontrado",0) -> Parque Sul | C50: ESTRUTURA | D50: ESTRUTURA DE CONCRETO | E50: 225000 | F50: =SUMIFS(tbContratos[VALOR CONTRATO],tbContratos[OBRA],tbOrçamento[[#This Row],[OBRA]],tbContratos[SUBDISCIPLINA],tbOrçamento[[#This Row],[SUBDISCIPLINA]]) -> 210000 | G50: =tbOrçamento[[#This Row],[ORÇAMENTO BASE ]]-tbOrçamento[[#This Row],[VALOR CONTRATADO]] -> 15000 | H50: =SUMIFS(tbContratos[VALOR MEDIDO],tbContratos[OBRA],tbOrçamento[[#This Row],[OBRA]],tbContratos[SUBDISCIPLINA],tbOrçamento[[#This Row],[SUBDISCIPLINA]]) -> 31500 | I50: =tbOrçamento[[#This Row],[VALOR CONTRATADO]]-tbOrçamento[[#This Row],[VALOR MEDIDO]] -> 178500 | J50: Contratado
A51: PQSUL | B51: =_xlfn.XLOOKUP(tbOrçamento[[#This Row],[OBRA]],tbObras[CÓDIGO],tbObras[NOME],"Não encontrado",0) -> Parque Sul | C51: FUNDAÇÃO | D51: FUNDAÇÃO PROFUNDA | E51: 30000 | F51: =SUMIFS(tbContratos[VALOR CONTRATO],tbContratos[OBRA],tbOrçamento[[#This Row],[OBRA]],tbContratos[SUBDISCIPLINA],tbOrçamento[[#This Row],[SUBDISCIPLINA]]) -> 30000 | G51: =tbOrçamento[[#This Row],[ORÇAMENTO BASE ]]-tbOrçamento[[#This Row],[VALOR CONTRATADO]] -> 0 | H51: =SUMIFS(tbContratos[VALOR MEDIDO],tbContratos[OBRA],tbOrçamento[[#This Row],[OBRA]],tbContratos[SUBDISCIPLINA],tbOrçamento[[#This Row],[SUBDISCIPLINA]]) -> 0 | I51: =tbOrçamento[[#This Row],[VALOR CONTRATADO]]-tbOrçamento[[#This Row],[VALOR MEDIDO]] -> 30000 | J51: Contratado
A52: PQSUL | B52: =_xlfn.XLOOKUP(tbOrçamento[[#This Row],[OBRA]],tbObras[CÓDIGO],tbObras[NOME],"Não encontrado",0) -> Parque Sul | C52: FUNDAÇÃO | D52: PISO SUBSOLO | E52: 5000 | F52: =SUMIFS(tbContratos[VALOR CONTRATO],tbContratos[OBRA],tbOrçamento[[#This Row],[OBRA]],tbContratos[SUBDISCIPLINA],tbOrçamento[[#This Row],[SUBDISCIPLINA]]) -> 0 | G52: =tbOrçamento[[#This Row],[ORÇAMENTO BASE ]]-tbOrçamento[[#This Row],[VALOR CONTRATADO]] -> 5000 | H52: =SUMIFS(tbContratos[VALOR MEDIDO],tbContratos[OBRA],tbOrçamento[[#This Row],[OBRA]],tbContratos[SUBDISCIPLINA],tbOrçamento[[#This Row],[SUBDISCIPLINA]]) -> 0 | I52: =tbOrçamento[[#This Row],[VALOR CONTRATADO]]-tbOrçamento[[#This Row],[VALOR MEDIDO]] -> 0 | J52: A contratar
A53: PQSUL | B53: =_xlfn.XLOOKUP(tbOrçamento[[#This Row],[OBRA]],tbObras[CÓDIGO],tbObras[NOME],"Não encontrado",0) -> Parque Sul | C53: COMPLEMENTARES | D53: COMPLEMENTARES | E53: 188700 | F53: =SUMIFS(tbContratos[VALOR CONTRATO],tbContratos[OBRA],tbOrçamento[[#This Row],[OBRA]],tbContratos[SUBDISCIPLINA],tbOrçamento[[#This Row],[SUBDISCIPLINA]]) -> 179500 | G53: =tbOrçamento[[#This Row],[ORÇAMENTO BASE ]]-tbOrçamento[[#This Row],[VALOR CONTRATADO]] -> 9200 | H53: =SUMIFS(tbContratos[VALOR MEDIDO],tbContratos[OBRA],tbOrçamento[[#This Row],[OBRA]],tbContratos[SUBDISCIPLINA],tbOrçamento[[#This Row],[SUBDISCIPLINA]]) -> 53850 | I53: =tbOrçamento[[#This Row],[VALOR CONTRATADO]]-tbOrçamento[[#This Row],[VALOR MEDIDO]] -> 125650 | J53: Contratado
... A62: PQSUL | B62: =_xlfn.XLOOKUP(tbOrçamento[[#This Row],[OBRA]],tbObras[CÓDIGO],tbObras[NOME],"Não encontrado",0) -> Parque Sul | C62: INFRAESTRUTURA | D62: INTERLIGAÇÃO ELÉTRICA | E62: 10000 | F62: =SUMIFS(tbContratos[VALOR CONTRATO],tbContratos[OBRA],tbOrçamento[[#This Row],[OBRA]],tbContratos[SUBDISCIPLINA],tbOrçamento[[#This Row],[SUBDISCIPLINA]]) -> 0 | G62: =tbOrçamento[[#This Row],[ORÇAMENTO BASE ]]-tbOrçamento[[#This Row],[VALOR CONTRATADO]] -> 10000 | H62: =SUMIFS(tbContratos[VALOR MEDIDO],tbContratos[OBRA],tbOrçamento[[#This Row],[OBRA]],tbContratos[SUBDISCIPLINA],tbOrçamento[[#This Row],[SUBDISCIPLINA]]) -> 0 | I62: =tbOrçamento[[#This Row],[VALOR CONTRATADO]]-tbOrçamento[[#This Row],[VALOR MEDIDO]] -> 0 | J62: A contratar
A63: PQSUL | B63: =_xlfn.XLOOKUP(tbOrçamento[[#This Row],[OBRA]],tbObras[CÓDIGO],tbObras[NOME],"Não encontrado",0) -> Parque Sul | C63: INFRAESTRUTURA | D63: PROLONGAMENTO REDE | F63: =SUMIFS(tbContratos[VALOR CONTRATO],tbContratos[OBRA],tbOrçamento[[#This Row],[OBRA]],tbContratos[SUBDISCIPLINA],tbOrçamento[[#This Row],[SUBDISCIPLINA]]) -> 0 | G63: =tbOrçamento[[#This Row],[ORÇAMENTO BASE ]]-tbOrçamento[[#This Row],[VALOR CONTRATADO]] -> 0 | H63: =SUMIFS(tbContratos[VALOR MEDIDO],tbContratos[OBRA],tbOrçamento[[#This Row],[OBRA]],tbContratos[SUBDISCIPLINA],tbOrçamento[[#This Row],[SUBDISCIPLINA]]) -> 0 | I63: =tbOrçamento[[#This Row],[VALOR CONTRATADO]]-tbOrçamento[[#This Row],[VALOR MEDIDO]] -> 0 | J63: A contratar
A64: PQSUL | B64: =_xlfn.XLOOKUP(tbOrçamento[[#This Row],[OBRA]],tbObras[CÓDIGO],tbObras[NOME],"Não encontrado",0) -> Parque Sul | C64: ORÇAMENTO | D64: PARAMÉTRICO | E64: 10000 | F64: =SUMIFS(tbContratos[VALOR CONTRATO],tbContratos[OBRA],tbOrçamento[[#This Row],[OBRA]],tbContratos[SUBDISCIPLINA],tbOrçamento[[#This Row],[SUBDISCIPLINA]]) -> 12429.45 | G64: =tbOrçamento[[#This Row],[ORÇAMENTO BASE ]]-tbOrçamento[[#This Row],[VALOR CONTRATADO]] -> -2429.45 | H64: =SUMIFS(tbContratos[VALOR MEDIDO],tbContratos[OBRA],tbOrçamento[[#This Row],[OBRA]],tbContratos[SUBDISCIPLINA],tbOrçamento[[#This Row],[SUBDISCIPLINA]]) -> 3728.835 | I64: =tbOrçamento[[#This Row],[VALOR CONTRATADO]]-tbOrçamento[[#This Row],[VALOR MEDIDO]] -> 8700.615 | J64: Contratado
A65: PQSUL | B65: =_xlfn.XLOOKUP(tbOrçamento[[#This Row],[OBRA]],tbObras[CÓDIGO],tbObras[NOME],"Não encontrado",0) -> Parque Sul | C65: ORÇAMENTO | D65: EXECUTIVO | E65: 30000 | F65: =SUMIFS(tbContratos[VALOR CONTRATO],tbContratos[OBRA],tbOrçamento[[#This Row],[OBRA]],tbContratos[SUBDISCIPLINA],tbOrçamento[[#This Row],[SUBDISCIPLINA]]) -> 0 | G65: =tbOrçamento[[#This Row],[ORÇAMENTO BASE ]]-tbOrçamento[[#This Row],[VALOR CONTRATADO]] -> 30000 | H65: =SUMIFS(tbContratos[VALOR MEDIDO],tbContratos[OBRA],tbOrçamento[[#This Row],[OBRA]],tbContratos[SUBDISCIPLINA],tbOrçamento[[#This Row],[SUBDISCIPLINA]]) -> 0 | I65: =tbOrçamento[[#This Row],[VALOR CONTRATADO]]-tbOrçamento[[#This Row],[VALOR MEDIDO]] -> 0 | J65: A contratar
A66: PQSUL | B66: =_xlfn.XLOOKUP(tbOrçamento[[#This Row],[OBRA]],tbObras[CÓDIGO],tbObras[NOME],"Não encontrado",0) -> Parque Sul | C66: PLANEJAMENTO | D66: EXECUTIVO | E66: 20000 | F66: =SUMIFS(tbContratos[VALOR CONTRATO],tbContratos[OBRA],tbOrçamento[[#This Row],[OBRA]],tbContratos[SUBDISCIPLINA],tbOrçamento[[#This Row],[SUBDISCIPLINA]]) -> 0 | G66: =tbOrçamento[[#This Row],[ORÇAMENTO BASE ]]-tbOrçamento[[#This Row],[VALOR CONTRATADO]] -> 20000 | H66: =SUMIFS(tbContratos[VALOR MEDIDO],tbContratos[OBRA],tbOrçamento[[#This Row],[OBRA]],tbContratos[SUBDISCIPLINA],tbOrçamento[[#This Row],[SUBDISCIPLINA]]) -> 0 | I66: =tbOrçamento[[#This Row],[VALOR CONTRATADO]]-tbOrçamento[[#This Row],[VALOR MEDIDO]] -> 0 | J66: A contratar
A67: PQSUL | B67: =_xlfn.XLOOKUP(tbOrçamento[[#This Row],[OBRA]],tbObras[CÓDIGO],tbObras[NOME],"Não encontrado",0) -> Parque Sul | C67: LEGALIZAÇÃO | D67: LEGALIZAÇÃO | E67: 742740.9 | F67: =SUMIFS(tbContratos[VALOR CONTRATO],tbContratos[OBRA],tbOrçamento[[#This Row],[OBRA]],tbContratos[SUBDISCIPLINA],tbOrçamento[[#This Row],[SUBDISCIPLINA]]) -> 742740.9 | G67: =tbOrçamento[[#This Row],[ORÇAMENTO BASE ]]-tbOrçamento[[#This Row],[VALOR CONTRATADO]] -> 0 | H67: =SUMIFS(tbContratos[VALOR MEDIDO],tbContratos[OBRA],tbOrçamento[[#This Row],[OBRA]],tbContratos[SUBDISCIPLINA],tbOrçamento[[#This Row],[SUBDISCIPLINA]]) -> 7125 | I67: =tbOrçamento[[#This Row],[VALOR CONTRATADO]]-tbOrçamento[[#This Row],[VALOR MEDIDO]] -> 735615.9 | J67: A contratar
A68: UNA | B68: =_xlfn.XLOOKUP(tbOrçamento[[#This Row],[OBRA]],tbObras[CÓDIGO],tbObras[NOME],"Não encontrado",0) -> UNA | C68: SONDAGEM | D68: SONDAGEM | E68: 20000 | F68: =SUMIFS(tbContratos[VALOR CONTRATO],tbContratos[OBRA],tbOrçamento[[#This Row],[OBRA]],tbContratos[SUBDISCIPLINA],tbOrçamento[[#This Row],[SUBDISCIPLINA]]) -> 0 | G68: =tbOrçamento[[#This Row],[ORÇAMENTO BASE ]]-tbOrçamento[[#This Row],[VALOR CONTRATADO]] -> 20000 | H68: =SUMIFS(tbContratos[VALOR MEDIDO],tbContratos[OBRA],tbOrçamento[[#This Row],[OBRA]],tbContratos[SUBDISCIPLINA],tbOrçamento[[#This Row],[SUBDISCIPLINA]]) -> 0 | I68: =tbOrçamento[[#This Row],[VALOR CONTRATADO]]-tbOrçamento[[#This Row],[VALOR MEDIDO]] -> 0 | J68: Contratado
A69: UNA | B69: =_xlfn.XLOOKUP(tbOrçamento[[#This Row],[OBRA]],tbObras[CÓDIGO],tbObras[NOME],"Não encontrado",0) -> UNA | C69: PLANIALTIMÉTRICO | D69: PLANIALTIMÉTRICO | E69: 5000 | F69: =SUMIFS(tbContratos[VALOR CONTRATO],tbContratos[OBRA],tbOrçamento[[#This Row],[OBRA]],tbContratos[SUBDISCIPLINA],tbOrçamento[[#This Row],[SUBDISCIPLINA]]) -> 1100 | G69: =tbOrçamento[[#This Row],[ORÇAMENTO BASE ]]-tbOrçamento[[#This Row],[VALOR CONTRATADO]] -> 3900 | H69: =SUMIFS(tbContratos[VALOR MEDIDO],tbContratos[OBRA],tbOrçamento[[#This Row],[OBRA]],tbContratos[SUBDISCIPLINA],tbOrçamento[[#This Row],[SUBDISCIPLINA]]) -> 1100 | I69: =tbOrçamento[[#This Row],[VALOR CONTRATADO]]-tbOrçamento[[#This Row],[VALOR MEDIDO]] -> 0 | J69: Contratado
A70: UNA | B70: =_xlfn.XLOOKUP(tbOrçamento[[#This Row],[OBRA]],tbObras[CÓDIGO],tbObras[NOME],"Não encontrado",0) -> UNA | C70: ARQUITETURA | D70: ARQUITERURA LEGAL | E70: 40000 | F70: =SUMIFS(tbContratos[VALOR CONTRATO],tbContratos[OBRA],tbOrçamento[[#This Row],[OBRA]],tbContratos[SUBDISCIPLINA],tbOrçamento[[#This Row],[SUBDISCIPLINA]]) -> 40000 | G70: =tbOrçamento[[#This Row],[ORÇAMENTO BASE ]]-tbOrçamento[[#This Row],[VALOR CONTRATADO]] -> 0 | H70: =SUMIFS(tbContratos[VALOR MEDIDO],tbContratos[OBRA],tbOrçamento[[#This Row],[OBRA]],tbContratos[SUBDISCIPLINA],tbOrçamento[[#This Row],[SUBDISCIPLINA]]) -> 20000 | I70: =tbOrçamento[[#This Row],[VALOR CONTRATADO]]-tbOrçamento[[#This Row],[VALOR MEDIDO]] -> 20000 | J70: Contratado
A71: UNA | B71: =_xlfn.XLOOKUP(tbOrçamento[[#This Row],[OBRA]],tbObras[CÓDIGO],tbObras[NOME],"Não encontrado",0) -> UNA | C71: ESTRUTURA | D71: ESTRUTURA DE AÇO | E71: 15000 | F71: =SUMIFS(tbContratos[VALOR CONTRATO],tbContratos[OBRA],tbOrçamento[[#This Row],[OBRA]],tbContratos[SUBDISCIPLINA],tbOrçamento[[#This Row],[SUBDISCIPLINA]]) -> 13000 | G71: =tbOrçamento[[#This Row],[ORÇAMENTO BASE ]]-tbOrçamento[[#This Row],[VALOR CONTRATADO]] -> 2000 | H71: =SUMIFS(tbContratos[VALOR MEDIDO],tbContratos[OBRA],tbOrçamento[[#This Row],[OBRA]],tbContratos[SUBDISCIPLINA],tbOrçamento[[#This Row],[SUBDISCIPLINA]]) -> 6500 | I71: =tbOrçamento[[#This Row],[VALOR CONTRATADO]]-tbOrçamento[[#This Row],[VALOR MEDIDO]] -> 6500 | J71: Contratado
A72: UNA | B72: =_xlfn.XLOOKUP(tbOrçamento[[#This Row],[OBRA]],tbObras[CÓDIGO],tbObras[NOME],"Não encontrado",0) -> UNA | C72: FUNDAÇÃO | D72: FUNDAÇÃO PROFUNDA | E72: 10000 | F72: =SUMIFS(tbContratos[VALOR CONTRATO],tbContratos[OBRA],tbOrçamento[[#This Row],[OBRA]],tbContratos[SUBDISCIPLINA],tbOrçamento[[#This Row],[SUBDISCIPLINA]]) -> 10000 | G72: =tbOrçamento[[#This Row],[ORÇAMENTO BASE ]]-tbOrçamento[[#This Row],[VALOR CONTRATADO]] -> 0 | H72: =SUMIFS(tbContratos[VALOR MEDIDO],tbContratos[OBRA],tbOrçamento[[#This Row],[OBRA]],tbContratos[SUBDISCIPLINA],tbOrçamento[[#This Row],[SUBDISCIPLINA]]) -> 0 | I72: =tbOrçamento[[#This Row],[VALOR CONTRATADO]]-tbOrçamento[[#This Row],[VALOR MEDIDO]] -> 10000 | J72: Contratado
A73: UNA | B73: =_xlfn.XLOOKUP(tbOrçamento[[#This Row],[OBRA]],tbObras[CÓDIGO],tbObras[NOME],"Não encontrado",0) -> UNA | C73: FUNDAÇÃO | D73: FUNDAÇÃO SUPERFICIAL | E73: 1500 | F73: =SUMIFS(tbContratos[VALOR CONTRATO],tbContratos[OBRA],tbOrçamento[[#This Row],[OBRA]],tbContratos[SUBDISCIPLINA],tbOrçamento[[#This Row],[SUBDISCIPLINA]]) -> 16500 | G73: =tbOrçamento[[#This Row],[ORÇAMENTO BASE ]]-tbOrçamento[[#This Row],[VALOR CONTRATADO]] -> -15000 | H73: =SUMIFS(tbContratos[VALOR MEDIDO],tbContratos[OBRA],tbOrçamento[[#This Row],[OBRA]],tbContratos[SUBDISCIPLINA],tbOrçamento[[#This Row],[SUBDISCIPLINA]]) -> 0 | I73: =tbOrçamento[[#This Row],[VALOR CONTRATADO]]-tbOrçamento[[#This Row],[VALOR MEDIDO]] -> 16500 | J73: A contratar
A74: UNA | B74: =_xlfn.XLOOKUP(tbOrçamento[[#This Row],[OBRA]],tbObras[CÓDIGO],tbObras[NOME],"Não encontrado",0) -> UNA | C74: FUNDAÇÃO | D74: CONTENÇÕES | E74: 1500 | F74: =SUMIFS(tbContratos[VALOR CONTRATO],tbContratos[OBRA],tbOrçamento[[#This Row],[OBRA]],tbContratos[SUBDISCIPLINA],tbOrçamento[[#This Row],[SUBDISCIPLINA]]) -> 0 | G74: =tbOrçamento[[#This Row],[ORÇAMENTO BASE ]]-tbOrçamento[[#This Row],[VALOR CONTRATADO]] -> 1500 | H74: =SUMIFS(tbContratos[VALOR MEDIDO],tbContratos[OBRA],tbOrçamento[[#This Row],[OBRA]],tbContratos[SUBDISCIPLINA],tbOrçamento[[#This Row],[SUBDISCIPLINA]]) -> 0 | I74: =tbOrçamento[[#This Row],[VALOR CONTRATADO]]-tbOrçamento[[#This Row],[VALOR MEDIDO]] -> 0 | J74: A contratar
A75: UNA | B75: =_xlfn.XLOOKUP(tbOrçamento[[#This Row],[OBRA]],tbObras[CÓDIGO],tbObras[NOME],"Não encontrado",0) -> UNA | C75: FUNDAÇÃO | D75: PISO SUBSOLO | E75: 1500 | F75: =SUMIFS(tbContratos[VALOR CONTRATO],tbContratos[OBRA],tbOrçamento[[#This Row],[OBRA]],tbContratos[SUBDISCIPLINA],tbOrçamento[[#This Row],[SUBDISCIPLINA]]) -> 0 | G75: =tbOrçamento[[#This Row],[ORÇAMENTO BASE ]]-tbOrçamento[[#This Row],[VALOR CONTRATADO]] -> 1500 | H75: =SUMIFS(tbContratos[VALOR MEDIDO],tbContratos[OBRA],tbOrçamento[[#This Row],[OBRA]],tbContratos[SUBDISCIPLINA],tbOrçamento[[#This Row],[SUBDISCIPLINA]]) -> 0 | I75: =tbOrçamento[[#This Row],[VALOR CONTRATADO]]-tbOrçamento[[#This Row],[VALOR MEDIDO]] -> 0 | J75: A contratar
... A84: UNA | B84: =_xlfn.XLOOKUP(tbOrçamento[[#This Row],[OBRA]],tbObras[CÓDIGO],tbObras[NOME],"Não encontrado",0) -> UNA | C84: INFRAESTRUTURA | D84: INTERLIGAÇÃO ELÉTRICA | E84: 10000 | F84: =SUMIFS(tbContratos[VALOR CONTRATO],tbContratos[OBRA],tbOrçamento[[#This Row],[OBRA]],tbContratos[SUBDISCIPLINA],tbOrçamento[[#This Row],[SUBDISCIPLINA]]) -> 0 | G84: =tbOrçamento[[#This Row],[ORÇAMENTO BASE ]]-tbOrçamento[[#This Row],[VALOR CONTRATADO]] -> 10000 | H84: =SUMIFS(tbContratos[VALOR MEDIDO],tbContratos[OBRA],tbOrçamento[[#This Row],[OBRA]],tbContratos[SUBDISCIPLINA],tbOrçamento[[#This Row],[SUBDISCIPLINA]]) -> 0 | I84: =tbOrçamento[[#This Row],[VALOR CONTRATADO]]-tbOrçamento[[#This Row],[VALOR MEDIDO]] -> 0 | J84: A contratar
A85: UNA | B85: =_xlfn.XLOOKUP(tbOrçamento[[#This Row],[OBRA]],tbObras[CÓDIGO],tbObras[NOME],"Não encontrado",0) -> UNA | C85: INFRAESTRUTURA | D85: PROLONGAMENTO REDE | F85: =SUMIFS(tbContratos[VALOR CONTRATO],tbContratos[OBRA],tbOrçamento[[#This Row],[OBRA]],tbContratos[SUBDISCIPLINA],tbOrçamento[[#This Row],[SUBDISCIPLINA]]) -> 0 | G85: =tbOrçamento[[#This Row],[ORÇAMENTO BASE ]]-tbOrçamento[[#This Row],[VALOR CONTRATADO]] -> 0 | H85: =SUMIFS(tbContratos[VALOR MEDIDO],tbContratos[OBRA],tbOrçamento[[#This Row],[OBRA]],tbContratos[SUBDISCIPLINA],tbOrçamento[[#This Row],[SUBDISCIPLINA]]) -> 0 | I85: =tbOrçamento[[#This Row],[VALOR CONTRATADO]]-tbOrçamento[[#This Row],[VALOR MEDIDO]] -> 0 | J85: A contratar
A86: UNA | B86: =_xlfn.XLOOKUP(tbOrçamento[[#This Row],[OBRA]],tbObras[CÓDIGO],tbObras[NOME],"Não encontrado",0) -> UNA | C86: ORÇAMENTO | D86: PARAMÉTRICO | E86: 10000 | F86: =SUMIFS(tbContratos[VALOR CONTRATO],tbContratos[OBRA],tbOrçamento[[#This Row],[OBRA]],tbContratos[SUBDISCIPLINA],tbOrçamento[[#This Row],[SUBDISCIPLINA]]) -> 8255.14 | G86: =tbOrçamento[[#This Row],[ORÇAMENTO BASE ]]-tbOrçamento[[#This Row],[VALOR CONTRATADO]] -> 1744.86 | H86: =SUMIFS(tbContratos[VALOR MEDIDO],tbContratos[OBRA],tbOrçamento[[#This Row],[OBRA]],tbContratos[SUBDISCIPLINA],tbOrçamento[[#This Row],[SUBDISCIPLINA]]) -> 2476.542 | I86: =tbOrçamento[[#This Row],[VALOR CONTRATADO]]-tbOrçamento[[#This Row],[VALOR MEDIDO]] -> 5778.598 | J86: Contratado
A87: UNA | B87: =_xlfn.XLOOKUP(tbOrçamento[[#This Row],[OBRA]],tbObras[CÓDIGO],tbObras[NOME],"Não encontrado",0) -> UNA | C87: ORÇAMENTO | D87: EXECUTIVO | E87: 15000 | F87: =SUMIFS(tbContratos[VALOR CONTRATO],tbContratos[OBRA],tbOrçamento[[#This Row],[OBRA]],tbContratos[SUBDISCIPLINA],tbOrçamento[[#This Row],[SUBDISCIPLINA]]) -> 0 | G87: =tbOrçamento[[#This Row],[ORÇAMENTO BASE ]]-tbOrçamento[[#This Row],[VALOR CONTRATADO]] -> 15000 | H87: =SUMIFS(tbContratos[VALOR MEDIDO],tbContratos[OBRA],tbOrçamento[[#This Row],[OBRA]],tbContratos[SUBDISCIPLINA],tbOrçamento[[#This Row],[SUBDISCIPLINA]]) -> 0 | I87: =tbOrçamento[[#This Row],[VALOR CONTRATADO]]-tbOrçamento[[#This Row],[VALOR MEDIDO]] -> 0 | J87: A contratar
A88: UNA | B88: =_xlfn.XLOOKUP(tbOrçamento[[#This Row],[OBRA]],tbObras[CÓDIGO],tbObras[NOME],"Não encontrado",0) -> UNA | C88: PLANEJAMENTO | D88: EXECUTIVO | E88: 5000 | F88: =SUMIFS(tbContratos[VALOR CONTRATO],tbContratos[OBRA],tbOrçamento[[#This Row],[OBRA]],tbContratos[SUBDISCIPLINA],tbOrçamento[[#This Row],[SUBDISCIPLINA]]) -> 0 | G88: =tbOrçamento[[#This Row],[ORÇAMENTO BASE ]]-tbOrçamento[[#This Row],[VALOR CONTRATADO]] -> 5000 | H88: =SUMIFS(tbContratos[VALOR MEDIDO],tbContratos[OBRA],tbOrçamento[[#This Row],[OBRA]],tbContratos[SUBDISCIPLINA],tbOrçamento[[#This Row],[SUBDISCIPLINA]]) -> 0 | I88: =tbOrçamento[[#This Row],[VALOR CONTRATADO]]-tbOrçamento[[#This Row],[VALOR MEDIDO]] -> 0 | J88: A contratar
A89: UNA | B89: =_xlfn.XLOOKUP(tbOrçamento[[#This Row],[OBRA]],tbObras[CÓDIGO],tbObras[NOME],"Não encontrado",0) -> UNA | C89: LEGALIZAÇÃO | D89: LEGALIZAÇÃO | E89: 250584 | F89: =SUMIFS(tbContratos[VALOR CONTRATO],tbContratos[OBRA],tbOrçamento[[#This Row],[OBRA]],tbContratos[SUBDISCIPLINA],tbOrçamento[[#This Row],[SUBDISCIPLINA]]) -> 250584 | G89: =tbOrçamento[[#This Row],[ORÇAMENTO BASE ]]-tbOrçamento[[#This Row],[VALOR CONTRATADO]] -> 0 | H89: =SUMIFS(tbContratos[VALOR MEDIDO],tbContratos[OBRA],tbOrçamento[[#This Row],[OBRA]],tbContratos[SUBDISCIPLINA],tbOrçamento[[#This Row],[SUBDISCIPLINA]]) -> 10610.93 | I89: =tbOrçamento[[#This Row],[VALOR CONTRATADO]]-tbOrçamento[[#This Row],[VALOR MEDIDO]] -> 239973.07 | J89: A contratar
A90: LIB | B90: =_xlfn.XLOOKUP(tbOrçamento[[#This Row],[OBRA]],tbObras[CÓDIGO],tbObras[NOME],"Não encontrado",0) -> Liberdade | C90: SONDAGEM | D90: SONDAGEM | E90: 35000 | F90: =SUMIFS(tbContratos[VALOR CONTRATO],tbContratos[OBRA],tbOrçamento[[#This Row],[OBRA]],tbContratos[SUBDISCIPLINA],tbOrçamento[[#This Row],[SUBDISCIPLINA]]) -> 0 | G90: =tbOrçamento[[#This Row],[ORÇAMENTO BASE ]]-tbOrçamento[[#This Row],[VALOR CONTRATADO]] -> 35000 | H90: =SUMIFS(tbContratos[VALOR MEDIDO],tbContratos[OBRA],tbOrçamento[[#This Row],[OBRA]],tbContratos[SUBDISCIPLINA],tbOrçamento[[#This Row],[SUBDISCIPLINA]]) -> 0 | I90: =tbOrçamento[[#This Row],[VALOR CONTRATADO]]-tbOrçamento[[#This Row],[VALOR MEDIDO]] -> 0 | J90: Contratado
A91: LIB | B91: =_xlfn.XLOOKUP(tbOrçamento[[#This Row],[OBRA]],tbObras[CÓDIGO],tbObras[NOME],"Não encontrado",0) -> Liberdade | C91: PLANIALTIMÉTRICO | D91: PLANIALTIMÉTRICO | E91: 5000 | F91: =SUMIFS(tbContratos[VALOR CONTRATO],tbContratos[OBRA],tbOrçamento[[#This Row],[OBRA]],tbContratos[SUBDISCIPLINA],tbOrçamento[[#This Row],[SUBDISCIPLINA]]) -> 0 | G91: =tbOrçamento[[#This Row],[ORÇAMENTO BASE ]]-tbOrçamento[[#This Row],[VALOR CONTRATADO]] -> 5000 | H91: =SUMIFS(tbContratos[VALOR MEDIDO],tbContratos[OBRA],tbOrçamento[[#This Row],[OBRA]],tbContratos[SUBDISCIPLINA],tbOrçamento[[#This Row],[SUBDISCIPLINA]]) -> 0 | I91: =tbOrçamento[[#This Row],[VALOR CONTRATADO]]-tbOrçamento[[#This Row],[VALOR MEDIDO]] -> 0 | J91: Contratado
A92: LIB | B92: =_xlfn.XLOOKUP(tbOrçamento[[#This Row],[OBRA]],tbObras[CÓDIGO],tbObras[NOME],"Não encontrado",0) -> Liberdade | C92: ARQUITETURA | D92: ARQUITERURA LEGAL | E92: 78000 | F92: =SUMIFS(tbContratos[VALOR CONTRATO],tbContratos[OBRA],tbOrçamento[[#This Row],[OBRA]],tbContratos[SUBDISCIPLINA],tbOrçamento[[#This Row],[SUBDISCIPLINA]]) -> 78000 | G92: =tbOrçamento[[#This Row],[ORÇAMENTO BASE ]]-tbOrçamento[[#This Row],[VALOR CONTRATADO]] -> 0 | H92: =SUMIFS(tbContratos[VALOR MEDIDO],tbContratos[OBRA],tbOrçamento[[#This Row],[OBRA]],tbContratos[SUBDISCIPLINA],tbOrçamento[[#This Row],[SUBDISCIPLINA]]) -> 23400 | I92: =tbOrçamento[[#This Row],[VALOR CONTRATADO]]-tbOrçamento[[#This Row],[VALOR MEDIDO]] -> 54600 | J92: Contratado
A93: LIB | B93: =_xlfn.XLOOKUP(tbOrçamento[[#This Row],[OBRA]],tbObras[CÓDIGO],tbObras[NOME],"Não encontrado",0) -> Liberdade | C93: ARQUITETURA | D93: ARQUITETURA EXECUTIVA | E93: 2000 | F93: =SUMIFS(tbContratos[VALOR CONTRATO],tbContratos[OBRA],tbOrçamento[[#This Row],[OBRA]],tbContratos[SUBDISCIPLINA],tbOrçamento[[#This Row],[SUBDISCIPLINA]]) -> 0 | G93: =tbOrçamento[[#This Row],[ORÇAMENTO BASE ]]-tbOrçamento[[#This Row],[VALOR CONTRATADO]] -> 2000 | H93: =SUMIFS(tbContratos[VALOR MEDIDO],tbContratos[OBRA],tbOrçamento[[#This Row],[OBRA]],tbContratos[SUBDISCIPLINA],tbOrçamento[[#This Row],[SUBDISCIPLINA]]) -> 0 | I93: =tbOrçamento[[#This Row],[VALOR CONTRATADO]]-tbOrçamento[[#This Row],[VALOR MEDIDO]] -> 0 | J93: Cancelado
A94: LIB | B94: =_xlfn.XLOOKUP(tbOrçamento[[#This Row],[OBRA]],tbObras[CÓDIGO],tbObras[NOME],"Não encontrado",0) -> Liberdade | C94: ESTRUTURA | D94: ESTRUTURA DE CONCRETO | E94: 66000 | F94: =SUMIFS(tbContratos[VALOR CONTRATO],tbContratos[OBRA],tbOrçamento[[#This Row],[OBRA]],tbContratos[SUBDISCIPLINA],tbOrçamento[[#This Row],[SUBDISCIPLINA]]) -> 0 | G94: =tbOrçamento[[#This Row],[ORÇAMENTO BASE ]]-tbOrçamento[[#This Row],[VALOR CONTRATADO]] -> 66000 | H94: =SUMIFS(tbContratos[VALOR MEDIDO],tbContratos[OBRA],tbOrçamento[[#This Row],[OBRA]],tbContratos[SUBDISCIPLINA],tbOrçamento[[#This Row],[SUBDISCIPLINA]]) -> 0 | I94: =tbOrçamento[[#This Row],[VALOR CONTRATADO]]-tbOrçamento[[#This Row],[VALOR MEDIDO]] -> 0 | J94: Cancelado
A95: LIB | B95: =_xlfn.XLOOKUP(tbOrçamento[[#This Row],[OBRA]],tbObras[CÓDIGO],tbObras[NOME],"Não encontrado",0) -> Liberdade | C95: FUNDAÇÃO | D95: FUNDAÇÃO PROFUNDA | E95: 15800 | F95: =SUMIFS(tbContratos[VALOR CONTRATO],tbContratos[OBRA],tbOrçamento[[#This Row],[OBRA]],tbContratos[SUBDISCIPLINA],tbOrçamento[[#This Row],[SUBDISCIPLINA]]) -> 0 | G95: =tbOrçamento[[#This Row],[ORÇAMENTO BASE ]]-tbOrçamento[[#This Row],[VALOR CONTRATADO]] -> 15800 | H95: =SUMIFS(tbContratos[VALOR MEDIDO],tbContratos[OBRA],tbOrçamento[[#This Row],[OBRA]],tbContratos[SUBDISCIPLINA],tbOrçamento[[#This Row],[SUBDISCIPLINA]]) -> 0 | I95: =tbOrçamento[[#This Row],[VALOR CONTRATADO]]-tbOrçamento[[#This Row],[VALOR MEDIDO]] -> 0 | J95: Contratado
A96: LIB | B96: =_xlfn.XLOOKUP(tbOrçamento[[#This Row],[OBRA]],tbObras[CÓDIGO],tbObras[NOME],"Não encontrado",0) -> Liberdade | C96: FUNDAÇÃO | D96: PISO SUBSOLO | E96: 5000 | F96: =SUMIFS(tbContratos[VALOR CONTRATO],tbContratos[OBRA],tbOrçamento[[#This Row],[OBRA]],tbContratos[SUBDISCIPLINA],tbOrçamento[[#This Row],[SUBDISCIPLINA]]) -> 0 | G96: =tbOrçamento[[#This Row],[ORÇAMENTO BASE ]]-tbOrçamento[[#This Row],[VALOR CONTRATADO]] -> 5000 | H96: =SUMIFS(tbContratos[VALOR MEDIDO],tbContratos[OBRA],tbOrçamento[[#This Row],[OBRA]],tbContratos[SUBDISCIPLINA],tbOrçamento[[#This Row],[SUBDISCIPLINA]]) -> 0 | I96: =tbOrçamento[[#This Row],[VALOR CONTRATADO]]-tbOrçamento[[#This Row],[VALOR MEDIDO]] -> 0 | J96: Cancelado
A97: LIB | B97: =_xlfn.XLOOKUP(tbOrçamento[[#This Row],[OBRA]],tbObras[CÓDIGO],tbObras[NOME],"Não encontrado",0) -> Liberdade | C97: COMPLEMENTARES | D97: COMPLEMENTARES | E97: 90000 | F97: =SUMIFS(tbContratos[VALOR CONTRATO],tbContratos[OBRA],tbOrçamento[[#This Row],[OBRA]],tbContratos[SUBDISCIPLINA],tbOrçamento[[#This Row],[SUBDISCIPLINA]]) -> 0 | G97: =tbOrçamento[[#This Row],[ORÇAMENTO BASE ]]-tbOrçamento[[#This Row],[VALOR CONTRATADO]] -> 90000 | H97: =SUMIFS(tbContratos[VALOR MEDIDO],tbContratos[OBRA],tbOrçamento[[#This Row],[OBRA]],tbContratos[SUBDISCIPLINA],tbOrçamento[[#This Row],[SUBDISCIPLINA]]) -> 0 | I97: =tbOrçamento[[#This Row],[VALOR CONTRATADO]]-tbOrçamento[[#This Row],[VALOR MEDIDO]] -> 0 | J97: Cancelado
... A105: LIB | B105: =_xlfn.XLOOKUP(tbOrçamento[[#This Row],[OBRA]],tbObras[CÓDIGO],tbObras[NOME],"Não encontrado",0) -> Liberdade | C105: INFRAESTRUTURA | D105: INTERLIGAÇÃO ELÉTRICA | E105: 10000 | F105: =SUMIFS(tbContratos[VALOR CONTRATO],tbContratos[OBRA],tbOrçamento[[#This Row],[OBRA]],tbContratos[SUBDISCIPLINA],tbOrçamento[[#This Row],[SUBDISCIPLINA]]) -> 0 | G105: =tbOrçamento[[#This Row],[ORÇAMENTO BASE ]]-tbOrçamento[[#This Row],[VALOR CONTRATADO]] -> 10000 | H105: =SUMIFS(tbContratos[VALOR MEDIDO],tbContratos[OBRA],tbOrçamento[[#This Row],[OBRA]],tbContratos[SUBDISCIPLINA],tbOrçamento[[#This Row],[SUBDISCIPLINA]]) -> 0 | I105: =tbOrçamento[[#This Row],[VALOR CONTRATADO]]-tbOrçamento[[#This Row],[VALOR MEDIDO]] -> 0 | J105: Cancelado
A106: LIB | B106: =_xlfn.XLOOKUP(tbOrçamento[[#This Row],[OBRA]],tbObras[CÓDIGO],tbObras[NOME],"Não encontrado",0) -> Liberdade | C106: INFRAESTRUTURA | D106: PROLONGAMENTO REDE | F106: =SUMIFS(tbContratos[VALOR CONTRATO],tbContratos[OBRA],tbOrçamento[[#This Row],[OBRA]],tbContratos[SUBDISCIPLINA],tbOrçamento[[#This Row],[SUBDISCIPLINA]]) -> 0 | G106: =tbOrçamento[[#This Row],[ORÇAMENTO BASE ]]-tbOrçamento[[#This Row],[VALOR CONTRATADO]] -> 0 | H106: =SUMIFS(tbContratos[VALOR MEDIDO],tbContratos[OBRA],tbOrçamento[[#This Row],[OBRA]],tbContratos[SUBDISCIPLINA],tbOrçamento[[#This Row],[SUBDISCIPLINA]]) -> 0 | I106: =tbOrçamento[[#This Row],[VALOR CONTRATADO]]-tbOrçamento[[#This Row],[VALOR MEDIDO]] -> 0 | J106: Cancelado
A107: LIB | B107: =_xlfn.XLOOKUP(tbOrçamento[[#This Row],[OBRA]],tbObras[CÓDIGO],tbObras[NOME],"Não encontrado",0) -> Liberdade | C107: ORÇAMENTO | D107: PARAMÉTRICO | E107: 10000 | F107: =SUMIFS(tbContratos[VALOR CONTRATO],tbContratos[OBRA],tbOrçamento[[#This Row],[OBRA]],tbContratos[SUBDISCIPLINA],tbOrçamento[[#This Row],[SUBDISCIPLINA]]) -> 8067.11 | G107: =tbOrçamento[[#This Row],[ORÇAMENTO BASE ]]-tbOrçamento[[#This Row],[VALOR CONTRATADO]] -> 1932.89 | H107: =SUMIFS(tbContratos[VALOR MEDIDO],tbContratos[OBRA],tbOrçamento[[#This Row],[OBRA]],tbContratos[SUBDISCIPLINA],tbOrçamento[[#This Row],[SUBDISCIPLINA]]) -> 2420.133 | I107: =tbOrçamento[[#This Row],[VALOR CONTRATADO]]-tbOrçamento[[#This Row],[VALOR MEDIDO]] -> 5646.977 | J107: Contratado
A108: LIB | B108: =_xlfn.XLOOKUP(tbOrçamento[[#This Row],[OBRA]],tbObras[CÓDIGO],tbObras[NOME],"Não encontrado",0) -> Liberdade | C108: ORÇAMENTO | D108: EXECUTIVO | E108: 15000 | F108: =SUMIFS(tbContratos[VALOR CONTRATO],tbContratos[OBRA],tbOrçamento[[#This Row],[OBRA]],tbContratos[SUBDISCIPLINA],tbOrçamento[[#This Row],[SUBDISCIPLINA]]) -> 0 | G108: =tbOrçamento[[#This Row],[ORÇAMENTO BASE ]]-tbOrçamento[[#This Row],[VALOR CONTRATADO]] -> 15000 | H108: =SUMIFS(tbContratos[VALOR MEDIDO],tbContratos[OBRA],tbOrçamento[[#This Row],[OBRA]],tbContratos[SUBDISCIPLINA],tbOrçamento[[#This Row],[SUBDISCIPLINA]]) -> 0 | I108: =tbOrçamento[[#This Row],[VALOR CONTRATADO]]-tbOrçamento[[#This Row],[VALOR MEDIDO]] -> 0 | J108: Cancelado
A109: LIB | B109: =_xlfn.XLOOKUP(tbOrçamento[[#This Row],[OBRA]],tbObras[CÓDIGO],tbObras[NOME],"Não encontrado",0) -> Liberdade | C109: PLANEJAMENTO | D109: EXECUTIVO | E109: 5000 | F109: =SUMIFS(tbContratos[VALOR CONTRATO],tbContratos[OBRA],tbOrçamento[[#This Row],[OBRA]],tbContratos[SUBDISCIPLINA],tbOrçamento[[#This Row],[SUBDISCIPLINA]]) -> 0 | G109: =tbOrçamento[[#This Row],[ORÇAMENTO BASE ]]-tbOrçamento[[#This Row],[VALOR CONTRATADO]] -> 5000 | H109: =SUMIFS(tbContratos[VALOR MEDIDO],tbContratos[OBRA],tbOrçamento[[#This Row],[OBRA]],tbContratos[SUBDISCIPLINA],tbOrçamento[[#This Row],[SUBDISCIPLINA]]) -> 0 | I109: =tbOrçamento[[#This Row],[VALOR CONTRATADO]]-tbOrçamento[[#This Row],[VALOR MEDIDO]] -> 0 | J109: Cancelado
A110: LIB | B110: =_xlfn.XLOOKUP(tbOrçamento[[#This Row],[OBRA]],tbObras[CÓDIGO],tbObras[NOME],"Não encontrado",0) -> Liberdade | C110: LEGALIZAÇÃO | D110: LEGALIZAÇÃO | E110: 148572 | F110: =SUMIFS(tbContratos[VALOR CONTRATO],tbContratos[OBRA],tbOrçamento[[#This Row],[OBRA]],tbContratos[SUBDISCIPLINA],tbOrçamento[[#This Row],[SUBDISCIPLINA]]) -> 600 | G110: =tbOrçamento[[#This Row],[ORÇAMENTO BASE ]]-tbOrçamento[[#This Row],[VALOR CONTRATADO]] -> 147972 | H110: =SUMIFS(tbContratos[VALOR MEDIDO],tbContratos[OBRA],tbOrçamento[[#This Row],[OBRA]],tbContratos[SUBDISCIPLINA],tbOrçamento[[#This Row],[SUBDISCIPLINA]]) -> 0 | I110: =tbOrçamento[[#This Row],[VALOR CONTRATADO]]-tbOrçamento[[#This Row],[VALOR MEDIDO]] -> 600 | J110: Cancelado
A111: Total | E111: =SUBTOTAL(109,tbOrçamento[[ORÇAMENTO BASE ]]) -> 4903692.5 | F111: =SUBTOTAL(109,tbOrçamento[VALOR CONTRATADO]) -> 3845910.5 | G111: =SUBTOTAL(109,tbOrçamento[SALDO A CONTRATAR]) -> 1057782 | J111: =SUBTOTAL(103,tbOrçamento[[STATUS ]]) -> 109

Sheet tbContratos
A1: CONTRATO_ID | B1: NUM SIENGE | C1: EMPRESA | D1: OBRA | E1: DISCIPLINA | F1: SUBDISCIPLINA | G1: VALOR CONTRATO | H1: VALOR MEDIDO | I1: SALDO A MEDIR | J1: PERCENTUAL MEDIDO
A2: CT001 | B2: 95 | C2: SOMA | D2: ALT | E2: =_xlfn.XLOOKUP(tbContratos[[#This Row],[EMPRESA]],tbFornecedores[FORNECEDOR],tbFornecedores[TIPO],"Não encontrado") -> ARQUITETURA | F2: ARQUITERURA LEGAL | G2: 108000 | H2: =SUMIFS(tbMedições[VALOR MEDIÇÃO],tbMedições[CONTRATO_ID],tbContratos[[#This Row],[CONTRATO_ID]],tbMedições[STATUS],"Pago")+SUMIFS(tbMedições[VALOR MEDIÇÃO],tbMedições[CONTRATO_ID],tbContratos[[#This Row],[CONTRATO_ID]],tbMedições[STATUS],"Medido") -> 102600 | I2: =tbContratos[[#This Row],[VALOR CONTRATO]]-tbContratos[[#This Row],[VALOR MEDIDO]] -> 5400 | J2: =tbContratos[[#This Row],[VALOR MEDIDO]]/tbContratos[[#This Row],[VALOR CONTRATO]] -> 0.95
A3: CT002 | B3: 593 | C3: SOMA | D3: GAL | E3: =_xlfn.XLOOKUP(tbContratos[[#This Row],[EMPRESA]],tbFornecedores[FORNECEDOR],tbFornecedores[TIPO],"Não encontrado") -> ARQUITETURA | F3: ARQUITERURA LEGAL | G3: 85680 | H3: =SUMIFS(tbMedições[VALOR MEDIÇÃO],tbMedições[CONTRATO_ID],tbContratos[[#This Row],[CONTRATO_ID]],tbMedições[STATUS],"Pago")+SUMIFS(tbMedições[VALOR MEDIÇÃO],tbMedições[CONTRATO_ID],tbContratos[[#This Row],[CONTRATO_ID]],tbMedições[STATUS],"Medido") -> 47124 | I3: =tbContratos[[#This Row],[VALOR CONTRATO]]-tbContratos[[#This Row],[VALOR MEDIDO]] -> 38556 | J3: =tbContratos[[#This Row],[VALOR MEDIDO]]/tbContratos[[#This Row],[VALOR CONTRATO]] -> 0.55
A4: CT003 | B4: 355 | C4: SOMA | D4: PQSUL | E4: =_xlfn.XLOOKUP(tbContratos[[#This Row],[EMPRESA]],tbFornecedores[FORNECEDOR],tbFornecedores[TIPO],"Não encontrado") -> ARQUITETURA | F4: ARQUITERURA LEGAL | G4: 160000 | H4: =SUMIFS(tbMedições[VALOR MEDIÇÃO],tbMedições[CONTRATO_ID],tbContratos[[#This Row],[CONTRATO_ID]],tbMedições[STATUS],"Pago")+SUMIFS(tbMedições[VALOR MEDIÇÃO],tbMedições[CONTRATO_ID],tbContratos[[#This Row],[CONTRATO_ID]],tbMedições[STATUS],"Medido") -> 64000 | I4: =tbContratos[[#This Row],[VALOR CONTRATO]]-tbContratos[[#This Row],[VALOR MEDIDO]] -> 96000 | J4: =tbContratos[[#This Row],[VALOR MEDIDO]]/tbContratos[[#This Row],[VALOR CONTRATO]] -> 0.4
A5: CT004 | B5: 42 | C5: SOMA | D5: LIB | E5: =_xlfn.XLOOKUP(tbContratos[[#This Row],[EMPRESA]],tbFornecedores[FORNECEDOR],tbFornecedores[TIPO],"Não encontrado") -> ARQUITETURA | F5: ARQUITERURA LEGAL | G5: 78000 | H5: =SUMIFS(tbMedições[VALOR MEDIÇÃO],tbMedições[CONTRATO_ID],tbContratos[[#This Row],[CONTRATO_ID]],tbMedições[STATUS],"Pago")+SUMIFS(tbMedições[VALOR MEDIÇÃO],tbMedições[CONTRATO_ID],tbContratos[[#This Row],[CONTRATO_ID]],tbMedições[STATUS],"Medido") -> 23400 | I5: =tbContratos[[#This Row],[VALOR CONTRATO]]-tbContratos[[#This Row],[VALOR MEDIDO]] -> 54600 | J5: =tbContratos[[#This Row],[VALOR MEDIDO]]/tbContratos[[#This Row],[VALOR CONTRATO]] -> 0.3
A6: CT005 | B6: 240 | C6: MBUIATE | D6: ALT | E6: =_xlfn.XLOOKUP(tbContratos[[#This Row],[EMPRESA]],tbFornecedores[FORNECEDOR],tbFornecedores[TIPO],"Não encontrado") -> ESTRUTURA | F6: ESTRUTURA DE CONCRETO | G6: 90000 | H6: =SUMIFS(tbMedições[VALOR MEDIÇÃO],tbMedições[CONTRATO_ID],tbContratos[[#This Row],[CONTRATO_ID]],tbMedições[STATUS],"Pago")+SUMIFS(tbMedições[VALOR MEDIÇÃO],tbMedições[CONTRATO_ID],tbContratos[[#This Row],[CONTRATO_ID]],tbMedições[STATUS],"Medido") -> 18000 | I6: =tbContratos[[#This Row],[VALOR CONTRATO]]-tbContratos[[#This Row],[VALOR MEDIDO]] -> 72000 | J6: =tbContratos[[#This Row],[VALOR MEDIDO]]/tbContratos[[#This Row],[VALOR CONTRATO]] -> 0.2
A7: CT006 | B7: 594 | C7: MBUIATE | D7: GAL | E7: =_xlfn.XLOOKUP(tbContratos[[#This Row],[EMPRESA]],tbFornecedores[FORNECEDOR],tbFornecedores[TIPO],"Não encontrado") -> ESTRUTURA | F7: ESTRUTURA DE CONCRETO | G7: 100000 | H7: =SUMIFS(tbMedições[VALOR MEDIÇÃO],tbMedições[CONTRATO_ID],tbContratos[[#This Row],[CONTRATO_ID]],tbMedições[STATUS],"Pago")+SUMIFS(tbMedições[VALOR MEDIÇÃO],tbMedições[CONTRATO_ID],tbContratos[[#This Row],[CONTRATO_ID]],tbMedições[STATUS],"Medido") -> 15000 | I7: =tbContratos[[#This Row],[VALOR CONTRATO]]-tbContratos[[#This Row],[VALOR MEDIDO]] -> 85000 | J7: =tbContratos[[#This Row],[VALOR MEDIDO]]/tbContratos[[#This Row],[VALOR CONTRATO]] -> 0.15
A8: CT007 | B8: 484 | C8: MBUIATE | D8: PQSUL | E8: =_xlfn.XLOOKUP(tbContratos[[#This Row],[EMPRESA]],tbFornecedores[FORNECEDOR],tbFornecedores[TIPO],"Não encontrado") -> ESTRUTURA | F8: ESTRUTURA DE CONCRETO | G8: 210000 | H8: =SUMIFS(tbMedições[VALOR MEDIÇÃO],tbMedições[CONTRATO_ID],tbContratos[[#This Row],[CONTRATO_ID]],tbMedições[STATUS],"Pago")+SUMIFS(tbMedições[VALOR MEDIÇÃO],tbMedições[CONTRATO_ID],tbContratos[[#This Row],[CONTRATO_ID]],tbMedições[STATUS],"Medido") -> 31500 | I8: =tbContratos[[#This Row],[VALOR CONTRATO]]-tbContratos[[#This Row],[VALOR MEDIDO]] -> 178500 | J8: =tbContratos[[#This Row],[VALOR MEDIDO]]/tbContratos[[#This Row],[VALOR CONTRATO]] -> 0.15
A9: CT008 | B9: 485 | C9: DALTON | D9: UNA | E9: =_xlfn.XLOOKUP(tbContratos[[#This Row],[EMPRESA]],tbFornecedores[FORNECEDOR],tbFornecedores[TIPO],"Não encontrado") -> INTERIORES | F9: INTERIORES | G9: 29000 | H9: =SUMIFS(tbMedições[VALOR MEDIÇÃO],tbMedições[CONTRATO_ID],tbContratos[[#This Row],[CONTRATO_ID]],tbMedições[STATUS],"Pago")+SUMIFS(tbMedições[VALOR MEDIÇÃO],tbMedições[CONTRATO_ID],tbContratos[[#This Row],[CONTRATO_ID]],tbMedições[STATUS],"Medido") -> 9404.1667 | I9: =tbContratos[[#This Row],[VALOR CONTRATO]]-tbContratos[[#This Row],[VALOR MEDIDO]] -> 19595.833 | J9: =tbContratos[[#This Row],[VALOR MEDIDO]]/tbContratos[[#This Row],[VALOR CONTRATO]] -> 0.32428161
A10: CT009 | B10: 595 | C10: DALTON | D10: GAL | E10: =_xlfn.XLOOKUP(tbContratos[[#This Row],[EMPRESA]],tbFornecedores[FORNECEDOR],tbFornecedores[TIPO],"Não encontrado") -> INTERIORES | F10: INTERIORES | G10: 70000 | H10: =SUMIFS(tbMedições[VALOR MEDIÇÃO],tbMedições[CONTRATO_ID],tbContratos[[#This Row],[CONTRATO_ID]],tbMedições[STATUS],"Pago")+SUMIFS(tbMedições[VALOR MEDIÇÃO],tbMedições[CONTRATO_ID],tbContratos[[#This Row],[CONTRATO_ID]],tbMedições[STATUS],"Medido") -> 14000 | I10: =tbContratos[[#This Row],[VALOR CONTRATO]]-tbContratos[[#This Row],[VALOR MEDIDO]] -> 56000 | J10: =tbContratos[[#This Row],[VALOR MEDIDO]]/tbContratos[[#This Row],[VALOR CONTRATO]] -> 0.2
A11: CT010 | B11: 310 | C11: KARINA | D11: ALT | E11: =_xlfn.XLOOKUP(tbContratos[[#This Row],[EMPRESA]],tbFornecedores[FORNECEDOR],tbFornecedores[TIPO],"Não encontrado") -> INTERIORES | F11: INTERIORES | G11: 39500 | H11: =SUMIFS(tbMedições[VALOR MEDIÇÃO],tbMedições[CONTRATO_ID],tbContratos[[#This Row],[CONTRATO_ID]],tbMedições[STATUS],"Pago")+SUMIFS(tbMedições[VALOR MEDIÇÃO],tbMedições[CONTRATO_ID],tbContratos[[#This Row],[CONTRATO_ID]],tbMedições[STATUS],"Medido") -> 20700 | I11: =tbContratos[[#This Row],[VALOR CONTRATO]]-tbContratos[[#This Row],[VALOR MEDIDO]] -> 18800 | J11: =tbContratos[[#This Row],[VALOR MEDIDO]]/tbContratos[[#This Row],[VALOR CONTRATO]] -> 0.52405063
A12: CT011 | B12: 451 | C12: GEOMETA | D12: ALT | E12: =_xlfn.XLOOKUP(tbContratos[[#This Row],[EMPRESA]],tbFornecedores[FORNECEDOR],tbFornecedores[TIPO],"Não encontrado") -> SONDAGEM | F12: SONDAGEM | G12: 17500.65 | H12: =SUMIFS(tbMedições[VALOR MEDIÇÃO],tbMedições[CONTRATO_ID],tbContratos[[#This Row],[CONTRATO_ID]],tbMedições[STATUS],"Pago")+SUMIFS(tbMedições[VALOR MEDIÇÃO],tbMedições[CONTRATO_ID],tbContratos[[#This Row],[CONTRATO_ID]],tbMedições[STATUS],"Medido") -> 17500.65 | I12: =tbContratos[[#This Row],[VALOR CONTRATO]]-tbContratos[[#This Row],[VALOR MEDIDO]] -> 0 | J12: =tbContratos[[#This Row],[VALOR MEDIDO]]/tbContratos[[#This Row],[VALOR CONTRATO]] -> 1
A13: CT012 | B13: 596 | C13: GEOMETA | D13: GAL | E13: =_xlfn.XLOOKUP(tbContratos[[#This Row],[EMPRESA]],tbFornecedores[FORNECEDOR],tbFornecedores[TIPO],"Não encontrado") -> SONDAGEM | F13: SONDAGEM | G13: 25313.28 | H13: =SUMIFS(tbMedições[VALOR MEDIÇÃO],tbMedições[CONTRATO_ID],tbContratos[[#This Row],[CONTRATO_ID]],tbMedições[STATUS],"Pago")+SUMIFS(tbMedições[VALOR MEDIÇÃO],tbMedições[CONTRATO_ID],tbContratos[[#This Row],[CONTRATO_ID]],tbMedições[STATUS],"Medido") -> 25313.28 | I13: =tbContratos[[#This Row],[VALOR CONTRATO]]-tbContratos[[#This Row],[VALOR MEDIDO]] -> 0 | J13: =tbContratos[[#This Row],[VALOR MEDIDO]]/tbContratos[[#This Row],[VALOR CONTRATO]] -> 1
... A18: CT017 | B18: 599 | C18: JP SERVIÇOS | D18: GAL | E18: =_xlfn.XLOOKUP(tbContratos[[#This Row],[EMPRESA]],tbFornecedores[FORNECEDOR],tbFornecedores[TIPO],"Não encontrado") -> SONDAGEM | F18: SONDAGEM | G18: 3640 | H18: =SUMIFS(tbMedições[VALOR MEDIÇÃO],tbMedições[CONTRATO_ID],tbContratos[[#This Row],[CONTRATO_ID]],tbMedições[STATUS],"Pago")+SUMIFS(tbMedições[VALOR MEDIÇÃO],tbMedições[CONTRATO_ID],tbContratos[[#This Row],[CONTRATO_ID]],tbMedições[STATUS],"Medido") -> 3640 | I18: =tbContratos[[#This Row],[VALOR CONTRATO]]-tbContratos[[#This Row],[VALOR MEDIDO]] -> 0 | J18: =tbContratos[[#This Row],[VALOR MEDIDO]]/tbContratos[[#This Row],[VALOR CONTRATO]] -> 1
A19: CT018 | C19: IDEAL | D19: ALT | E19: =_xlfn.XLOOKUP(tbContratos[[#This Row],[EMPRESA]],tbFornecedores[FORNECEDOR],tbFornecedores[TIPO],"Não encontrado") -> PLANIALTIMÉTRICO | F19: PLANIALTIMÉTRICO | G19: 4550 | H19: =SUMIFS(tbMedições[VALOR MEDIÇÃO],tbMedições[CONTRATO_ID],tbContratos[[#This Row],[CONTRATO_ID]],tbMedições[STATUS],"Pago")+SUMIFS(tbMedições[VALOR MEDIÇÃO],tbMedições[CONTRATO_ID],tbContratos[[#This Row],[CONTRATO_ID]],tbMedições[STATUS],"Medido") -> 4550 | I19: =tbContratos[[#This Row],[VALOR CONTRATO]]-tbContratos[[#This Row],[VALOR MEDIDO]] -> 0 | J19: =tbContratos[[#This Row],[VALOR MEDIDO]]/tbContratos[[#This Row],[VALOR CONTRATO]] -> 1
A20: CT019 | B20: 348 | C20: GEOMAP | D20: GAL | E20: =_xlfn.XLOOKUP(tbContratos[[#This Row],[EMPRESA]],tbFornecedores[FORNECEDOR],tbFornecedores[TIPO],"Não encontrado") -> PLANIALTIMÉTRICO | F20: PLANIALTIMÉTRICO | G20: 2850 | H20: =SUMIFS(tbMedições[VALOR MEDIÇÃO],tbMedições[CONTRATO_ID],tbContratos[[#This Row],[CONTRATO_ID]],tbMedições[STATUS],"Pago")+SUMIFS(tbMedições[VALOR MEDIÇÃO],tbMedições[CONTRATO_ID],tbContratos[[#This Row],[CONTRATO_ID]],tbMedições[STATUS],"Medido") -> 2850 | I20: =tbContratos[[#This Row],[VALOR CONTRATO]]-tbContratos[[#This Row],[VALOR MEDIDO]] -> 0 | J20: =tbContratos[[#This Row],[VALOR MEDIDO]]/tbContratos[[#This Row],[VALOR CONTRATO]] -> 1
A21: CT020 | B21: 348 | C21: GEOMAP | D21: PQSUL | E21: =_xlfn.XLOOKUP(tbContratos[[#This Row],[EMPRESA]],tbFornecedores[FORNECEDOR],tbFornecedores[TIPO],"Não encontrado") -> PLANIALTIMÉTRICO | F21: PLANIALTIMÉTRICO | G21: 1300 | H21: =SUMIFS(tbMedições[VALOR MEDIÇÃO],tbMedições[CONTRATO_ID],tbContratos[[#This Row],[CONTRATO_ID]],tbMedições[STATUS],"Pago")+SUMIFS(tbMedições[VALOR MEDIÇÃO],tbMedições[CONTRATO_ID],tbContratos[[#This Row],[CONTRATO_ID]],tbMedições[STATUS],"Medido") -> 1300 | I21: =tbContratos[[#This Row],[VALOR CONTRATO]]-tbContratos[[#This Row],[VALOR MEDIDO]] -> 0 | J21: =tbContratos[[#This Row],[VALOR MEDIDO]]/tbContratos[[#This Row],[VALOR CONTRATO]] -> 1
A22: CT021 | B22: 348 | C22: GEOMAP | D22: UNA | E22: =_xlfn.XLOOKUP(tbContratos[[#This Row],[EMPRESA]],tbFornecedores[FORNECEDOR],tbFornecedores[TIPO],"Não encontrado") -> PLANIALTIMÉTRICO | F22: PLANIALTIMÉTRICO | G22: 1100 | H22: =SUMIFS(tbMedições[VALOR MEDIÇÃO],tbMedições[CONTRATO_ID],tbContratos[[#This Row],[CONTRATO_ID]],tbMedições[STATUS],"Pago")+SUMIFS(tbMedições[VALOR MEDIÇÃO],tbMedições[CONTRATO_ID],tbContratos[[#This Row],[CONTRATO_ID]],tbMedições[STATUS],"Medido") -> 1100 | I22: =tbContratos[[#This Row],[VALOR CONTRATO]]-tbContratos[[#This Row],[VALOR MEDIDO]] -> 0 | J22: =tbContratos[[#This Row],[VALOR MEDIDO]]/tbContratos[[#This Row],[VALOR CONTRATO]] -> 1
A23: CT022 | B23: 348 | C23: GEOMAP | D23: STM | E23: =_xlfn.XLOOKUP(tbContratos[[#This Row],[EMPRESA]],tbFornecedores[FORNECEDOR],tbFornecedores[TIPO],"Não encontrado") -> PLANIALTIMÉTRICO | F23: PLANIALTIMÉTRICO | G23: 2635 | H23: =SUMIFS(tbMedições[VALOR MEDIÇÃO],tbMedições[CONTRATO_ID],tbContratos[[#This Row],[CONTRATO_ID]],tbMedições[STATUS],"Pago")+SUMIFS(tbMedições[VALOR MEDIÇÃO],tbMedições[CONTRATO_ID],tbContratos[[#This Row],[CONTRATO_ID]],tbMedições[STATUS],"Medido") -> 0 | I23: =tbContratos[[#This Row],[VALOR CONTRATO]]-tbContratos[[#This Row],[VALOR MEDIDO]] -> 2635 | J23: =tbContratos[[#This Row],[VALOR MEDIDO]]/tbContratos[[#This Row],[VALOR CONTRATO]] -> 0
A24: CT023 | B24: 348 | C24: GEOMAP | D24: SEFAZ | E24: =_xlfn.XLOOKUP(tbContratos[[#This Row],[EMPRESA]],tbFornecedores[FORNECEDOR],tbFornecedores[TIPO],"Não encontrado") -> PLANIALTIMÉTRICO | F24: PLANIALTIMÉTRICO | G24: 1800 | H24: =SUMIFS(tbMedições[VALOR MEDIÇÃO],tbMedições[CONTRATO_ID],tbContratos[[#This Row],[CONTRATO_ID]],tbMedições[STATUS],"Pago")+SUMIFS(tbMedições[VALOR MEDIÇÃO],tbMedições[CONTRATO_ID],tbContratos[[#This Row],[CONTRATO_ID]],tbMedições[STATUS],"Medido") -> 0 | I24: =tbContratos[[#This Row],[VALOR CONTRATO]]-tbContratos[[#This Row],[VALOR MEDIDO]] -> 1800 | J24: =tbContratos[[#This Row],[VALOR MEDIDO]]/tbContratos[[#This Row],[VALOR CONTRATO]] -> 0
A25: CT024 | B25: 344 | C25: GÊMEAS | D25: UNA | E25: =_xlfn.XLOOKUP(tbContratos[[#This Row],[EMPRESA]],tbFornecedores[FORNECEDOR],tbFornecedores[TIPO],"Não encontrado") -> ARQUITETURA | F25: ARQUITERURA LEGAL | G25: 40000 | H25: =SUMIFS(tbMedições[VALOR MEDIÇÃO],tbMedições[CONTRATO_ID],tbContratos[[#This Row],[CONTRATO_ID]],tbMedições[STATUS],"Pago")+SUMIFS(tbMedições[VALOR MEDIÇÃO],tbMedições[CONTRATO_ID],tbContratos[[#This Row],[CONTRATO_ID]],tbMedições[STATUS],"Medido") -> 20000 | I25: =tbContratos[[#This Row],[VALOR CONTRATO]]-tbContratos[[#This Row],[VALOR MEDIDO]] -> 20000 | J25: =tbContratos[[#This Row],[VALOR MEDIDO]]/tbContratos[[#This Row],[VALOR CONTRATO]] -> 0.5
A26: CT025 | B26: 296 | C26: EMMIG | D26: UNA | E26: =_xlfn.XLOOKUP(tbContratos[[#This Row],[EMPRESA]],tbFornecedores[FORNECEDOR],tbFornecedores[TIPO],"Não encontrado") -> ESTRUTURA | F26: ESTRUTURA DE AÇO | G26: 13000 | H26: =SUMIFS(tbMedições[VALOR MEDIÇÃO],tbMedições[CONTRATO_ID],tbContratos[[#This Row],[CONTRATO_ID]],tbMedições[STATUS],"Pago")+SUMIFS(tbMedições[VALOR MEDIÇÃO],tbMedições[CONTRATO_ID],tbContratos[[#This Row],[CONTRATO_ID]],tbMedições[STATUS],"Medido") -> 6500 | I26: =tbContratos[[#This Row],[VALOR CONTRATO]]-tbContratos[[#This Row],[VALOR MEDIDO]] -> 6500 | J26: =tbContratos[[#This Row],[VALOR MEDIDO]]/tbContratos[[#This Row],[VALOR CONTRATO]] -> 0.5
A27: CT026 | B27: 349 | C27: GEOMETRIA | D27: ALT | E27: =_xlfn.XLOOKUP(tbContratos[[#This Row],[EMPRESA]],tbFornecedores[FORNECEDOR],tbFornecedores[TIPO],"Não encontrado") -> FUNDAÇÃO | F27: FUNDAÇÃO PROFUNDA | G27: 25000 | H27: =SUMIFS(tbMedições[VALOR MEDIÇÃO],tbMedições[CONTRATO_ID],tbContratos[[#This Row],[CONTRATO_ID]],tbMedições[STATUS],"Pago")+SUMIFS(tbMedições[VALOR MEDIÇÃO],tbMedições[CONTRATO_ID],tbContratos[[#This Row],[CONTRATO_ID]],tbMedições[STATUS],"Medido") -> 0 | I27: =tbContratos[[#This Row],[VALOR CONTRATO]]-tbContratos[[#This Row],[VALOR MEDIDO]] -> 25000 | J27: =tbContratos[[#This Row],[VALOR MEDIDO]]/tbContratos[[#This Row],[VALOR CONTRATO]] -> 0
A28: CT027 | C28: GEOMETRIA | D28: GAL | E28: =_xlfn.XLOOKUP(tbContratos[[#This Row],[EMPRESA]],tbFornecedores[FORNECEDOR],tbFornecedores[TIPO],"Não encontrado") -> FUNDAÇÃO | F28: FUNDAÇÃO PROFUNDA | G28: 12000 | H28: =SUMIFS(tbMedições[VALOR MEDIÇÃO],tbMedições[CONTRATO_ID],tbContratos[[#This Row],[CONTRATO_ID]],tbMedições[STATUS],"Pago")+SUMIFS(tbMedições[VALOR MEDIÇÃO],tbMedições[CONTRATO_ID],tbContratos[[#This Row],[CONTRATO_ID]],tbMedições[STATUS],"Medido") -> 0 | I28: =tbContratos[[#This Row],[VALOR CONTRATO]]-tbContratos[[#This Row],[VALOR MEDIDO]] -> 12000 | J28: =tbContratos[[#This Row],[VALOR MEDIDO]]/tbContratos[[#This Row],[VALOR CONTRATO]] -> 0
A29: CT028 | B29: 349 | C29: GEOMETRIA | D29: PQSUL | E29: =_xlfn.XLOOKUP(tbContratos[[#This Row],[EMPRESA]],tbFornecedores[FORNECEDOR],tbFornecedores[TIPO],"Não encontrado") -> FUNDAÇÃO | F29: FUNDAÇÃO PROFUNDA | G29: 30000 | H29: =SUMIFS(tbMedições[VALOR MEDIÇÃO],tbMedições[CONTRATO_ID],tbContratos[[#This Row],[CONTRATO_ID]],tbMedições[STATUS],"Pago")+SUMIFS(tbMedições[VALOR MEDIÇÃO],tbMedições[CONTRATO_ID],tbContratos[[#This Row],[CONTRATO_ID]],tbMedições[STATUS],"Medido") -> 0 | I29: =tbContratos[[#This Row],[VALOR CONTRATO]]-tbContratos[[#This Row],[VALOR MEDIDO]] -> 30000 | J29: =tbContratos[[#This Row],[VALOR MEDIDO]]/tbContratos[[#This Row],[VALOR CONTRATO]] -> 0
A30: CT029 | B30: 349 | C30: GEOMETRIA | D30: UNA | E30: =_xlfn.XLOOKUP(tbContratos[[#This Row],[EMPRESA]],tbFornecedores[FORNECEDOR],tbFornecedores[TIPO],"Não encontrado") -> FUNDAÇÃO | F30: FUNDAÇÃO PROFUNDA | G30: 10000 | H30: =SUMIFS(tbMedições[VALOR MEDIÇÃO],tbMedições[CONTRATO_ID],tbContratos[[#This Row],[CONTRATO_ID]],tbMedições[STATUS],"Pago")+SUMIFS(tbMedições[VALOR MEDIÇÃO],tbMedições[CONTRATO_ID],tbContratos[[#This Row],[CONTRATO_ID]],tbMedições[STATUS],"Medido") -> 0 | I30: =tbContratos[[#This Row],[VALOR CONTRATO]]-tbContratos[[#This Row],[VALOR MEDIDO]] -> 10000 | J30: =tbContratos[[#This Row],[VALOR MEDIDO]]/tbContratos[[#This Row],[VALOR CONTRATO]] -> 0
A31: CT030 | B31: 265 | C31: VERTICAL | D31: ALT | E31: =_xlfn.XLOOKUP(tbContratos[[#This Row],[EMPRESA]],tbFornecedores[FORNECEDOR],tbFornecedores[TIPO],"Não encontrado") -> ORÇAMENTO | F31: PARAMÉTRICO | G31: 9000 | H31: =SUMIFS(tbMedições[VALOR MEDIÇÃO],tbMedições[CONTRATO_ID],tbContratos[[#This Row],[CONTRATO_ID]],tbMedições[STATUS],"Pago")+SUMIFS(tbMedições[VALOR MEDIÇÃO],tbMedições[CONTRATO_ID],tbContratos[[#This Row],[CONTRATO_ID]],tbMedições[STATUS],"Medido") -> 9000 | I31: =tbContratos[[#This Row],[VALOR CONTRATO]]-tbContratos[[#This Row],[VALOR MEDIDO]] -> 0 | J31: =tbContratos[[#This Row],[VALOR MEDIDO]]/tbContratos[[#This Row],[VALOR CONTRATO]] -> 1
A32: CT031 | C32: VERTICAL | D32: GAL | E32: =_xlfn.XLOOKUP(tbContratos[[#This Row],[EMPRESA]],tbFornecedores[FORNECEDOR],tbFornecedores[TIPO],"Não encontrado") -> ORÇAMENTO | F32: PARAMÉTRICO | G32: 6248.31 | H32: =SUMIFS(tbMedições[VALOR MEDIÇÃO],tbMedições[CONTRATO_ID],tbContratos[[#This Row],[CONTRATO_ID]],tbMedições[STATUS],"Pago")+SUMIFS(tbMedições[VALOR MEDIÇÃO],tbMedições[CONTRATO_ID],tbContratos[[#This Row],[CONTRATO_ID]],tbMedições[STATUS],"Medido") -> 1874.493 | I32: =tbContratos[[#This Row],[VALOR CONTRATO]]-tbContratos[[#This Row],[VALOR MEDIDO]] -> 4373.817 | J32: =tbContratos[[#This Row],[VALOR MEDIDO]]/tbContratos[[#This Row],[VALOR CONTRATO]] -> 0.3
A33: CT032 | B33: 434 | C33: VERTICAL | D33: PQSUL | E33: =_xlfn.XLOOKUP(tbContratos[[#This Row],[EMPRESA]],tbFornecedores[FORNECEDOR],tbFornecedores[TIPO],"Não encontrado") -> ORÇAMENTO | F33: PARAMÉTRICO | G33: 12429.45 | H33: =SUMIFS(tbMedições[VALOR MEDIÇÃO],tbMedições[CONTRATO_ID],tbContratos[[#This Row],[CONTRATO_ID]],tbMedições[STATUS],"Pago")+SUMIFS(tbMedições[VALOR MEDIÇÃO],tbMedições[CONTRATO_ID],tbContratos[[#This Row],[CONTRATO_ID]],tbMedições[STATUS],"Medido") -> 3728.835 | I33: =tbContratos[[#This Row],[VALOR CONTRATO]]-tbContratos[[#This Row],[VALOR MEDIDO]] -> 8700.615 | J33: =tbContratos[[#This Row],[VALOR MEDIDO]]/tbContratos[[#This Row],[VALOR CONTRATO]] -> 0.3
A34: CT033 | B34: 434 | C34: VERTICAL | D34: LIB | E34: =_xlfn.XLOOKUP(tbContratos[[#This Row],[EMPRESA]],tbFornecedores[FORNECEDOR],tbFornecedores[TIPO],"Não encontrado") -> ORÇAMENTO | F34: PARAMÉTRICO | G34: 8067.11 | H34: =SUMIFS(tbMedições[VALOR MEDIÇÃO],tbMedições[CONTRATO_ID],tbContratos[[#This Row],[CONTRATO_ID]],tbMedições[STATUS],"Pago")+SUMIFS(tbMedições[VALOR MEDIÇÃO],tbMedições[CONTRATO_ID],tbContratos[[#This Row],[CONTRATO_ID]],tbMedições[STATUS],"Medido") -> 2420.133 | I34: =tbContratos[[#This Row],[VALOR CONTRATO]]-tbContratos[[#This Row],[VALOR MEDIDO]] -> 5646.977 | J34: =tbContratos[[#This Row],[VALOR MEDIDO]]/tbContratos[[#This Row],[VALOR CONTRATO]] -> 0.3
A35: CT034 | B35: 434 | C35: VERTICAL | D35: UNA | E35: =_xlfn.XLOOKUP(tbContratos[[#This Row],[EMPRESA]],tbFornecedores[FORNECEDOR],tbFornecedores[TIPO],"Não encontrado") -> ORÇAMENTO | F35: PARAMÉTRICO | G35: 8255.14 | H35: =SUMIFS(tbMedições[VALOR MEDIÇÃO],tbMedições[CONTRATO_ID],tbContratos[[#This Row],[CONTRATO_ID]],tbMedições[STATUS],"Pago")+SUMIFS(tbMedições[VALOR MEDIÇÃO],tbMedições[CONTRATO_ID],tbContratos[[#This Row],[CONTRATO_ID]],tbMedições[STATUS],"Medido") -> 2476.542 | I35: =tbContratos[[#This Row],[VALOR CONTRATO]]-tbContratos[[#This Row],[VALOR MEDIDO]] -> 5778.598 | J35: =tbContratos[[#This Row],[VALOR MEDIDO]]/tbContratos[[#This Row],[VALOR CONTRATO]] -> 0.3
A36: CT035 | B36: 345 | C36: BINV | D36: ALT | E36: =_xlfn.XLOOKUP(tbContratos[[#This Row],[EMPRESA]],tbFornecedores[FORNECEDOR],tbFornecedores[TIPO],"Não encontrado") -> COMPLEMENTARES | F36: COMPLEMENTARES | G36: 150000 | H36: =SUMIFS(tbMedições[VALOR MEDIÇÃO],tbMedições[CONTRATO_ID],tbContratos[[#This Row],[CONTRATO_ID]],tbMedições[STATUS],"Pago")+SUMIFS(tbMedições[VALOR MEDIÇÃO],tbMedições[CONTRATO_ID],tbContratos[[#This Row],[CONTRATO_ID]],tbMedições[STATUS],"Medido") -> 67000 | I36: =tbContratos[[#This Row],[VALOR CONTRATO]]-tbContratos[[#This Row],[VALOR MEDIDO]] -> 83000 | J36: =tbContratos[[#This Row],[VALOR MEDIDO]]/tbContratos[[#This Row],[VALOR CONTRATO]] -> 0.44666667
A37: CT036 | B37: 346 | C37: BINV | D37: UNA | E37: =_xlfn.XLOOKUP(tbContratos[[#This Row],[EMPRESA]],tbFornecedores[FORNECEDOR],tbFornecedores[TIPO],"Não encontrado") -> COMPLEMENTARES | F37: COMPLEMENTARES | G37: 65450 | H37: =SUMIFS(tbMedições[VALOR MEDIÇÃO],tbMedições[CONTRATO_ID],tbContratos[[#This Row],[CONTRATO_ID]],tbMedições[STATUS],"Pago")+SUMIFS(tbMedições[VALOR MEDIÇÃO],tbMedições[CONTRATO_ID],tbContratos[[#This Row],[CONTRATO_ID]],tbMedições[STATUS],"Medido") -> 33180 | I37: =tbContratos[[#This Row],[VALOR CONTRATO]]-tbContratos[[#This Row],[VALOR MEDIDO]] -> 32270 | J37: =tbContratos[[#This Row],[VALOR MEDIDO]]/tbContratos[[#This Row],[VALOR CONTRATO]] -> 0.50695187
A38: CT037 | B38: 347 | C38: BINV | D38: MON | E38: =_xlfn.XLOOKUP(tbContratos[[#This Row],[EMPRESA]],tbFornecedores[FORNECEDOR],tbFornecedores[TIPO],"Não encontrado") -> COMPLEMENTARES | F38: COMPLEMENTARES | G38: 20000 | H38: =SUMIFS(tbMedições[VALOR MEDIÇÃO],tbMedições[CONTRATO_ID],tbContratos[[#This Row],[CONTRATO_ID]],tbMedições[STATUS],"Pago")+SUMIFS(tbMedições[VALOR MEDIÇÃO],tbMedições[CONTRATO_ID],tbContratos[[#This Row],[CONTRATO_ID]],tbMedições[STATUS],"Medido") -> 12000 | I38: =tbContratos[[#This Row],[VALOR CONTRATO]]-tbContratos[[#This Row],[VALOR MEDIDO]] -> 8000 | J38: =tbContratos[[#This Row],[VALOR MEDIDO]]/tbContratos[[#This Row],[VALOR CONTRATO]] -> 0.6
A39: CT038 | B39: 488 | C39: ARCIS | D39: PQSUL | E39: =_xlfn.XLOOKUP(tbContratos[[#This Row],[EMPRESA]],tbFornecedores[FORNECEDOR],tbFornecedores[TIPO],"Não encontrado") -> COMPLEMENTARES | F39: COMPLEMENTARES | G39: 179500 | H39: =SUMIFS(tbMedições[VALOR MEDIÇÃO],tbMedições[CONTRATO_ID],tbContratos[[#This Row],[CONTRATO_ID]],tbMedições[STATUS],"Pago")+SUMIFS(tbMedições[VALOR MEDIÇÃO],tbMedições[CONTRATO_ID],tbContratos[[#This Row],[CONTRATO_ID]],tbMedições[STATUS],"Medido") -> 53850 | I39: =tbContratos[[#This Row],[VALOR CONTRATO]]-tbContratos[[#This Row],[VALOR MEDIDO]] -> 125650 | J39: =tbContratos[[#This Row],[VALOR MEDIDO]]/tbContratos[[#This Row],[VALOR CONTRATO]] -> 0.3
A40: CT039 | B40: 528 | C40: ARCIS | D40: ALT | E40: =_xlfn.XLOOKUP(tbContratos[[#This Row],[EMPRESA]],tbFornecedores[FORNECEDOR],tbFornecedores[TIPO],"Não encontrado") -> COMPLEMENTARES | F40: COMPLEMENTARES | G40: 140000 | H40: =SUMIFS(tbMedições[VALOR MEDIÇÃO],tbMedições[CONTRATO_ID],tbContratos[[#This Row],[CONTRATO_ID]],tbMedições[STATUS],"Pago")+SUMIFS(tbMedições[VALOR MEDIÇÃO],tbMedições[CONTRATO_ID],tbContratos[[#This Row],[CONTRATO_ID]],tbMedições[STATUS],"Medido") -> 42000 | I40: =tbContratos[[#This Row],[VALOR CONTRATO]]-tbContratos[[#This Row],[VALOR MEDIDO]] -> 98000 | J40: =tbContratos[[#This Row],[VALOR MEDIDO]]/tbContratos[[#This Row],[VALOR CONTRATO]] -> 0.3
A41: CT040 | B41: 598 | C41: ARCIS | D41: GAL | E41: =_xlfn.XLOOKUP(tbContratos[[#This Row],[EMPRESA]],tbFornecedores[FORNECEDOR],tbFornecedores[TIPO],"Não encontrado") -> COMPLEMENTARES | F41: COMPLEMENTARES | G41: 129800 | H41: =SUMIFS(tbMedições[VALOR MEDIÇÃO],tbMedições[CONTRATO_ID],tbContratos[[#This Row],[CONTRATO_ID]],tbMedições[STATUS],"Pago")+SUMIFS(tbMedições[VALOR MEDIÇÃO],tbMedições[CONTRATO_ID],tbContratos[[#This Row],[CONTRATO_ID]],tbMedições[STATUS],"Medido") -> 38940 | I41: =tbContratos[[#This Row],[VALOR CONTRATO]]-tbContratos[[#This Row],[VALOR MEDIDO]] -> 90860 | J41: =tbContratos[[#This Row],[VALOR MEDIDO]]/tbContratos[[#This Row],[VALOR CONTRATO]] -> 0.3
A42: CT041 | B42: 505 | C42: ARCIS | D42: UNA | E42: =_xlfn.XLOOKUP(tbContratos[[#This Row],[EMPRESA]],tbFornecedores[FORNECEDOR],tbFornecedores[TIPO],"Não encontrado") -> COMPLEMENTARES | F42: COMPLEMENTARES | G42: 85900 | H42: =SUMIFS(tbMedições[VALOR MEDIÇÃO],tbMedições[CONTRATO_ID],tbContratos[[#This Row],[CONTRATO_ID]],tbMedições[STATUS],"Pago")+SUMIFS(tbMedições[VALOR MEDIÇÃO],tbMedições[CONTRATO_ID],tbContratos[[#This Row],[CONTRATO_ID]],tbMedições[STATUS],"Medido") -> 25770 | I42: =tbContratos[[#This Row],[VALOR CONTRATO]]-tbContratos[[#This Row],[VALOR MEDIDO]] -> 60130 | J42: =tbContratos[[#This Row],[VALOR MEDIDO]]/tbContratos[[#This Row],[VALOR CONTRATO]] -> 0.3
A43: CT042 | B43: 608 | C43: ARCIS | D43: MON | E43: =_xlfn.XLOOKUP(tbContratos[[#This Row],[EMPRESA]],tbFornecedores[FORNECEDOR],tbFornecedores[TIPO],"Não encontrado") -> COMPLEMENTARES | F43: COMPLEMENTARES | G43: 35800 | H43: =SUMIFS(tbMedições[VALOR MEDIÇÃO],tbMedições[CONTRATO_ID],tbContratos[[#This Row],[CONTRATO_ID]],tbMedições[STATUS],"Pago")+SUMIFS(tbMedições[VALOR MEDIÇÃO],tbMedições[CONTRATO_ID],tbContratos[[#This Row],[CONTRATO_ID]],tbMedições[STATUS],"Medido") -> 15800 | I43: =tbContratos[[#This Row],[VALOR CONTRATO]]-tbContratos[[#This Row],[VALOR MEDIDO]] -> 20000 | J43: =tbContratos[[#This Row],[VALOR MEDIDO]]/tbContratos[[#This Row],[VALOR CONTRATO]] -> 0.44134078
A44: CT043 | B44: 431 | C44: DOMANI | D44: ALT | E44: =_xlfn.XLOOKUP(tbContratos[[#This Row],[EMPRESA]],tbFornecedores[FORNECEDOR],tbFornecedores[TIPO],"Não encontrado") -> DESEMPENHO | F44: DESEMPENHO | G44: 5000 | H44: =SUMIFS(tbMedições[VALOR MEDIÇÃO],tbMedições[CONTRATO_ID],tbContratos[[#This Row],[CONTRATO_ID]],tbMedições[STATUS],"Pago")+SUMIFS(tbMedições[VALOR MEDIÇÃO],tbMedições[CONTRATO_ID],tbContratos[[#This Row],[CONTRATO_ID]],tbMedições[STATUS],"Medido") -> 0 | I44: =tbContratos[[#This Row],[VALOR CONTRATO]]-tbContratos[[#This Row],[VALOR MEDIDO]] -> 5000 | J44: =tbContratos[[#This Row],[VALOR MEDIDO]]/tbContratos[[#This Row],[VALOR CONTRATO]] -> 0
A45: CT044 | C45: DOMANI | D45: GAL | E45: =_xlfn.XLOOKUP(tbContratos[[#This Row],[EMPRESA]],tbFornecedores[FORNECEDOR],tbFornecedores[TIPO],"Não encontrado") -> DESEMPENHO | F45: DESEMPENHO | G45: 5000 | H45: =SUMIFS(tbMedições[VALOR MEDIÇÃO],tbMedições[CONTRATO_ID],tbContratos[[#This Row],[CONTRATO_ID]],tbMedições[STATUS],"Pago")+SUMIFS(tbMedições[VALOR MEDIÇÃO],tbMedições[CONTRATO_ID],tbContratos[[#This Row],[CONTRATO_ID]],tbMedições[STATUS],"Medido") -> 0 | I45: =tbContratos[[#This Row],[VALOR CONTRATO]]-tbContratos[[#This Row],[VALOR MEDIDO]] -> 5000 | J45: =tbContratos[[#This Row],[VALOR MEDIDO]]/tbContratos[[#This Row],[VALOR CONTRATO]] -> 0
A46: CT045 | B46: 431 | C46: DOMANI | D46: PQSUL | E46: =_xlfn.XLOOKUP(tbContratos[[#This Row],[EMPRESA]],tbFornecedores[FORNECEDOR],tbFornecedores[TIPO],"Não encontrado") -> DESEMPENHO | F46: DESEMPENHO | G46: 5000 | H46: =SUMIFS(tbMedições[VALOR MEDIÇÃO],tbMedições[CONTRATO_ID],tbContratos[[#This Row],[CONTRATO_ID]],tbMedições[STATUS],"Pago")+SUMIFS(tbMedições[VALOR MEDIÇÃO],tbMedições[CONTRATO_ID],tbContratos[[#This Row],[CONTRATO_ID]],tbMedições[STATUS],"Medido") -> 0 | I46: =tbContratos[[#This Row],[VALOR CONTRATO]]-tbContratos[[#This Row],[VALOR MEDIDO]] -> 5000 | J46: =tbContratos[[#This Row],[VALOR MEDIDO]]/tbContratos[[#This Row],[VALOR CONTRATO]] -> 0
A47: CT046 | B47: 431 | C47: DOMANI | D47: LIB | E47: =_xlfn.XLOOKUP(tbContratos[[#This Row],[EMPRESA]],tbFornecedores[FORNECEDOR],tbFornecedores[TIPO],"Não encontrado") -> DESEMPENHO | F47: DESEMPENHO | G47: 5000 | H47: =SUMIFS(tbMedições[VALOR MEDIÇÃO],tbMedições[CONTRATO_ID],tbContratos[[#This Row],[CONTRATO_ID]],tbMedições[STATUS],"Pago")+SUMIFS(tbMedições[VALOR MEDIÇÃO],tbMedições[CONTRATO_ID],tbContratos[[#This Row],[CONTRATO_ID]],tbMedições[STATUS],"Medido") -> 0 | I47: =tbContratos[[#This Row],[VALOR CONTRATO]]-tbContratos[[#This Row],[VALOR MEDIDO]] -> 5000 | J47: =tbContratos[[#This Row],[VALOR MEDIDO]]/tbContratos[[#This Row],[VALOR CONTRATO]] -> 0
A48: CT047 | B48: 382 | C48: THAIS | D48: ALT | E48: =_xlfn.XLOOKUP(tbContratos[[#This Row],[EMPRESA]],tbFornecedores[FORNECEDOR],tbFornecedores[TIPO],"Não encontrado") -> LEGALIZAÇÃO | F48: LEGALIZAÇÃO | G48: =10*1425 -> 14250 | H48: =SUMIFS(tbMedições[VALOR MEDIÇÃO],tbMedições[CONTRATO_ID],tbContratos[[#This Row],[CONTRATO_ID]],tbMedições[STATUS],"Pago")+SUMIFS(tbMedições[VALOR MEDIÇÃO],tbMedições[CONTRATO_ID],tbContratos[[#This Row],[CONTRATO_ID]],tbMedições[STATUS],"Medido") -> 7125 | I48: =tbContratos[[#This Row],[VALOR CONTRATO]]-tbContratos[[#This Row],[VALOR MEDIDO]] -> 7125 | J48: =tbContratos[[#This Row],[VALOR MEDIDO]]/tbContratos[[#This Row],[VALOR CONTRATO]] -> 0.5
A49: CT048 | B49: 382 | C49: THAIS | D49: PQSUL | E49: =_xlfn.XLOOKUP(tbContratos[[#This Row],[EMPRESA]],tbFornecedores[FORNECEDOR],tbFornecedores[TIPO],"Não encontrado") -> LEGALIZAÇÃO | F49: LEGALIZAÇÃO | G49: =10*1425 -> 14250 | H49: =SUMIFS(tbMedições[VALOR MEDIÇÃO],tbMedições[CONTRATO_ID],tbContratos[[#This Row],[CONTRATO_ID]],tbMedições[STATUS],"Pago")+SUMIFS(tbMedições[VALOR MEDIÇÃO],tbMedições[CONTRATO_ID],tbContratos[[#This Row],[CONTRATO_ID]],tbMedições[STATUS],"Medido") -> 7125 | I49: =tbContratos[[#This Row],[VALOR CONTRATO]]-tbContratos[[#This Row],[VALOR MEDIDO]] -> 7125 | J49: =tbContratos[[#This Row],[VALOR MEDIDO]]/tbContratos[[#This Row],[VALOR CONTRATO]] -> 0.5
A50: CT049 | B50: 382 | C50: THAIS | D50: UNA | E50: =_xlfn.XLOOKUP(tbContratos[[#This Row],[EMPRESA]],tbFornecedores[FORNECEDOR],tbFornecedores[TIPO],"Não encontrado") -> LEGALIZAÇÃO | F50: LEGALIZAÇÃO | G50: =10*1425 -> 14250 | H50: =SUMIFS(tbMedições[VALOR MEDIÇÃO],tbMedições[CONTRATO_ID],tbContratos[[#This Row],[CONTRATO_ID]],tbMedições[STATUS],"Pago")+SUMIFS(tbMedições[VALOR MEDIÇÃO],tbMedições[CONTRATO_ID],tbContratos[[#This Row],[CONTRATO_ID]],tbMedições[STATUS],"Medido") -> 7125 | I50: =tbContratos[[#This Row],[VALOR CONTRATO]]-tbContratos[[#This Row],[VALOR MEDIDO]] -> 7125 | J50: =tbContratos[[#This Row],[VALOR MEDIDO]]/tbContratos[[#This Row],[VALOR CONTRATO]] -> 0.5
A51: CT050 | B51: 597 | C51: THAIS | D51: GAL | E51: =_xlfn.XLOOKUP(tbContratos[[#This Row],[EMPRESA]],tbFornecedores[FORNECEDOR],tbFornecedores[TIPO],"Não encontrado") -> LEGALIZAÇÃO | F51: LEGALIZAÇÃO | G51: =10*1425 -> 14250 | H51: =SUMIFS(tbMedições[VALOR MEDIÇÃO],tbMedições[CONTRATO_ID],tbContratos[[#This Row],[CONTRATO_ID]],tbMedições[STATUS],"Pago")+SUMIFS(tbMedições[VALOR MEDIÇÃO],tbMedições[CONTRATO_ID],tbContratos[[#This Row],[CONTRATO_ID]],tbMedições[STATUS],"Medido") -> 7125 | I51: =tbContratos[[#This Row],[VALOR CONTRATO]]-tbContratos[[#This Row],[VALOR MEDIDO]] -> 7125 | J51: =tbContratos[[#This Row],[VALOR MEDIDO]]/tbContratos[[#This Row],[VALOR CONTRATO]] -> 0.5
A52: CT051 | B52: 385 | C52: COSTA | D52: ALT | E52: =_xlfn.XLOOKUP(tbContratos[[#This Row],[EMPRESA]],tbFornecedores[FORNECEDOR],tbFornecedores[TIPO],"Não encontrado") -> LEGALIZAÇÃO | F52: LEGALIZAÇÃO | G52: 600 | H52: =SUMIFS(tbMedições[VALOR MEDIÇÃO],tbMedições[CONTRATO_ID],tbContratos[[#This Row],[CONTRATO_ID]],tbMedições[STATUS],"Pago")+SUMIFS(tbMedições[VALOR MEDIÇÃO],tbMedições[CONTRATO_ID],tbContratos[[#This Row],[CONTRATO_ID]],tbMedições[STATUS],"Medido") -> 600 | I52: =tbContratos[[#This Row],[VALOR CONTRATO]]-tbContratos[[#This Row],[VALOR MEDIDO]] -> 0 | J52: =tbContratos[[#This Row],[VALOR MEDIDO]]/tbContratos[[#This Row],[VALOR CONTRATO]] -> 1
A53: CT052 | B53: 385 | C53: COSTA | D53: GAL | E53: =_xlfn.XLOOKUP(tbContratos[[#This Row],[EMPRESA]],tbFornecedores[FORNECEDOR],tbFornecedores[TIPO],"Não encontrado") -> LEGALIZAÇÃO | F53: LEGALIZAÇÃO | G53: 600 | H53: =SUMIFS(tbMedições[VALOR MEDIÇÃO],tbMedições[CONTRATO_ID],tbContratos[[#This Row],[CONTRATO_ID]],tbMedições[STATUS],"Pago")+SUMIFS(tbMedições[VALOR MEDIÇÃO],tbMedições[CONTRATO_ID],tbContratos[[#This Row],[CONTRATO_ID]],tbMedições[STATUS],"Medido") -> 0 | I53: =tbContratos[[#This Row],[VALOR CONTRATO]]-tbContratos[[#This Row],[VALOR MEDIDO]] -> 600 | J53: =tbContratos[[#This Row],[VALOR MEDIDO]]/tbContratos[[#This Row],[VALOR CONTRATO]] -> 0
A54: CT053 | B54: 385 | C54: COSTA | D54: PQSUL | E54: =_xlfn.XLOOKUP(tbContratos[[#This Row],[EMPRESA]],tbFornecedores[FORNECEDOR],tbFornecedores[TIPO],"Não encontrado") -> LEGALIZAÇÃO | F54: LEGALIZAÇÃO | G54: 600 | H54: =SUMIFS(tbMedições[VALOR MEDIÇÃO],tbMedições[CONTRATO_ID],tbContratos[[#This Row],[CONTRATO_ID]],tbMedições[STATUS],"Pago")+SUMIFS(tbMedições[VALOR MEDIÇÃO],tbMedições[CONTRATO_ID],tbContratos[[#This Row],[CONTRATO_ID]],tbMedições[STATUS],"Medido") -> 0 | I54: =tbContratos[[#This Row],[VALOR CONTRATO]]-tbContratos[[#This Row],[VALOR MEDIDO]] -> 600 | J54: =tbContratos[[#This Row],[VALOR MEDIDO]]/tbContratos[[#This Row],[VALOR CONTRATO]] -> 0
A55: CT054 | B55: 385 | C55: COSTA | D55: LIB | E55: =_xlfn.XLOOKUP(tbContratos[[#This Row],[EMPRESA]],tbFornecedores[FORNECEDOR],tbFornecedores[TIPO],"Não encontrado") -> LEGALIZAÇÃO | F55: LEGALIZAÇÃO | G55: 600 | H55: =SUMIFS(tbMedições[VALOR MEDIÇÃO],tbMedições[CONTRATO_ID],tbContratos[[#This Row],[CONTRATO_ID]],tbMedições[STATUS],"Pago")+SUMIFS(tbMedições[VALOR MEDIÇÃO],tbMedições[CONTRATO_ID],tbContratos[[#This Row],[CONTRATO_ID]],tbMedições[STATUS],"Medido") -> 0 | I55: =tbContratos[[#This Row],[VALOR CONTRATO]]-tbContratos[[#This Row],[VALOR MEDIDO]] -> 600 | J55: =tbContratos[[#This Row],[VALOR MEDIDO]]/tbContratos[[#This Row],[VALOR CONTRATO]] -> 0
A56: CT055 | B56: 385 | C56: COSTA | D56: UNA | E56: =_xlfn.XLOOKUP(tbContratos[[#This Row],[EMPRESA]],tbFornecedores[FORNECEDOR],tbFornecedores[TIPO],"Não encontrado") -> LEGALIZAÇÃO | F56: LEGALIZAÇÃO | G56: 600 | H56: =SUMIFS(tbMedições[VALOR MEDIÇÃO],tbMedições[CONTRATO_ID],tbContratos[[#This Row],[CONTRATO_ID]],tbMedições[STATUS],"Pago")+SUMIFS(tbMedições[VALOR MEDIÇÃO],tbMedições[CONTRATO_ID],tbContratos[[#This Row],[CONTRATO_ID]],tbMedições[STATUS],"Medido") -> 600 | I56: =tbContratos[[#This Row],[VALOR CONTRATO]]-tbContratos[[#This Row],[VALOR MEDIDO]] -> 0 | J56: =tbContratos[[#This Row],[VALOR MEDIDO]]/tbContratos[[#This Row],[VALOR CONTRATO]] -> 1
A57: CT056 | B57: 584 | C57: MBUIATE | D57: MON | E57: =_xlfn.XLOOKUP(tbContratos[[#This Row],[EMPRESA]],tbFornecedores[FORNECEDOR],tbFornecedores[TIPO],"Não encontrado") -> ESTRUTURA | F57: ESTRUTURA DE CONCRETO | G57: 55000 | H57: =SUMIFS(tbMedições[VALOR MEDIÇÃO],tbMedições[CONTRATO_ID],tbContratos[[#This Row],[CONTRATO_ID]],tbMedições[STATUS],"Pago")+SUMIFS(tbMedições[VALOR MEDIÇÃO],tbMedições[CONTRATO_ID],tbContratos[[#This Row],[CONTRATO_ID]],tbMedições[STATUS],"Medido") -> 0 | I57: =tbContratos[[#This Row],[VALOR CONTRATO]]-tbContratos[[#This Row],[VALOR MEDIDO]] -> 55000 | J57: =tbContratos[[#This Row],[VALOR MEDIDO]]/tbContratos[[#This Row],[VALOR CONTRATO]] -> 0
A58: CT057 | B58: 585 | C58: MBUIATE | D58: UNA | E58: =_xlfn.XLOOKUP(tbContratos[[#This Row],[EMPRESA]],tbFornecedores[FORNECEDOR],tbFornecedores[TIPO],"Não encontrado") -> ESTRUTURA | F58: FUNDAÇÃO SUPERFICIAL | G58: 16500 | H58: =SUMIFS(tbMedições[VALOR MEDIÇÃO],tbMedições[CONTRATO_ID],tbContratos[[#This Row],[CONTRATO_ID]],tbMedições[STATUS],"Pago")+SUMIFS(tbMedições[VALOR MEDIÇÃO],tbMedições[CONTRATO_ID],tbContratos[[#This Row],[CONTRATO_ID]],tbMedições[STATUS],"Medido") -> 0 | I58: =tbContratos[[#This Row],[VALOR CONTRATO]]-tbContratos[[#This Row],[VALOR MEDIDO]] -> 16500 | J58: =tbContratos[[#This Row],[VALOR MEDIDO]]/tbContratos[[#This Row],[VALOR CONTRATO]] -> 0
A59: CT058 | C59: TAXAS | D59: ALT | E59: =_xlfn.XLOOKUP(tbContratos[[#This Row],[EMPRESA]],tbFornecedores[FORNECEDOR],tbFornecedores[TIPO],"Não encontrado") -> LEGALIZAÇÃO | F59: LEGALIZAÇÃO | G59: =528286.4-14250-600 -> 513436.4 | H59: =SUMIFS(tbMedições[VALOR MEDIÇÃO],tbMedições[CONTRATO_ID],tbContratos[[#This Row],[CONTRATO_ID]],tbMedições[STATUS],"Pago")+SUMIFS(tbMedições[VALOR MEDIÇÃO],tbMedições[CONTRATO_ID],tbContratos[[#This Row],[CONTRATO_ID]],tbMedições[STATUS],"Medido") -> 6060.03 | I59: =tbContratos[[#This Row],[VALOR CONTRATO]]-tbContratos[[#This Row],[VALOR MEDIDO]] -> 507376.37 | J59: =tbContratos[[#This Row],[VALOR MEDIDO]]/tbContratos[[#This Row],[VALOR CONTRATO]] -> 0.011802883
A60: CT059 | C60: TAXAS | D60: GAL | E60: =_xlfn.XLOOKUP(tbContratos[[#This Row],[EMPRESA]],tbFornecedores[FORNECEDOR],tbFornecedores[TIPO],"Não encontrado") -> LEGALIZAÇÃO | F60: LEGALIZAÇÃO | G60: =304579.2-14250-600 -> 289729.2 | H60: =SUMIFS(tbMedições[VALOR MEDIÇÃO],tbMedições[CONTRATO_ID],tbContratos[[#This Row],[CONTRATO_ID]],tbMedições[STATUS],"Pago")+SUMIFS(tbMedições[VALOR MEDIÇÃO],tbMedições[CONTRATO_ID],tbContratos[[#This Row],[CONTRATO_ID]],tbMedições[STATUS],"Medido") -> 10986.22 | I60: =tbContratos[[#This Row],[VALOR CONTRATO]]-tbContratos[[#This Row],[VALOR MEDIDO]] -> 278742.98 | J60: =tbContratos[[#This Row],[VALOR MEDIDO]]/tbContratos[[#This Row],[VALOR CONTRATO]] -> 0.037918926
A61: CT060 | C61: TAXAS | D61: PQSUL | E61: =_xlfn.XLOOKUP(tbContratos[[#This Row],[EMPRESA]],tbFornecedores[FORNECEDOR],tbFornecedores[TIPO],"Não encontrado") -> LEGALIZAÇÃO | F61: LEGALIZAÇÃO | G61: =742740.9-14250-600 -> 727890.9 | H61: =SUMIFS(tbMedições[VALOR MEDIÇÃO],tbMedições[CONTRATO_ID],tbContratos[[#This Row],[CONTRATO_ID]],tbMedições[STATUS],"Pago")+SUMIFS(tbMedições[VALOR MEDIÇÃO],tbMedições[CONTRATO_ID],tbContratos[[#This Row],[CONTRATO_ID]],tbMedições[STATUS],"Medido") -> 0 | I61: =tbContratos[[#This Row],[VALOR CONTRATO]]-tbContratos[[#This Row],[VALOR MEDIDO]] -> 727890.9 | J61: =tbContratos[[#This Row],[VALOR MEDIDO]]/tbContratos[[#This Row],[VALOR CONTRATO]] -> 0
A62: CT061 | C62: TAXAS | D62: UNA | E62: =_xlfn.XLOOKUP(tbContratos[[#This Row],[EMPRESA]],tbFornecedores[FORNECEDOR],tbFornecedores[TIPO],"Não encontrado") -> LEGALIZAÇÃO | F62: LEGALIZAÇÃO | G62: =250584-14250-600 -> 235734 | H62: =SUMIFS(tbMedições[VALOR MEDIÇÃO],tbMedições[CONTRATO_ID],tbContratos[[#This Row],[CONTRATO_ID]],tbMedições[STATUS],"Pago")+SUMIFS(tbMedições[VALOR MEDIÇÃO],tbMedições[CONTRATO_ID],tbContratos[[#This Row],[CONTRATO_ID]],tbMedições[STATUS],"Medido") -> 2885.93 | I62: =tbContratos[[#This Row],[VALOR CONTRATO]]-tbContratos[[#This Row],[VALOR MEDIDO]] -> 232848.07 | J62: =tbContratos[[#This Row],[VALOR MEDIDO]]/tbContratos[[#This Row],[VALOR CONTRATO]] -> 0.012242315

Sheet tbMedições
A1: Estudo preliminar | B1: CONTRATO_ID | C1: EMPRESA | D1: OBRA | E1: ETAPA | F1: PERCENTUAL | G1: DATA PREVISTA | H1: DATA MEDIÇÃO | I1: DATA REFERÊNCIA | J1: MÊS | K1: VALOR MEDIÇÃO | L1: STATUS | M1: NF | N1: DATA PAGAMENTO
A2: MED001 | B2: {=_xlfn.XLOOKUP(tbMedições[[#This Row],[EMPRESA]]&tbMedições[[#This Row],[OBRA]],tbContratos[EMPRESA]&tbContratos[OBRA],tbContratos[CONTRATO_ID],"Não localizado")} -> CT001 | C2: SOMA | D2: ALT | E2: Aceita proposta | F2: 0.1 | H2: 45797 | I2: =IF(tbMedições[[#This Row],[STATUS]]="Cancelada",DATE(1900,1,1),IF(OR(tbMedições[[#This Row],[STATUS]]="Pago",tbMedições[[#This Row],[STATUS]]="Medido"),tbMedições[[#This Row],[DATA MEDIÇÃO]],tbMedições[[#This Row],[DATA PREVISTA]])) -> 45797 | J2: =TEXT(tbMedições[[#This Row],[DATA REFERÊNCIA]],"aa/mm") -> 25/05 | K2: =_xlfn.XLOOKUP(tbMedições[[#This Row],[CONTRATO_ID]],tbContratos[CONTRATO_ID],tbContratos[VALOR CONTRATO],"Não encontrado")*tbMedições[[#This Row],[PERCENTUAL]] -> 10800 | L2: Pago
A3: MED002 | B3: {=_xlfn.XLOOKUP(tbMedições[[#This Row],[EMPRESA]]&tbMedições[[#This Row],[OBRA]],tbContratos[EMPRESA]&tbContratos[OBRA],tbContratos[CONTRATO_ID],"Não localizado")} -> CT001 | C3: SOMA | D3: ALT | E3: Emissão inicial EP | F3: 0.1 | H3: 45870 | I3: =IF(tbMedições[[#This Row],[STATUS]]="Cancelada",DATE(1900,1,1),IF(OR(tbMedições[[#This Row],[STATUS]]="Pago",tbMedições[[#This Row],[STATUS]]="Medido"),tbMedições[[#This Row],[DATA MEDIÇÃO]],tbMedições[[#This Row],[DATA PREVISTA]])) -> 45870 | J3: =TEXT(tbMedições[[#This Row],[DATA REFERÊNCIA]],"aa/mm") -> 25/08 | K3: =_xlfn.XLOOKUP(tbMedições[[#This Row],[CONTRATO_ID]],tbContratos[CONTRATO_ID],tbContratos[VALOR CONTRATO],"Não encontrado")*tbMedições[[#This Row],[PERCENTUAL]] -> 10800 | L3: Pago | S3: Rótulos de Linha | T3: Desembolso | U3: Acumulado
A4: MED003 | B4: {=_xlfn.XLOOKUP(tbMedições[[#This Row],[EMPRESA]]&tbMedições[[#This Row],[OBRA]],tbContratos[EMPRESA]&tbContratos[OBRA],tbContratos[CONTRATO_ID],"Não localizado")} -> CT001 | C4: SOMA | D4: ALT | E4: Emissão final EP | F4: 0.1 | H4: 46056 | I4: =IF(tbMedições[[#This Row],[STATUS]]="Cancelada",DATE(1900,1,1),IF(OR(tbMedições[[#This Row],[STATUS]]="Pago",tbMedições[[#This Row],[STATUS]]="Medido"),tbMedições[[#This Row],[DATA MEDIÇÃO]],tbMedições[[#This Row],[DATA PREVISTA]])) -> 46056 | J4: =TEXT(tbMedições[[#This Row],[DATA REFERÊNCIA]],"aa/mm") -> 26/02 | K4: =_xlfn.XLOOKUP(tbMedições[[#This Row],[CONTRATO_ID]],tbContratos[CONTRATO_ID],tbContratos[VALOR CONTRATO],"Não encontrado")*tbMedições[[#This Row],[PERCENTUAL]] -> 10800 | L4: Pago | M4: 375 | S4: 23/08 | T4: 3450 | U4: 3450
A5: MED004 | B5: {=_xlfn.XLOOKUP(tbMedições[[#This Row],[EMPRESA]]&tbMedições[[#This Row],[OBRA]],tbContratos[EMPRESA]&tbContratos[OBRA],tbContratos[CONTRATO_ID],"Não localizado")} -> CT001 | C5: SOMA | D5: ALT | E5: Emissão inicial PL | F5: 0.15 | H5: 46111 | I5: =IF(tbMedições[[#This Row],[STATUS]]="Cancelada",DATE(1900,1,1),IF(OR(tbMedições[[#This Row],[STATUS]]="Pago",tbMedições[[#This Row],[STATUS]]="Medido"),tbMedições[[#This Row],[DATA MEDIÇÃO]],tbMedições[[#This Row],[DATA PREVISTA]])) -> 46111 | J5: =TEXT(tbMedições[[#This Row],[DATA REFERÊNCIA]],"aa/mm") -> 26/03 | K5: =_xlfn.XLOOKUP(tbMedições[[#This Row],[CONTRATO_ID]],tbContratos[CONTRATO_ID],tbContratos[VALOR CONTRATO],"Não encontrado")*tbMedições[[#This Row],[PERCENTUAL]] -> 16200 | L5: Pago | M5: 467 | S5: 25/05 | T5: 11900 | U5: 15350
A6: MED005 | B6: {=_xlfn.XLOOKUP(tbMedições[[#This Row],[EMPRESA]]&tbMedições[[#This Row],[OBRA]],tbContratos[EMPRESA]&tbContratos[OBRA],tbContratos[CONTRATO_ID],"Não localizado")} -> CT001 | C6: SOMA | D6: ALT | E6: 1° Comunique-se | F6: 0.3 | H6: 46195 | I6: =IF(tbMedições[[#This Row],[STATUS]]="Cancelada",DATE(1900,1,1),IF(OR(tbMedições[[#This Row],[STATUS]]="Pago",tbMedições[[#This Row],[STATUS]]="Medido"),tbMedições[[#This Row],[DATA MEDIÇÃO]],tbMedições[[#This Row],[DATA PREVISTA]])) -> 46195 | J6: =TEXT(tbMedições[[#This Row],[DATA REFERÊNCIA]],"aa/mm") -> 26/06 | K6: =_xlfn.XLOOKUP(tbMedições[[#This Row],[CONTRATO_ID]],tbContratos[CONTRATO_ID],tbContratos[VALOR CONTRATO],"Não encontrado")*tbMedições[[#This Row],[PERCENTUAL]] -> 32400 | L6: Pago | M6: 593 | S6: 25/08 | T6: 10800 | U6: 26150
A7: MED006 | B7: {=_xlfn.XLOOKUP(tbMedições[[#This Row],[EMPRESA]]&tbMedições[[#This Row],[OBRA]],tbContratos[EMPRESA]&tbContratos[OBRA],tbContratos[CONTRATO_ID],"Não localizado")} -> CT001 | C7: SOMA | D7: ALT | E7: 2° Comunique-se | F7: 0.2 | H7: 46237 | I7: =IF(tbMedições[[#This Row],[STATUS]]="Cancelada",DATE(1900,1,1),IF(OR(tbMedições[[#This Row],[STATUS]]="Pago",tbMedições[[#This Row],[STATUS]]="Medido"),tbMedições[[#This Row],[DATA MEDIÇÃO]],tbMedições[[#This Row],[DATA PREVISTA]])) -> 46237 | J7: =TEXT(tbMedições[[#This Row],[DATA REFERÊNCIA]],"aa/mm") -> 26/08 | K7: =_xlfn.XLOOKUP(tbMedições[[#This Row],[CONTRATO_ID]],tbContratos[CONTRATO_ID],tbContratos[VALOR CONTRATO],"Não encontrado")*tbMedições[[#This Row],[PERCENTUAL]] -> 21600 | L7: Medido | M7: 653 | S7: 25/11 | T7: 4500 | U7: 30650
A8: MED007 | B8: {=_xlfn.XLOOKUP(tbMedições[[#This Row],[EMPRESA]]&tbMedições[[#This Row],[OBRA]],tbContratos[EMPRESA]&tbContratos[OBRA],tbContratos[CONTRATO_ID],"Não localizado")} -> CT001 | C8: SOMA | D8: ALT | E8: Emissão alvará | F8: 0.05 | G8: 46268 | I8: =IF(tbMedições[[#This Row],[STATUS]]="Cancelada",DATE(1900,1,1),IF(OR(tbMedições[[#This Row],[STATUS]]="Pago",tbMedições[[#This Row],[STATUS]]="Medido"),tbMedições[[#This Row],[DATA MEDIÇÃO]],tbMedições[[#This Row],[DATA PREVISTA]])) -> 46268 | J8: =TEXT(tbMedições[[#This Row],[DATA REFERÊNCIA]],"aa/mm") -> 26/09 | K8: =_xlfn.XLOOKUP(tbMedições[[#This Row],[CONTRATO_ID]],tbContratos[CONTRATO_ID],tbContratos[VALOR CONTRATO],"Não encontrado")*tbMedições[[#This Row],[PERCENTUAL]] -> 5400 | L8: A medir | S8: 25/12 | T8: 9000 | U8: 39650
A9: MED008 | B9: {=_xlfn.XLOOKUP(tbMedições[[#This Row],[EMPRESA]]&tbMedições[[#This Row],[OBRA]],tbContratos[EMPRESA]&tbContratos[OBRA],tbContratos[CONTRATO_ID],"Não localizado")} -> CT002 | C9: SOMA | D9: GAL | E9: Aceite proposta | F9: 0.1 | H9: 46093 | I9: =IF(tbMedições[[#This Row],[STATUS]]="Cancelada",DATE(1900,1,1),IF(OR(tbMedições[[#This Row],[STATUS]]="Pago",tbMedições[[#This Row],[STATUS]]="Medido"),tbMedições[[#This Row],[DATA MEDIÇÃO]],tbMedições[[#This Row],[DATA PREVISTA]])) -> 46093 | J9: =TEXT(tbMedições[[#This Row],[DATA REFERÊNCIA]],"aa/mm") -> 26/03 | K9: =_xlfn.XLOOKUP(tbMedições[[#This Row],[CONTRATO_ID]],tbContratos[CONTRATO_ID],tbContratos[VALOR CONTRATO],"Não encontrado")*tbMedições[[#This Row],[PERCENTUAL]] -> 8568 | L9: Pago | M9: 415 | S9: 26/01 | T9: 48500 | U9: 88150
A10: MED009 | B10: {=_xlfn.XLOOKUP(tbMedições[[#This Row],[EMPRESA]]&tbMedições[[#This Row],[OBRA]],tbContratos[EMPRESA]&tbContratos[OBRA],tbContratos[CONTRATO_ID],"Não localizado")} -> CT002 | C10: SOMA | D10: GAL | E10: Estudo de massa | F10: 0.1 | H10: 46113 | I10: =IF(tbMedições[[#This Row],[STATUS]]="Cancelada",DATE(1900,1,1),IF(OR(tbMedições[[#This Row],[STATUS]]="Pago",tbMedições[[#This Row],[STATUS]]="Medido"),tbMedições[[#This Row],[DATA MEDIÇÃO]],tbMedições[[#This Row],[DATA PREVISTA]])) -> 46113 | J10: =TEXT(tbMedições[[#This Row],[DATA REFERÊNCIA]],"aa/mm") -> 26/04 | K10: =_xlfn.XLOOKUP(tbMedições[[#This Row],[CONTRATO_ID]],tbContratos[CONTRATO_ID],tbContratos[VALOR CONTRATO],"Não encontrado")*tbMedições[[#This Row],[PERCENTUAL]] -> 8568 | L10: Pago | M10: 469 | S10: 26/02 | T10: 55800 | U10: 143950
A11: MED010 | B11: {=_xlfn.XLOOKUP(tbMedições[[#This Row],[EMPRESA]]&tbMedições[[#This Row],[OBRA]],tbContratos[EMPRESA]&tbContratos[OBRA],tbContratos[CONTRATO_ID],"Não localizado")} -> CT002 | C11: SOMA | D11: GAL | E11: Emissão inicial EP | F11: 0.2 | H11: 46195 | I11: =IF(tbMedições[[#This Row],[STATUS]]="Cancelada",DATE(1900,1,1),IF(OR(tbMedições[[#This Row],[STATUS]]="Pago",tbMedições[[#This Row],[STATUS]]="Medido"),tbMedições[[#This Row],[DATA MEDIÇÃO]],tbMedições[[#This Row],[DATA PREVISTA]])) -> 46195 | J11: =TEXT(tbMedições[[#This Row],[DATA REFERÊNCIA]],"aa/mm") -> 26/06 | K11: =_xlfn.XLOOKUP(tbMedições[[#This Row],[CONTRATO_ID]],tbContratos[CONTRATO_ID],tbContratos[VALOR CONTRATO],"Não encontrado")*tbMedições[[#This Row],[PERCENTUAL]] -> 17136 | L11: Pago | M11: 594 | S11: 26/03 | T11: 18225 | U11: 162175
A12: MED011 | B12: {=_xlfn.XLOOKUP(tbMedições[[#This Row],[EMPRESA]]&tbMedições[[#This Row],[OBRA]],tbContratos[EMPRESA]&tbContratos[OBRA],tbContratos[CONTRATO_ID],"Não localizado")} -> CT002 | C12: SOMA | D12: GAL | E12: Emissão final EP | F12: 0.15 | H12: 46204 | I12: =IF(tbMedições[[#This Row],[STATUS]]="Cancelada",DATE(1900,1,1),IF(OR(tbMedições[[#This Row],[STATUS]]="Pago",tbMedições[[#This Row],[STATUS]]="Medido"),tbMedições[[#This Row],[DATA MEDIÇÃO]],tbMedições[[#This Row],[DATA PREVISTA]])) -> 46204 | J12: =TEXT(tbMedições[[#This Row],[DATA REFERÊNCIA]],"aa/mm") -> 26/07 | K12: =_xlfn.XLOOKUP(tbMedições[[#This Row],[CONTRATO_ID]],tbContratos[CONTRATO_ID],tbContratos[VALOR CONTRATO],"Não encontrado")*tbMedições[[#This Row],[PERCENTUAL]] -> 12852 | L12: Pago | M12: 641 | S12: 26/04 | T12: 7376.64 | U12: 169551.64
A13: MED012 | B13: {=_xlfn.XLOOKUP(tbMedições[[#This Row],[EMPRESA]]&tbMedições[[#This Row],[OBRA]],tbContratos[EMPRESA]&tbContratos[OBRA],tbContratos[CONTRATO_ID],"Não localizado")} -> CT002 | C13: SOMA | D13: GAL | E13: Emissão PL | F13: 0.2 | G13: 46244 | I13: =IF(tbMedições[[#This Row],[STATUS]]="Cancelada",DATE(1900,1,1),IF(OR(tbMedições[[#This Row],[STATUS]]="Pago",tbMedições[[#This Row],[STATUS]]="Medido"),tbMedições[[#This Row],[DATA MEDIÇÃO]],tbMedições[[#This Row],[DATA PREVISTA]])) -> 46244 | J13: =TEXT(tbMedições[[#This Row],[DATA REFERÊNCIA]],"aa/mm") -> 26/08 | K13: =_xlfn.XLOOKUP(tbMedições[[#This Row],[CONTRATO_ID]],tbContratos[CONTRATO_ID],tbContratos[VALOR CONTRATO],"Não encontrado")*tbMedições[[#This Row],[PERCENTUAL]] -> 17136 | L13: A medir | S13: 26/05 | T13: 19005 | U13: 188556.64
A14: MED013 | B14: {=_xlfn.XLOOKUP(tbMedições[[#This Row],[EMPRESA]]&tbMedições[[#This Row],[OBRA]],tbContratos[EMPRESA]&tbContratos[OBRA],tbContratos[CONTRATO_ID],"Não localizado")} -> CT002 | C14: SOMA | D14: GAL | E14: 1° Comunique-se | F14: 0.1 | G14: 46275 | I14: =IF(tbMedições[[#This Row],[STATUS]]="Cancelada",DATE(1900,1,1),IF(OR(tbMedições[[#This Row],[STATUS]]="Pago",tbMedições[[#This Row],[STATUS]]="Medido"),tbMedições[[#This Row],[DATA MEDIÇÃO]],tbMedições[[#This Row],[DATA PREVISTA]])) -> 46275 | J14: =TEXT(tbMedições[[#This Row],[DATA REFERÊNCIA]],"aa/mm") -> 26/09 | K14: =_xlfn.XLOOKUP(tbMedições[[#This Row],[CONTRATO_ID]],tbContratos[CONTRATO_ID],tbContratos[VALOR CONTRATO],"Não encontrado")*tbMedições[[#This Row],[PERCENTUAL]] -> 8568 | L14: A medir | S14: 26/06 | T14: 94434.04 | U14: 282990.68
A15: MED014 | B15: {=_xlfn.XLOOKUP(tbMedições[[#This Row],[EMPRESA]]&tbMedições[[#This Row],[OBRA]],tbContratos[EMPRESA]&tbContratos[OBRA],tbContratos[CONTRATO_ID],"Não localizado")} -> CT002 | C15: SOMA | D15: GAL | E15: 2° Comunique-se | F15: 0.1 | G15: 46305 | I15: =IF(tbMedições[[#This Row],[STATUS]]="Cancelada",DATE(1900,1,1),IF(OR(tbMedições[[#This Row],[STATUS]]="Pago",tbMedições[[#This Row],[STATUS]]="Medido"),tbMedições[[#This Row],[DATA MEDIÇÃO]],tbMedições[[#This Row],[DATA PREVISTA]])) -> 46305 | J15: =TEXT(tbMedições[[#This Row],[DATA REFERÊNCIA]],"aa/mm") -> 26/10 | K15: =_xlfn.XLOOKUP(tbMedições[[#This Row],[CONTRATO_ID]],tbContratos[CONTRATO_ID],tbContratos[VALOR CONTRATO],"Não encontrado")*tbMedições[[#This Row],[PERCENTUAL]] -> 8568 | L15: A medir | S15: 26/07 | T15: 1425 | U15: 284415.68
A16: MED015 | B16: {=_xlfn.XLOOKUP(tbMedições[[#This Row],[EMPRESA]]&tbMedições[[#This Row],[OBRA]],tbContratos[EMPRESA]&tbContratos[OBRA],tbContratos[CONTRATO_ID],"Não localizado")} -> CT002 | C16: SOMA | D16: GAL | E16: Emissão alvará | F16: 0.05 | G16: 46336 | I16: =IF(tbMedições[[#This Row],[STATUS]]="Cancelada",DATE(1900,1,1),IF(OR(tbMedições[[#This Row],[STATUS]]="Pago",tbMedições[[#This Row],[STATUS]]="Medido"),tbMedições[[#This Row],[DATA MEDIÇÃO]],tbMedições[[#This Row],[DATA PREVISTA]])) -> 46336 | J16: =TEXT(tbMedições[[#This Row],[DATA REFERÊNCIA]],"aa/mm") -> 26/11 | K16: =_xlfn.XLOOKUP(tbMedições[[#This Row],[CONTRATO_ID]],tbContratos[CONTRATO_ID],tbContratos[VALOR CONTRATO],"Não encontrado")*tbMedições[[#This Row],[PERCENTUAL]] -> 4284 | L16: A medir | S16: 26/08 | T16: 73425 | U16: 357840.68
A17: MED016 | B17: {=_xlfn.XLOOKUP(tbMedições[[#This Row],[EMPRESA]]&tbMedições[[#This Row],[OBRA]],tbContratos[EMPRESA]&tbContratos[OBRA],tbContratos[CONTRATO_ID],"Não localizado")} -> CT003 | C17: SOMA | D17: PQSUL | E17: Aceite proposta | F17: 0.1 | H17: 46093 | I17: =IF(tbMedições[[#This Row],[STATUS]]="Cancelada",DATE(1900,1,1),IF(OR(tbMedições[[#This Row],[STATUS]]="Pago",tbMedições[[#This Row],[STATUS]]="Medido"),tbMedições[[#This Row],[DATA MEDIÇÃO]],tbMedições[[#This Row],[DATA PREVISTA]])) -> 46093 | J17: =TEXT(tbMedições[[#This Row],[DATA REFERÊNCIA]],"aa/mm") -> 26/03 | K17: =_xlfn.XLOOKUP(tbMedições[[#This Row],[CONTRATO_ID]],tbContratos[CONTRATO_ID],tbContratos[VALOR CONTRATO],"Não encontrado")*tbMedições[[#This Row],[PERCENTUAL]] -> 16000 | L17: Pago | M17: 414 | S17: 26/09 | T17: 34825 | U17: 392665.68
A18: MED017 | B18: {=_xlfn.XLOOKUP(tbMedições[[#This Row],[EMPRESA]]&tbMedições[[#This Row],[OBRA]],tbContratos[EMPRESA]&tbContratos[OBRA],tbContratos[CONTRATO_ID],"Não localizado")} -> CT003 | C18: SOMA | D18: PQSUL | E18: Estudo de massa | F18: 0.1 | H18: 46113 | I18: =IF(tbMedições[[#This Row],[STATUS]]="Cancelada",DATE(1900,1,1),IF(OR(tbMedições[[#This Row],[STATUS]]="Pago",tbMedições[[#This Row],[STATUS]]="Medido"),tbMedições[[#This Row],[DATA MEDIÇÃO]],tbMedições[[#This Row],[DATA PREVISTA]])) -> 46113 | J18: =TEXT(tbMedições[[#This Row],[DATA REFERÊNCIA]],"aa/mm") -> 26/04 | K18: =_xlfn.XLOOKUP(tbMedições[[#This Row],[CONTRATO_ID]],tbContratos[CONTRATO_ID],tbContratos[VALOR CONTRATO],"Não encontrado")*tbMedições[[#This Row],[PERCENTUAL]] -> 16000 | L18: Pago | M18: 468 | S18: 26/10 | T18: 52325 | U18: 444990.68
A19: MED018 | B19: {=_xlfn.XLOOKUP(tbMedições[[#This Row],[EMPRESA]]&tbMedições[[#This Row],[OBRA]],tbContratos[EMPRESA]&tbContratos[OBRA],tbContratos[CONTRATO_ID],"Não localizado")} -> CT003 | C19: SOMA | D19: PQSUL | E19: Emissão inicial EP | F19: 0.2 | H19: 46195 | I19: =IF(tbMedições[[#This Row],[STATUS]]="Cancelada",DATE(1900,1,1),IF(OR(tbMedições[[#This Row],[STATUS]]="Pago",tbMedições[[#This Row],[STATUS]]="Medido"),tbMedições[[#This Row],[DATA MEDIÇÃO]],tbMedições[[#This Row],[DATA PREVISTA]])) -> 46195 | J19: =TEXT(tbMedições[[#This Row],[DATA REFERÊNCIA]],"aa/mm") -> 26/06 | K19: =_xlfn.XLOOKUP(tbMedições[[#This Row],[CONTRATO_ID]],tbContratos[CONTRATO_ID],tbContratos[VALOR CONTRATO],"Não encontrado")*tbMedições[[#This Row],[PERCENTUAL]] -> 32000 | L19: Pago | M19: 595 | S19: 26/11 | T19: 58425 | U19: 503415.68
A20: MED019 | B20: {=_xlfn.XLOOKUP(tbMedições[[#This Row],[EMPRESA]]&tbMedições[[#This Row],[OBRA]],tbContratos[EMPRESA]&tbContratos[OBRA],tbContratos[CONTRATO_ID],"Não localizado")} -> CT003 | C20: SOMA | D20: PQSUL | E20: Emissão final EP | F20: 0.15 | G20: 46287 | I20: =IF(tbMedições[[#This Row],[STATUS]]="Cancelada",DATE(1900,1,1),IF(OR(tbMedições[[#This Row],[STATUS]]="Pago",tbMedições[[#This Row],[STATUS]]="Medido"),tbMedições[[#This Row],[DATA MEDIÇÃO]],tbMedições[[#This Row],[DATA PREVISTA]])) -> 46287 | J20: =TEXT(tbMedições[[#This Row],[DATA REFERÊNCIA]],"aa/mm") -> 26/09 | K20: =_xlfn.XLOOKUP(tbMedições[[#This Row],[CONTRATO_ID]],tbContratos[CONTRATO_ID],tbContratos[VALOR CONTRATO],"Não encontrado")*tbMedições[[#This Row],[PERCENTUAL]] -> 24000 | L20: A medir | S20: 26/12 | T20: 13425 | U20: 516840.68
A21: MED020 | B21: {=_xlfn.XLOOKUP(tbMedições[[#This Row],[EMPRESA]]&tbMedições[[#This Row],[OBRA]],tbContratos[EMPRESA]&tbContratos[OBRA],tbContratos[CONTRATO_ID],"Não localizado")} -> CT003 | C21: SOMA | D21: PQSUL | E21: Emissão PL | F21: 0.2 | G21: 46317 | I21: =IF(tbMedições[[#This Row],[STATUS]]="Cancelada",DATE(1900,1,1),IF(OR(tbMedições[[#This Row],[STATUS]]="Pago",tbMedições[[#This Row],[STATUS]]="Medido"),tbMedições[[#This Row],[DATA MEDIÇÃO]],tbMedições[[#This Row],[DATA PREVISTA]])) -> 46317 | J21: =TEXT(tbMedições[[#This Row],[DATA REFERÊNCIA]],"aa/mm") -> 26/10 | K21: =_xlfn.XLOOKUP(tbMedições[[#This Row],[CONTRATO_ID]],tbContratos[CONTRATO_ID],tbContratos[VALOR CONTRATO],"Não encontrado")*tbMedições[[#This Row],[PERCENTUAL]] -> 32000 | L21: A medir | S21: 27/01 | T21: 7000 | U21: 523840.68
A22: MED021 | B22: {=_xlfn.XLOOKUP(tbMedições[[#This Row],[EMPRESA]]&tbMedições[[#This Row],[OBRA]],tbContratos[EMPRESA]&tbContratos[OBRA],tbContratos[CONTRATO_ID],"Não localizado")} -> CT003 | C22: SOMA | D22: PQSUL | E22: 1° Comunique-se | F22: 0.1 | G22: 46348 | I22: =IF(tbMedições[[#This Row],[STATUS]]="Cancelada",DATE(1900,1,1),IF(OR(tbMedições[[#This Row],[STATUS]]="Pago",tbMedições[[#This Row],[STATUS]]="Medido"),tbMedições[[#This Row],[DATA MEDIÇÃO]],tbMedições[[#This Row],[DATA PREVISTA]])) -> 46348 | J22: =TEXT(tbMedições[[#This Row],[DATA REFERÊNCIA]],"aa/mm") -> 26/11 | K22: =_xlfn.XLOOKUP(tbMedições[[#This Row],[CONTRATO_ID]],tbContratos[CONTRATO_ID],tbContratos[VALOR CONTRATO],"Não encontrado")*tbMedições[[#This Row],[PERCENTUAL]] -> 16000 | L22: A medir | S22: 27/02 | T22: 7000 | U22: 530840.68
A23: MED022 | B23: {=_xlfn.XLOOKUP(tbMedições[[#This Row],[EMPRESA]]&tbMedições[[#This Row],[OBRA]],tbContratos[EMPRESA]&tbContratos[OBRA],tbContratos[CONTRATO_ID],"Não localizado")} -> CT003 | C23: SOMA | D23: PQSUL | E23: 2° Comunique-se | F23: 0.1 | G23: 46378 | I23: =IF(tbMedições[[#This Row],[STATUS]]="Cancelada",DATE(1900,1,1),IF(OR(tbMedições[[#This Row],[STATUS]]="Pago",tbMedições[[#This Row],[STATUS]]="Medido"),tbMedições[[#This Row],[DATA MEDIÇÃO]],tbMedições[[#This Row],[DATA PREVISTA]])) -> 46378 | J23: =TEXT(tbMedições[[#This Row],[DATA REFERÊNCIA]],"aa/mm") -> 26/12 | K23: =_xlfn.XLOOKUP(tbMedições[[#This Row],[CONTRATO_ID]],tbContratos[CONTRATO_ID],tbContratos[VALOR CONTRATO],"Não encontrado")*tbMedições[[#This Row],[PERCENTUAL]] -> 16000 | L23: A medir | S23: Total Geral | T23: 530840.68
A24: MED023 | B24: {=_xlfn.XLOOKUP(tbMedições[[#This Row],[EMPRESA]]&tbMedições[[#This Row],[OBRA]],tbContratos[EMPRESA]&tbContratos[OBRA],tbContratos[CONTRATO_ID],"Não localizado")} -> CT003 | C24: SOMA | D24: PQSUL | E24: Emissão alvará | F24: 0.05 | G24: 46044 | I24: =IF(tbMedições[[#This Row],[STATUS]]="Cancelada",DATE(1900,1,1),IF(OR(tbMedições[[#This Row],[STATUS]]="Pago",tbMedições[[#This Row],[STATUS]]="Medido"),tbMedições[[#This Row],[DATA MEDIÇÃO]],tbMedições[[#This Row],[DATA PREVISTA]])) -> 46044 | J24: =TEXT(tbMedições[[#This Row],[DATA REFERÊNCIA]],"aa/mm") -> 26/01 | K24: =_xlfn.XLOOKUP(tbMedições[[#This Row],[CONTRATO_ID]],tbContratos[CONTRATO_ID],tbContratos[VALOR CONTRATO],"Não encontrado")*tbMedições[[#This Row],[PERCENTUAL]] -> 8000 | L24: A medir
A25: MED024 | B25: {=_xlfn.XLOOKUP(tbMedições[[#This Row],[EMPRESA]]&tbMedições[[#This Row],[OBRA]],tbContratos[EMPRESA]&tbContratos[OBRA],tbContratos[CONTRATO_ID],"Não localizado")} -> CT004 | C25: SOMA | D25: LIB | E25: Aceite proposta | F25: 0.1 | H25: 45807 | I25: =IF(tbMedições[[#This Row],[STATUS]]="Cancelada",DATE(1900,1,1),IF(OR(tbMedições[[#This Row],[STATUS]]="Pago",tbMedições[[#This Row],[STATUS]]="Medido"),tbMedições[[#This Row],[DATA MEDIÇÃO]],tbMedições[[#This Row],[DATA PREVISTA]])) -> 45807 | J25: =TEXT(tbMedições[[#This Row],[DATA REFERÊNCIA]],"aa/mm") -> 25/05 | K25: =_xlfn.XLOOKUP(tbMedições[[#This Row],[CONTRATO_ID]],tbContratos[CONTRATO_ID],tbContratos[VALOR CONTRATO],"Não encontrado")*tbMedições[[#This Row],[PERCENTUAL]] -> 7800 | L25: Pago
A26: MED025 | B26: {=_xlfn.XLOOKUP(tbMedições[[#This Row],[EMPRESA]]&tbMedições[[#This Row],[OBRA]],tbContratos[EMPRESA]&tbContratos[OBRA],tbContratos[CONTRATO_ID],"Não localizado")} -> CT004 | C26: SOMA | D26: LIB | E26: Emissão inicial EP | F26: 0.2 | H26: 45915 | I26: =IF(tbMedições[[#This Row],[STATUS]]="Cancelada",DATE(1900,1,1),IF(OR(tbMedições[[#This Row],[STATUS]]="Pago",tbMedições[[#This Row],[STATUS]]="Medido"),tbMedições[[#This Row],[DATA MEDIÇÃO]],tbMedições[[#This Row],[DATA PREVISTA]])) -> 45915 | J26: =TEXT(tbMedições[[#This Row],[DATA REFERÊNCIA]],"aa/mm") -> 25/09 | K26: =_xlfn.XLOOKUP(tbMedições[[#This Row],[CONTRATO_ID]],tbContratos[CONTRATO_ID],tbContratos[VALOR CONTRATO],"Não encontrado")*tbMedições[[#This Row],[PERCENTUAL]] -> 15600 | L26: Pago
A27: MED026 | B27: {=_xlfn.XLOOKUP(tbMedições[[#This Row],[EMPRESA]]&tbMedições[[#This Row],[OBRA]],tbContratos[EMPRESA]&tbContratos[OBRA],tbContratos[CONTRATO_ID],"Não localizado")} -> CT004 | C27: SOMA | D27: LIB | E27: Emissão final EP | F27: 0.2 | G27: 46310 | I27: =IF(tbMedições[[#This Row],[STATUS]]="Cancelada",DATE(1900,1,1),IF(OR(tbMedições[[#This Row],[STATUS]]="Pago",tbMedições[[#This Row],[STATUS]]="Medido"),tbMedições[[#This Row],[DATA MEDIÇÃO]],tbMedições[[#This Row],[DATA PREVISTA]])) -> 46310 | J27: =TEXT(tbMedições[[#This Row],[DATA REFERÊNCIA]],"aa/mm") -> 26/10 | K27: =_xlfn.XLOOKUP(tbMedições[[#This Row],[CONTRATO_ID]],tbContratos[CONTRATO_ID],tbContratos[VALOR CONTRATO],"Não encontrado")*tbMedições[[#This Row],[PERCENTUAL]] -> 15600 | L27: A medir
A28: MED027 | B28: {=_xlfn.XLOOKUP(tbMedições[[#This Row],[EMPRESA]]&tbMedições[[#This Row],[OBRA]],tbContratos[EMPRESA]&tbContratos[OBRA],tbContratos[CONTRATO_ID],"Não localizado")} -> CT004 | C28: SOMA | D28: LIB | E28: Emissão inicial PL | F28: 0.2 | I28: =IF(tbMedições[[#This Row],[STATUS]]="Cancelada",DATE(1900,1,1),IF(OR(tbMedições[[#This Row],[STATUS]]="Pago",tbMedições[[#This Row],[STATUS]]="Medido"),tbMedições[[#This Row],[DATA MEDIÇÃO]],tbMedições[[#This Row],[DATA PREVISTA]])) -> 1 | J28: =TEXT(tbMedições[[#This Row],[DATA REFERÊNCIA]],"aa/mm") -> 00/01 | K28: =_xlfn.XLOOKUP(tbMedições[[#This Row],[CONTRATO_ID]],tbContratos[CONTRATO_ID],tbContratos[VALOR CONTRATO],"Não encontrado")*tbMedições[[#This Row],[PERCENTUAL]] -> 15600 | L28: Cancelada
A29: MED028 | B29: {=_xlfn.XLOOKUP(tbMedições[[#This Row],[EMPRESA]]&tbMedições[[#This Row],[OBRA]],tbContratos[EMPRESA]&tbContratos[OBRA],tbContratos[CONTRATO_ID],"Não localizado")} -> CT004 | C29: SOMA | D29: LIB | E29: 1° Comunique-se | F29: 0.15 | I29: =IF(tbMedições[[#This Row],[STATUS]]="Cancelada",DATE(1900,1,1),IF(OR(tbMedições[[#This Row],[STATUS]]="Pago",tbMedições[[#This Row],[STATUS]]="Medido"),tbMedições[[#This Row],[DATA MEDIÇÃO]],tbMedições[[#This Row],[DATA PREVISTA]])) -> 1 | J29: =TEXT(tbMedições[[#This Row],[DATA REFERÊNCIA]],"aa/mm") -> 00/01 | K29: =_xlfn.XLOOKUP(tbMedições[[#This Row],[CONTRATO_ID]],tbContratos[CONTRATO_ID],tbContratos[VALOR CONTRATO],"Não encontrado")*tbMedições[[#This Row],[PERCENTUAL]] -> 11700 | L29: Cancelada
A30: MED029 | B30: {=_xlfn.XLOOKUP(tbMedições[[#This Row],[EMPRESA]]&tbMedições[[#This Row],[OBRA]],tbContratos[EMPRESA]&tbContratos[OBRA],tbContratos[CONTRATO_ID],"Não localizado")} -> CT004 | C30: SOMA | D30: LIB | E30: 2° Comunique-se | F30: 0.1 | I30: =IF(tbMedições[[#This Row],[STATUS]]="Cancelada",DATE(1900,1,1),IF(OR(tbMedições[[#This Row],[STATUS]]="Pago",tbMedições[[#This Row],[STATUS]]="Medido"),tbMedições[[#This Row],[DATA MEDIÇÃO]],tbMedições[[#This Row],[DATA PREVISTA]])) -> 1 | J30: =TEXT(tbMedições[[#This Row],[DATA REFERÊNCIA]],"aa/mm") -> 00/01 | K30: =_xlfn.XLOOKUP(tbMedições[[#This Row],[CONTRATO_ID]],tbContratos[CONTRATO_ID],tbContratos[VALOR CONTRATO],"Não encontrado")*tbMedições[[#This Row],[PERCENTUAL]] -> 7800 | L30: Cancelada
A31: MED030 | B31: {=_xlfn.XLOOKUP(tbMedições[[#This Row],[EMPRESA]]&tbMedições[[#This Row],[OBRA]],tbContratos[EMPRESA]&tbContratos[OBRA],tbContratos[CONTRATO_ID],"Não localizado")} -> CT004 | C31: SOMA | D31: LIB | E31: Emissão alvará | F31: 0.05 | I31: =IF(tbMedições[[#This Row],[STATUS]]="Cancelada",DATE(1900,1,1),IF(OR(tbMedições[[#This Row],[STATUS]]="Pago",tbMedições[[#This Row],[STATUS]]="Medido"),tbMedições[[#This Row],[DATA MEDIÇÃO]],tbMedições[[#This Row],[DATA PREVISTA]])) -> 1 | J31: =TEXT(tbMedições[[#This Row],[DATA REFERÊNCIA]],"aa/mm") -> 00/01 | K31: =_xlfn.XLOOKUP(tbMedições[[#This Row],[CONTRATO_ID]],tbContratos[CONTRATO_ID],tbContratos[VALOR CONTRATO],"Não encontrado")*tbMedições[[#This Row],[PERCENTUAL]] -> 3900 | L31: Cancelada
A32: MED031 | B32: {=_xlfn.XLOOKUP(tbMedições[[#This Row],[EMPRESA]]&tbMedições[[#This Row],[OBRA]],tbContratos[EMPRESA]&tbContratos[OBRA],tbContratos[CONTRATO_ID],"Não localizado")} -> CT005 | C32: MBUIATE | D32: ALT | E32: Entrada | F32: 0.05 | H32: 45979 | I32: =IF(tbMedições[[#This Row],[STATUS]]="Cancelada",DATE(1900,1,1),IF(OR(tbMedições[[#This Row],[STATUS]]="Pago",tbMedições[[#This Row],[STATUS]]="Medido"),tbMedições[[#This Row],[DATA MEDIÇÃO]],tbMedições[[#This Row],[DATA PREVISTA]])) -> 45979 | J32: =TEXT(tbMedições[[#This Row],[DATA REFERÊNCIA]],"aa/mm") -> 25/11 | K32: =_xlfn.XLOOKUP(tbMedições[[#This Row],[CONTRATO_ID]],tbContratos[CONTRATO_ID],tbContratos[VALOR CONTRATO],"Não encontrado")*tbMedições[[#This Row],[PERCENTUAL]] -> 4500 | L32: Pago
A33: MED032 | B33: {=_xlfn.XLOOKUP(tbMedições[[#This Row],[EMPRESA]]&tbMedições[[#This Row],[OBRA]],tbContratos[EMPRESA]&tbContratos[OBRA],tbContratos[CONTRATO_ID],"Não localizado")} -> CT005 | C33: MBUIATE | D33: ALT | E33: Projeto preliminar | F33: 0.15 | H33: 46197 | I33: =IF(tbMedições[[#This Row],[STATUS]]="Cancelada",DATE(1900,1,1),IF(OR(tbMedições[[#This Row],[STATUS]]="Pago",tbMedições[[#This Row],[STATUS]]="Medido"),tbMedições[[#This Row],[DATA MEDIÇÃO]],tbMedições[[#This Row],[DATA PREVISTA]])) -> 46197 | J33: =TEXT(tbMedições[[#This Row],[DATA REFERÊNCIA]],"aa/mm") -> 26/06 | K33: =_xlfn.XLOOKUP(tbMedições[[#This Row],[CONTRATO_ID]],tbContratos[CONTRATO_ID],tbContratos[VALOR CONTRATO],"Não encontrado")*tbMedições[[#This Row],[PERCENTUAL]] -> 13500 | L33: Pago
A34: MED033 | B34: {=_xlfn.XLOOKUP(tbMedições[[#This Row],[EMPRESA]]&tbMedições[[#This Row],[OBRA]],tbContratos[EMPRESA]&tbContratos[OBRA],tbContratos[CONTRATO_ID],"Não localizado")} -> CT005 | C34: MBUIATE | D34: ALT | E34: Projeto pré-executivo | F34: 0.4 | G34: 46336 | I34: =IF(tbMedições[[#This Row],[STATUS]]="Cancelada",DATE(1900,1,1),IF(OR(tbMedições[[#This Row],[STATUS]]="Pago",tbMedições[[#This Row],[STATUS]]="Medido"),tbMedições[[#This Row],[DATA MEDIÇÃO]],tbMedições[[#This Row],[DATA PREVISTA]])) -> 46336 | J34: =TEXT(tbMedições[[#This Row],[DATA REFERÊNCIA]],"aa/mm") -> 26/11 | K34: =_xlfn.XLOOKUP(tbMedições[[#This Row],[CONTRATO_ID]],tbContratos[CONTRATO_ID],tbContratos[VALOR CONTRATO],"Não encontrado")*tbMedições[[#This Row],[PERCENTUAL]] -> 36000 | L34: A medir
A35: MED034 | B35: {=_xlfn.XLOOKUP(tbMedições[[#This Row],[EMPRESA]]&tbMedições[[#This Row],[OBRA]],tbContratos[EMPRESA]&tbContratos[OBRA],tbContratos[CONTRATO_ID],"Não localizado")} -> CT005 | C35: MBUIATE | D35: ALT | E35: Projeto executivo | F35: 0.4 | G35: 46032 | I35: =IF(tbMedições[[#This Row],[STATUS]]="Cancelada",DATE(1900,1,1),IF(OR(tbMedições[[#This Row],[STATUS]]="Pago",tbMedições[[#This Row],[STATUS]]="Medido"),tbMedições[[#This Row],[DATA MEDIÇÃO]],tbMedições[[#This Row],[DATA PREVISTA]])) -> 46032 | J35: =TEXT(tbMedições[[#This Row],[DATA REFERÊNCIA]],"aa/mm") -> 26/01 | K35: =_xlfn.XLOOKUP(tbMedições[[#This Row],[CONTRATO_ID]],tbContratos[CONTRATO_ID],tbContratos[VALOR CONTRATO],"Não encontrado")*tbMedições[[#This Row],[PERCENTUAL]] -> 36000 | L35: A fazer
A36: MED035 | B36: {=_xlfn.XLOOKUP(tbMedições[[#This Row],[EMPRESA]]&tbMedições[[#This Row],[OBRA]],tbContratos[EMPRESA]&tbContratos[OBRA],tbContratos[CONTRATO_ID],"Não localizado")} -> CT006 | C36: MBUIATE | D36: GAL | E36: Entrada | F36: 0.15 | H36: 46197 | I36: =IF(tbMedições[[#This Row],[STATUS]]="Cancelada",DATE(1900,1,1),IF(OR(tbMedições[[#This Row],[STATUS]]="Pago",tbMedições[[#This Row],[STATUS]]="Medido"),tbMedições[[#This Row],[DATA MEDIÇÃO]],tbMedições[[#This Row],[DATA PREVISTA]])) -> 46197 | J36: =TEXT(tbMedições[[#This Row],[DATA REFERÊNCIA]],"aa/mm") -> 26/06 | K36: =_xlfn.XLOOKUP(tbMedições[[#This Row],[CONTRATO_ID]],tbContratos[CONTRATO_ID],tbContratos[VALOR CONTRATO],"Não encontrado")*tbMedições[[#This Row],[PERCENTUAL]] -> 15000 | L36: Pago
A37: MED036 | B37: {=_xlfn.XLOOKUP(tbMedições[[#This Row],[EMPRESA]]&tbMedições[[#This Row],[OBRA]],tbContratos[EMPRESA]&tbContratos[OBRA],tbContratos[CONTRATO_ID],"Não localizado")} -> CT006 | C37: MBUIATE | D37: GAL | E37: Projeto preliminar | F37: 0.2 | G37: 46275 | I37: =IF(tbMedições[[#This Row],[STATUS]]="Cancelada",DATE(1900,1,1),IF(OR(tbMedições[[#This Row],[STATUS]]="Pago",tbMedições[[#This Row],[STATUS]]="Medido"),tbMedições[[#This Row],[DATA MEDIÇÃO]],tbMedições[[#This Row],[DATA PREVISTA]])) -> 46275 | J37: =TEXT(tbMedições[[#This Row],[DATA REFERÊNCIA]],"aa/mm") -> 26/09 | K37: =_xlfn.XLOOKUP(tbMedições[[#This Row],[CONTRATO_ID]],tbContratos[CONTRATO_ID],tbContratos[VALOR CONTRATO],"Não encontrado")*tbMedições[[#This Row],[PERCENTUAL]] -> 20000 | L37: A medir
A38: MED037 | B38: {=_xlfn.XLOOKUP(tbMedições[[#This Row],[EMPRESA]]&tbMedições[[#This Row],[OBRA]],tbContratos[EMPRESA]&tbContratos[OBRA],tbContratos[CONTRATO_ID],"Não localizado")} -> CT006 | C38: MBUIATE | D38: GAL | E38: Projeto pré-executivo | F38: 0.2 | G38: 46366 | I38: =IF(tbMedições[[#This Row],[STATUS]]="Cancelada",DATE(1900,1,1),IF(OR(tbMedições[[#This Row],[STATUS]]="Pago",tbMedições[[#This Row],[STATUS]]="Medido"),tbMedições[[#This Row],[DATA MEDIÇÃO]],tbMedições[[#This Row],[DATA PREVISTA]])) -> 46366 | J38: =TEXT(tbMedições[[#This Row],[DATA REFERÊNCIA]],"aa/mm") -> 26/12 | K38: =_xlfn.XLOOKUP(tbMedições[[#This Row],[CONTRATO_ID]],tbContratos[CONTRATO_ID],tbContratos[VALOR CONTRATO],"Não encontrado")*tbMedições[[#This Row],[PERCENTUAL]] -> 20000 | L38: A medir
A39: MED038 | B39: {=_xlfn.XLOOKUP(tbMedições[[#This Row],[EMPRESA]]&tbMedições[[#This Row],[OBRA]],tbContratos[EMPRESA]&tbContratos[OBRA],tbContratos[CONTRATO_ID],"Não localizado")} -> CT006 | C39: MBUIATE | D39: GAL | E39: Projeto executivo | F39: 0.45 | G39: 46032 | I39: =IF(tbMedições[[#This Row],[STATUS]]="Cancelada",DATE(1900,1,1),IF(OR(tbMedições[[#This Row],[STATUS]]="Pago",tbMedições[[#This Row],[STATUS]]="Medido"),tbMedições[[#This Row],[DATA MEDIÇÃO]],tbMedições[[#This Row],[DATA PREVISTA]])) -> 46032 | J39: =TEXT(tbMedições[[#This Row],[DATA REFERÊNCIA]],"aa/mm") -> 26/01 | K39: =_xlfn.XLOOKUP(tbMedições[[#This Row],[CONTRATO_ID]],tbContratos[CONTRATO_ID],tbContratos[VALOR CONTRATO],"Não encontrado")*tbMedições[[#This Row],[PERCENTUAL]] -> 45000 | L39: A medir
A40: MED039 | B40: {=_xlfn.XLOOKUP(tbMedições[[#This Row],[EMPRESA]]&tbMedições[[#This Row],[OBRA]],tbContratos[EMPRESA]&tbContratos[OBRA],tbContratos[CONTRATO_ID],"Não localizado")} -> CT007 | C40: MBUIATE | D40: PQSUL | E40: Entrada | F40: 0.15 | H40: 46197 | I40: =IF(tbMedições[[#This Row],[STATUS]]="Cancelada",DATE(1900,1,1),IF(OR(tbMedições[[#This Row],[STATUS]]="Pago",tbMedições[[#This Row],[STATUS]]="Medido"),tbMedições[[#This Row],[DATA MEDIÇÃO]],tbMedições[[#This Row],[DATA PREVISTA]])) -> 46197 | J40: =TEXT(tbMedições[[#This Row],[DATA REFERÊNCIA]],"aa/mm") -> 26/06 | K40: =_xlfn.XLOOKUP(tbMedições[[#This Row],[CONTRATO_ID]],tbContratos[CONTRATO_ID],tbContratos[VALOR CONTRATO],"Não encontrado")*tbMedições[[#This Row],[PERCENTUAL]] -> 31500 | L40: Pago
A41: MED040 | B41: {=_xlfn.XLOOKUP(tbMedições[[#This Row],[EMPRESA]]&tbMedições[[#This Row],[OBRA]],tbContratos[EMPRESA]&tbContratos[OBRA],tbContratos[CONTRATO_ID],"Não localizado")} -> CT007 | C41: MBUIATE | D41: PQSUL | E41: Projeto preliminar | F41: 0.2 | G41: 46336 | I41: =IF(tbMedições[[#This Row],[STATUS]]="Cancelada",DATE(1900,1,1),IF(OR(tbMedições[[#This Row],[STATUS]]="Pago",tbMedições[[#This Row],[STATUS]]="Medido"),tbMedições[[#This Row],[DATA MEDIÇÃO]],tbMedições[[#This Row],[DATA PREVISTA]])) -> 46336 | J41: =TEXT(tbMedições[[#This Row],[DATA REFERÊNCIA]],"aa/mm") -> 26/11 | K41: =_xlfn.XLOOKUP(tbMedições[[#This Row],[CONTRATO_ID]],tbContratos[CONTRATO_ID],tbContratos[VALOR CONTRATO],"Não encontrado")*tbMedições[[#This Row],[PERCENTUAL]] -> 42000 | L41: A medir
A42: MED041 | B42: {=_xlfn.XLOOKUP(tbMedições[[#This Row],[EMPRESA]]&tbMedições[[#This Row],[OBRA]],tbContratos[EMPRESA]&tbContratos[OBRA],tbContratos[CONTRATO_ID],"Não localizado")} -> CT007 | C42: MBUIATE | D42: PQSUL | E42: Projeto pré-executivo | F42: 0.2 | G42: 46032 | I42: =IF(tbMedições[[#This Row],[STATUS]]="Cancelada",DATE(1900,1,1),IF(OR(tbMedições[[#This Row],[STATUS]]="Pago",tbMedições[[#This Row],[STATUS]]="Medido"),tbMedições[[#This Row],[DATA MEDIÇÃO]],tbMedições[[#This Row],[DATA PREVISTA]])) -> 46032 | J42: =TEXT(tbMedições[[#This Row],[DATA REFERÊNCIA]],"aa/mm") -> 26/01 | K42: =_xlfn.XLOOKUP(tbMedições[[#This Row],[CONTRATO_ID]],tbContratos[CONTRATO_ID],tbContratos[VALOR CONTRATO],"Não encontrado")*tbMedições[[#This Row],[PERCENTUAL]] -> 42000 | L42: A medir
A43: MED042 | B43: {=_xlfn.XLOOKUP(tbMedições[[#This Row],[EMPRESA]]&tbMedições[[#This Row],[OBRA]],tbContratos[EMPRESA]&tbContratos[OBRA],tbContratos[CONTRATO_ID],"Não localizado")} -> CT007 | C43: MBUIATE | D43: PQSUL | E43: Projeto executivo | F43: 0.45 | G43: 46091 | I43: =IF(tbMedições[[#This Row],[STATUS]]="Cancelada",DATE(1900,1,1),IF(OR(tbMedições[[#This Row],[STATUS]]="Pago",tbMedições[[#This Row],[STATUS]]="Medido"),tbMedições[[#This Row],[DATA MEDIÇÃO]],tbMedições[[#This Row],[DATA PREVISTA]])) -> 46091 | J43: =TEXT(tbMedições[[#This Row],[DATA REFERÊNCIA]],"aa/mm") -> 26/03 | K43: =_xlfn.XLOOKUP(tbMedições[[#This Row],[CONTRATO_ID]],tbContratos[CONTRATO_ID],tbContratos[VALOR CONTRATO],"Não encontrado")*tbMedições[[#This Row],[PERCENTUAL]] -> 94500 | L43: A medir
A44: MED043 | B44: {=_xlfn.XLOOKUP(tbMedições[[#This Row],[EMPRESA]]&tbMedições[[#This Row],[OBRA]],tbContratos[EMPRESA]&tbContratos[OBRA],tbContratos[CONTRATO_ID],"Não localizado")} -> CT008 | C44: DALTON | D44: UNA | E44: Assessoria PL parte 1 | F44: 0.10258621 | H44: 46198 | I44: =IF(tbMedições[[#This Row],[STATUS]]="Cancelada",DATE(1900,1,1),IF(OR(tbMedições[[#This Row],[STATUS]]="Pago",tbMedições[[#This Row],[STATUS]]="Medido"),tbMedições[[#This Row],[DATA MEDIÇÃO]],tbMedições[[#This Row],[DATA PREVISTA]])) -> 46198 | J44: =TEXT(tbMedições[[#This Row],[DATA REFERÊNCIA]],"aa/mm") -> 26/06 | K44: =_xlfn.XLOOKUP(tbMedições[[#This Row],[CONTRATO_ID]],tbContratos[CONTRATO_ID],tbContratos[VALOR CONTRATO],"Não encontrado")*tbMedições[[#This Row],[PERCENTUAL]] -> 2975 | L44: Pago
A45: MED044 | B45: {=_xlfn.XLOOKUP(tbMedições[[#This Row],[EMPRESA]]&tbMedições[[#This Row],[OBRA]],tbContratos[EMPRESA]&tbContratos[OBRA],tbContratos[CONTRATO_ID],"Não localizado")} -> CT008 | C45: DALTON | D45: UNA | E45: Assessoria PL parte 2 | F45: 0.10258621 | G45: 46290 | I45: =IF(tbMedições[[#This Row],[STATUS]]="Cancelada",DATE(1900,1,1),IF(OR(tbMedições[[#This Row],[STATUS]]="Pago",tbMedições[[#This Row],[STATUS]]="Medido"),tbMedições[[#This Row],[DATA MEDIÇÃO]],tbMedições[[#This Row],[DATA PREVISTA]])) -> 46290 | J45: =TEXT(tbMedições[[#This Row],[DATA REFERÊNCIA]],"aa/mm") -> 26/09 | K45: =_xlfn.XLOOKUP(tbMedições[[#This Row],[CONTRATO_ID]],tbContratos[CONTRATO_ID],tbContratos[VALOR CONTRATO],"Não encontrado")*tbMedições[[#This Row],[PERCENTUAL]] -> 2975 | L45: A medir
A46: MED045 | B46: {=_xlfn.XLOOKUP(tbMedições[[#This Row],[EMPRESA]]&tbMedições[[#This Row],[OBRA]],tbContratos[EMPRESA]&tbContratos[OBRA],tbContratos[CONTRATO_ID],"Não localizado")} -> CT008 | C46: DALTON | D46: UNA | E46: Estudo preliminar | F46: 0.12974138 | H46: 46231 | I46: =IF(tbMedições[[#This Row],[STATUS]]="Cancelada",DATE(1900,1,1),IF(OR(tbMedições[[#This Row],[STATUS]]="Pago",tbMedições[[#This Row],[STATUS]]="Medido"),tbMedições[[#This Row],[DATA MEDIÇÃO]],tbMedições[[#This Row],[DATA PREVISTA]])) -> 46231 | J46: =TEXT(tbMedições[[#This Row],[DATA REFERÊNCIA]],"aa/mm") -> 26/07 | K46: =_xlfn.XLOOKUP(tbMedições[[#This Row],[CONTRATO_ID]],tbContratos[CONTRATO_ID],tbContratos[VALOR CONTRATO],"Não encontrado")*tbMedições[[#This Row],[PERCENTUAL]] -> 3762.5 | L46: Medido
A47: MED046 | B47: {=_xlfn.XLOOKUP(tbMedições[[#This Row],[EMPRESA]]&tbMedições[[#This Row],[OBRA]],tbContratos[EMPRESA]&tbContratos[OBRA],tbContratos[CONTRATO_ID],"Não localizado")} -> CT008 | C47: DALTON | D47: UNA | E47: Anteprojeto | F47: 0.12974138 | G47: 46262 | I47: =IF(tbMedições[[#This Row],[STATUS]]="Cancelada",DATE(1900,1,1),IF(OR(tbMedições[[#This Row],[STATUS]]="Pago",tbMedições[[#This Row],[STATUS]]="Medido"),tbMedições[[#This Row],[DATA MEDIÇÃO]],tbMedições[[#This Row],[DATA PREVISTA]])) -> 46262 | J47: =TEXT(tbMedições[[#This Row],[DATA REFERÊNCIA]],"aa/mm") -> 26/08 | K47: =_xlfn.XLOOKUP(tbMedições[[#This Row],[CONTRATO_ID]],tbContratos[CONTRATO_ID],tbContratos[VALOR CONTRATO],"Não encontrado")*tbMedições[[#This Row],[PERCENTUAL]] -> 3762.5 | L47: A medir
A48: MED047 | B48: {=_xlfn.XLOOKUP(tbMedições[[#This Row],[EMPRESA]]&tbMedições[[#This Row],[OBRA]],tbContratos[EMPRESA]&tbContratos[OBRA],tbContratos[CONTRATO_ID],"Não localizado")} -> CT008 | C48: DALTON | D48: UNA | E48: Executivo 1 | F48: 0.12974138 | G48: 46293 | I48: =IF(tbMedições[[#This Row],[STATUS]]="Cancelada",DATE(1900,1,1),IF(OR(tbMedições[[#This Row],[STATUS]]="Pago",tbMedições[[#This Row],[STATUS]]="Medido"),tbMedições[[#This Row],[DATA MEDIÇÃO]],tbMedições[[#This Row],[DATA PREVISTA]])) -> 46293 | J48: =TEXT(tbMedições[[#This Row],[DATA REFERÊNCIA]],"aa/mm") -> 26/09 | K48: =_xlfn.XLOOKUP(tbMedições[[#This Row],[CONTRATO_ID]],tbContratos[CONTRATO_ID],tbContratos[VALOR CONTRATO],"Não encontrado")*tbMedições[[#This Row],[PERCENTUAL]] -> 3762.5 | L48: A medir
A49: MED048 | B49: {=_xlfn.XLOOKUP(tbMedições[[#This Row],[EMPRESA]]&tbMedições[[#This Row],[OBRA]],tbContratos[EMPRESA]&tbContratos[OBRA],tbContratos[CONTRATO_ID],"Não localizado")} -> CT008 | C49: DALTON | D49: UNA | E49: Executivo 2 | F49: 0.12974138 | G49: 46323 | I49: =IF(tbMedições[[#This Row],[STATUS]]="Cancelada",DATE(1900,1,1),IF(OR(tbMedições[[#This Row],[STATUS]]="Pago",tbMedições[[#This Row],[STATUS]]="Medido"),tbMedições[[#This Row],[DATA MEDIÇÃO]],tbMedições[[#This Row],[DATA PREVISTA]])) -> 46323 | J49: =TEXT(tbMedições[[#This Row],[DATA REFERÊNCIA]],"aa/mm") -> 26/10 | K49: =_xlfn.XLOOKUP(tbMedições[[#This Row],[CONTRATO_ID]],tbContratos[CONTRATO_ID],tbContratos[VALOR CONTRATO],"Não encontrado")*tbMedições[[#This Row],[PERCENTUAL]] -> 3762.5 | L49: A medir
A50: MED049 | B50: {=_xlfn.XLOOKUP(tbMedições[[#This Row],[EMPRESA]]&tbMedições[[#This Row],[OBRA]],tbContratos[EMPRESA]&tbContratos[OBRA],tbContratos[CONTRATO_ID],"Não localizado")} -> CT008 | C50: DALTON | D50: UNA | E50: Fachada EP | F50: 0.091954023 | H50: 46231 | I50: =IF(tbMedições[[#This Row],[STATUS]]="Cancelada",DATE(1900,1,1),IF(OR(tbMedições[[#This Row],[STATUS]]="Pago",tbMedições[[#This Row],[STATUS]]="Medido"),tbMedições[[#This Row],[DATA MEDIÇÃO]],tbMedições[[#This Row],[DATA PREVISTA]])) -> 46231 | J50: =TEXT(tbMedições[[#This Row],[DATA REFERÊNCIA]],"aa/mm") -> 26/07 | K50: =_xlfn.XLOOKUP(tbMedições[[#This Row],[CONTRATO_ID]],tbContratos[CONTRATO_ID],tbContratos[VALOR CONTRATO],"Não encontrado")*tbMedições[[#This Row],[PERCENTUAL]] -> 2666.6667 | L50: Medido
A51: MED050 | B51: {=_xlfn.XLOOKUP(tbMedições[[#This Row],[EMPRESA]]&tbMedições[[#This Row],[OBRA]],tbContratos[EMPRESA]&tbContratos[OBRA],tbContratos[CONTRATO_ID],"Não localizado")} -> CT008 | C51: DALTON | D51: UNA | E51: Fachada AP | F51: 0.091954023 | G51: 46262 | I51: =IF(tbMedições[[#This Row],[STATUS]]="Cancelada",DATE(1900,1,1),IF(OR(tbMedições[[#This Row],[STATUS]]="Pago",tbMedições[[#This Row],[STATUS]]="Medido"),tbMedições[[#This Row],[DATA MEDIÇÃO]],tbMedições[[#This Row],[DATA PREVISTA]])) -> 46262 | J51: =TEXT(tbMedições[[#This Row],[DATA REFERÊNCIA]],"aa/mm") -> 26/08 | K51: =_xlfn.XLOOKUP(tbMedições[[#This Row],[CONTRATO_ID]],tbContratos[CONTRATO_ID],tbContratos[VALOR CONTRATO],"Não encontrado")*tbMedições[[#This Row],[PERCENTUAL]] -> 2666.6667 | L51: A medir
A52: MED051 | B52: {=_xlfn.XLOOKUP(tbMedições[[#This Row],[EMPRESA]]&tbMedições[[#This Row],[OBRA]],tbContratos[EMPRESA]&tbContratos[OBRA],tbContratos[CONTRATO_ID],"Não localizado")} -> CT008 | C52: DALTON | D52: UNA | E52: Fachada EX | F52: 0.091954023 | G52: 46293 | I52: =IF(tbMedições[[#This Row],[STATUS]]="Cancelada",DATE(1900,1,1),IF(OR(tbMedições[[#This Row],[STATUS]]="Pago",tbMedições[[#This Row],[STATUS]]="Medido"),tbMedições[[#This Row],[DATA MEDIÇÃO]],tbMedições[[#This Row],[DATA PREVISTA]])) -> 46293 | J52: =TEXT(tbMedições[[#This Row],[DATA REFERÊNCIA]],"aa/mm") -> 26/09 | K52: =_xlfn.XLOOKUP(tbMedições[[#This Row],[CONTRATO_ID]],tbContratos[CONTRATO_ID],tbContratos[VALOR CONTRATO],"Não encontrado")*tbMedições[[#This Row],[PERCENTUAL]] -> 2666.6667 | L52: A medir
A53: MED052 | B53: {=_xlfn.XLOOKUP(tbMedições[[#This Row],[EMPRESA]]&tbMedições[[#This Row],[OBRA]],tbContratos[EMPRESA]&tbContratos[OBRA],tbContratos[CONTRATO_ID],"Não localizado")} -> CT009 | C53: DALTON | D53: GAL | E53: Estudo preliminar | F53: 0.2 | H53: 46198 | I53: =IF(tbMedições[[#This Row],[STATUS]]="Cancelada",DATE(1900,1,1),IF(OR(tbMedições[[#This Row],[STATUS]]="Pago",tbMedições[[#This Row],[STATUS]]="Medido"),tbMedições[[#This Row],[DATA MEDIÇÃO]],tbMedições[[#This Row],[DATA PREVISTA]])) -> 46198 | J53: =TEXT(tbMedições[[#This Row],[DATA REFERÊNCIA]],"aa/mm") -> 26/06 | K53: =_xlfn.XLOOKUP(tbMedições[[#This Row],[CONTRATO_ID]],tbContratos[CONTRATO_ID],tbContratos[VALOR CONTRATO],"Não encontrado")*tbMedições[[#This Row],[PERCENTUAL]] -> 14000 | L53: Pago
A54: MED053 | B54: {=_xlfn.XLOOKUP(tbMedições[[#This Row],[EMPRESA]]&tbMedições[[#This Row],[OBRA]],tbContratos[EMPRESA]&tbContratos[OBRA],tbContratos[CONTRATO_ID],"Não localizado")} -> CT009 | C54: DALTON | D54: GAL | E54: Anteprojeto | F54: 0.2 | G54: 46259 | I54: =IF(tbMedições[[#This Row],[STATUS]]="Cancelada",DATE(1900,1,1),IF(OR(tbMedições[[#This Row],[STATUS]]="Pago",tbMedições[[#This Row],[STATUS]]="Medido"),tbMedições[[#This Row],[DATA MEDIÇÃO]],tbMedições[[#This Row],[DATA PREVISTA]])) -> 46259 | J54: =TEXT(tbMedições[[#This Row],[DATA REFERÊNCIA]],"aa/mm") -> 26/08 | K54: =_xlfn.XLOOKUP(tbMedições[[#This Row],[CONTRATO_ID]],tbContratos[CONTRATO_ID],tbContratos[VALOR CONTRATO],"Não encontrado")*tbMedições[[#This Row],[PERCENTUAL]] -> 14000 | L54: A medir
A55: MED054 | B55: {=_xlfn.XLOOKUP(tbMedições[[#This Row],[EMPRESA]]&tbMedições[[#This Row],[OBRA]],tbContratos[EMPRESA]&tbContratos[OBRA],tbContratos[CONTRATO_ID],"Não localizado")} -> CT009 | C55: DALTON | D55: GAL | E55: Projeto básico | F55: 0.2 | G55: 46320 | I55: =IF(tbMedições[[#This Row],[STATUS]]="Cancelada",DATE(1900,1,1),IF(OR(tbMedições[[#This Row],[STATUS]]="Pago",tbMedições[[#This Row],[STATUS]]="Medido"),tbMedições[[#This Row],[DATA MEDIÇÃO]],tbMedições[[#This Row],[DATA PREVISTA]])) -> 46320 | J55: =TEXT(tbMedições[[#This Row],[DATA REFERÊNCIA]],"aa/mm") -> 26/10 | K55: =_xlfn.XLOOKUP(tbMedições[[#This Row],[CONTRATO_ID]],tbContratos[CONTRATO_ID],tbContratos[VALOR CONTRATO],"Não encontrado")*tbMedições[[#This Row],[PERCENTUAL]] -> 14000 | L55: A medir
A56: MED055 | B56: {=_xlfn.XLOOKUP(tbMedições[[#This Row],[EMPRESA]]&tbMedições[[#This Row],[OBRA]],tbContratos[EMPRESA]&tbContratos[OBRA],tbContratos[CONTRATO_ID],"Não localizado")} -> CT009 | C56: DALTON | D56: GAL | E56: Executivo 1 | F56: 0.2 | G56: 46351 | I56: =IF(tbMedições[[#This Row],[STATUS]]="Cancelada",DATE(1900,1,1),IF(OR(tbMedições[[#This Row],[STATUS]]="Pago",tbMedições[[#This Row],[STATUS]]="Medido"),tbMedições[[#This Row],[DATA MEDIÇÃO]],tbMedições[[#This Row],[DATA PREVISTA]])) -> 46351 | J56: =TEXT(tbMedições[[#This Row],[DATA REFERÊNCIA]],"aa/mm") -> 26/11 | K56: =_xlfn.XLOOKUP(tbMedições[[#This Row],[CONTRATO_ID]],tbContratos[CONTRATO_ID],tbContratos[VALOR CONTRATO],"Não encontrado")*tbMedições[[#This Row],[PERCENTUAL]] -> 14000 | L56: A medir
A57: MED056 | B57: {=_xlfn.XLOOKUP(tbMedições[[#This Row],[EMPRESA]]&tbMedições[[#This Row],[OBRA]],tbContratos[EMPRESA]&tbContratos[OBRA],tbContratos[CONTRATO_ID],"Não localizado")} -> CT009 | C57: DALTON | D57: GAL | E57: Executivo 2 | F57: 0.2 | G57: 46381 | I57: =IF(tbMedições[[#This Row],[STATUS]]="Cancelada",DATE(1900,1,1),IF(OR(tbMedições[[#This Row],[STATUS]]="Pago",tbMedições[[#This Row],[STATUS]]="Medido"),tbMedições[[#This Row],[DATA MEDIÇÃO]],tbMedições[[#This Row],[DATA PREVISTA]])) -> 46381 | J57: =TEXT(tbMedições[[#This Row],[DATA REFERÊNCIA]],"aa/mm") -> 26/12 | K57: =_xlfn.XLOOKUP(tbMedições[[#This Row],[CONTRATO_ID]],tbContratos[CONTRATO_ID],tbContratos[VALOR CONTRATO],"Não encontrado")*tbMedições[[#This Row],[PERCENTUAL]] -> 14000 | L57: A medir
A58: MED057 | B58: {=_xlfn.XLOOKUP(tbMedições[[#This Row],[EMPRESA]]&tbMedições[[#This Row],[OBRA]],tbContratos[EMPRESA]&tbContratos[OBRA],tbContratos[CONTRATO_ID],"Não localizado")} -> CT010 | C58: KARINA | D58: ALT | E58: Entrada | F58: 0.17468354 | H58: 46184 | I58: =IF(tbMedições[[#This Row],[STATUS]]="Cancelada",DATE(1900,1,1),IF(OR(tbMedições[[#This Row],[STATUS]]="Pago",tbMedições[[#This Row],[STATUS]]="Medido"),tbMedições[[#This Row],[DATA MEDIÇÃO]],tbMedições[[#This Row],[DATA PREVISTA]])) -> 46184 | J58: =TEXT(tbMedições[[#This Row],[DATA REFERÊNCIA]],"aa/mm") -> 26/06 | K58: =_xlfn.XLOOKUP(tbMedições[[#This Row],[CONTRATO_ID]],tbContratos[CONTRATO_ID],tbContratos[VALOR CONTRATO],"Não encontrado")*tbMedições[[#This Row],[PERCENTUAL]] -> 6900 | L58: Pago
A59: MED058 | B59: {=_xlfn.XLOOKUP(tbMedições[[#This Row],[EMPRESA]]&tbMedições[[#This Row],[OBRA]],tbContratos[EMPRESA]&tbContratos[OBRA],tbContratos[CONTRATO_ID],"Não localizado")} -> CT010 | C59: KARINA | D59: ALT | E59: Projeto preliminar | F59: 0.34936709 | H59: 46184 | I59: =IF(tbMedições[[#This Row],[STATUS]]="Cancelada",DATE(1900,1,1),IF(OR(tbMedições[[#This Row],[STATUS]]="Pago",tbMedições[[#This Row],[STATUS]]="Medido"),tbMedições[[#This Row],[DATA MEDIÇÃO]],tbMedições[[#This Row],[DATA PREVISTA]])) -> 46184 | J59: =TEXT(tbMedições[[#This Row],[DATA REFERÊNCIA]],"aa/mm") -> 26/06 | K59: =_xlfn.XLOOKUP(tbMedições[[#This Row],[CONTRATO_ID]],tbContratos[CONTRATO_ID],tbContratos[VALOR CONTRATO],"Não encontrado")*tbMedições[[#This Row],[PERCENTUAL]] -> 13800 | L59: Pago
A60: MED059 | B60: {=_xlfn.XLOOKUP(tbMedições[[#This Row],[EMPRESA]]&tbMedições[[#This Row],[OBRA]],tbContratos[EMPRESA]&tbContratos[OBRA],tbContratos[CONTRATO_ID],"Não localizado")} -> CT010 | C60: KARINA | D60: ALT | E60: Projeto pré-executivo | F60: 0.17468354 | G60: 46254 | I60: =IF(tbMedições[[#This Row],[STATUS]]="Cancelada",DATE(1900,1,1),IF(OR(tbMedições[[#This Row],[STATUS]]="Pago",tbMedições[[#This Row],[STATUS]]="Medido"),tbMedições[[#This Row],[DATA MEDIÇÃO]],tbMedições[[#This Row],[DATA PREVISTA]])) -> 46254 | J60: =TEXT(tbMedições[[#This Row],[DATA REFERÊNCIA]],"aa/mm") -> 26/08 | K60: =_xlfn.XLOOKUP(tbMedições[[#This Row],[CONTRATO_ID]],tbContratos[CONTRATO_ID],tbContratos[VALOR CONTRATO],"Não encontrado")*tbMedições[[#This Row],[PERCENTUAL]] -> 6900 | L60: A medir
A61: MED060 | B61: {=_xlfn.XLOOKUP(tbMedições[[#This Row],[EMPRESA]]&tbMedições[[#This Row],[OBRA]],tbContratos[EMPRESA]&tbContratos[OBRA],tbContratos[CONTRATO_ID],"Não localizado")} -> CT010 | C61: KARINA | D61: ALT | E61: Projeto executivo | F61: 0.17468354 | G61: 46315 | I61: =IF(tbMedições[[#This Row],[STATUS]]="Cancelada",DATE(1900,1,1),IF(OR(tbMedições[[#This Row],[STATUS]]="Pago",tbMedições[[#This Row],[STATUS]]="Medido"),tbMedições[[#This Row],[DATA MEDIÇÃO]],tbMedições[[#This Row],[DATA PREVISTA]])) -> 46315 | J61: =TEXT(tbMedições[[#This Row],[DATA REFERÊNCIA]],"aa/mm") -> 26/10 | K61: =_xlfn.XLOOKUP(tbMedições[[#This Row],[CONTRATO_ID]],tbContratos[CONTRATO_ID],tbContratos[VALOR CONTRATO],"Não encontrado")*tbMedições[[#This Row],[PERCENTUAL]] -> 6900 | L61: A medir
A62: MED061 | B62: {=_xlfn.XLOOKUP(tbMedições[[#This Row],[EMPRESA]]&tbMedições[[#This Row],[OBRA]],tbContratos[EMPRESA]&tbContratos[OBRA],tbContratos[CONTRATO_ID],"Não localizado")} -> CT010 | C62: KARINA | D62: ALT | E62: Aditivo pós PL | F62: 0.12658228 | G62: 46376 | I62: =IF(tbMedições[[#This Row],[STATUS]]="Cancelada",DATE(1900,1,1),IF(OR(tbMedições[[#This Row],[STATUS]]="Pago",tbMedições[[#This Row],[STATUS]]="Medido"),tbMedições[[#This Row],[DATA MEDIÇÃO]],tbMedições[[#This Row],[DATA PREVISTA]])) -> 46376 | J62: =TEXT(tbMedições[[#This Row],[DATA REFERÊNCIA]],"aa/mm") -> 26/12 | K62: =_xlfn.XLOOKUP(tbMedições[[#This Row],[CONTRATO_ID]],tbContratos[CONTRATO_ID],tbContratos[VALOR CONTRATO],"Não encontrado")*tbMedições[[#This Row],[PERCENTUAL]] -> 5000 | L62: A medir
A63: MED062 | B63: {=_xlfn.XLOOKUP(tbMedições[[#This Row],[EMPRESA]]&tbMedições[[#This Row],[OBRA]],tbContratos[EMPRESA]&tbContratos[OBRA],tbContratos[CONTRATO_ID],"Não localizado")} -> CT011 | C63: GEOMETA | D63: ALT | E63: Sondagem | F63: 1 | H63: 46175 | I63: =IF(tbMedições[[#This Row],[STATUS]]="Cancelada",DATE(1900,1,1),IF(OR(tbMedições[[#This Row],[STATUS]]="Pago",tbMedições[[#This Row],[STATUS]]="Medido"),tbMedições[[#This Row],[DATA MEDIÇÃO]],tbMedições[[#This Row],[DATA PREVISTA]])) -> 46175 | J63: =TEXT(tbMedições[[#This Row],[DATA REFERÊNCIA]],"aa/mm") -> 26/06 | K63: =_xlfn.XLOOKUP(tbMedições[[#This Row],[CONTRATO_ID]],tbContratos[CONTRATO_ID],tbContratos[VALOR CONTRATO],"Não encontrado")*tbMedições[[#This Row],[PERCENTUAL]] -> 17500.65 | L63: Pago
A64: MED063 | B64: {=_xlfn.XLOOKUP(tbMedições[[#This Row],[EMPRESA]]&tbMedições[[#This Row],[OBRA]],tbContratos[EMPRESA]&tbContratos[OBRA],tbContratos[CONTRATO_ID],"Não localizado")} -> CT012 | C64: GEOMETA | D64: GAL | E64: Sondagem | F64: 1 | H64: 46206 | I64: =IF(tbMedições[[#This Row],[STATUS]]="Cancelada",DATE(1900,1,1),IF(OR(tbMedições[[#This Row],[STATUS]]="Pago",tbMedições[[#This Row],[STATUS]]="Medido"),tbMedições[[#This Row],[DATA MEDIÇÃO]],tbMedições[[#This Row],[DATA PREVISTA]])) -> 46206 | J64: =TEXT(tbMedições[[#This Row],[DATA REFERÊNCIA]],"aa/mm") -> 26/07 | K64: =_xlfn.XLOOKUP(tbMedições[[#This Row],[CONTRATO_ID]],tbContratos[CONTRATO_ID],tbContratos[VALOR CONTRATO],"Não encontrado")*tbMedições[[#This Row],[PERCENTUAL]] -> 25313.28 | L64: Pago
A65: MED064 | B65: {=_xlfn.XLOOKUP(tbMedições[[#This Row],[EMPRESA]]&tbMedições[[#This Row],[OBRA]],tbContratos[EMPRESA]&tbContratos[OBRA],tbContratos[CONTRATO_ID],"Não localizado")} -> CT013 | C65: GEOMETA | D65: PQSUL | E65: Sondagem | F65: 1 | H65: 46213 | I65: =IF(tbMedições[[#This Row],[STATUS]]="Cancelada",DATE(1900,1,1),IF(OR(tbMedições[[#This Row],[STATUS]]="Pago",tbMedições[[#This Row],[STATUS]]="Medido"),tbMedições[[#This Row],[DATA MEDIÇÃO]],tbMedições[[#This Row],[DATA PREVISTA]])) -> 46213 | J65: =TEXT(tbMedições[[#This Row],[DATA REFERÊNCIA]],"aa/mm") -> 26/07 | K65: =_xlfn.XLOOKUP(tbMedições[[#This Row],[CONTRATO_ID]],tbContratos[CONTRATO_ID],tbContratos[VALOR CONTRATO],"Não encontrado")*tbMedições[[#This Row],[PERCENTUAL]] -> 23556.1 | L65: Medido
A66: MED065 | B66: {=_xlfn.XLOOKUP(tbMedições[[#This Row],[EMPRESA]]&tbMedições[[#This Row],[OBRA]],tbContratos[EMPRESA]&tbContratos[OBRA],tbContratos[CONTRATO_ID],"Não localizado")} -> CT014 | C66: VANIA | D66: ALT | E66: Pipa para sondagem | F66: 1 | H66: 46175 | I66: =IF(tbMedições[[#This Row],[STATUS]]="Cancelada",DATE(1900,1,1),IF(OR(tbMedições[[#This Row],[STATUS]]="Pago",tbMedições[[#This Row],[STATUS]]="Medido"),tbMedições[[#This Row],[DATA MEDIÇÃO]],tbMedições[[#This Row],[DATA PREVISTA]])) -> 46175 | J66: =TEXT(tbMedições[[#This Row],[DATA REFERÊNCIA]],"aa/mm") -> 26/06 | K66: =_xlfn.XLOOKUP(tbMedições[[#This Row],[CONTRATO_ID]],tbContratos[CONTRATO_ID],tbContratos[VALOR CONTRATO],"Não encontrado")*tbMedições[[#This Row],[PERCENTUAL]] -> 1800 | L66: Pago
A67: MED066 | B67: {=_xlfn.XLOOKUP(tbMedições[[#This Row],[EMPRESA]]&tbMedições[[#This Row],[OBRA]],tbContratos[EMPRESA]&tbContratos[OBRA],tbContratos[CONTRATO_ID],"Não localizado")} -> CT015 | C67: VANIA | D67: GAL | E67: Pipa para sondagem | F67: 1 | H67: 46197 | I67: =IF(tbMedições[[#This Row],[STATUS]]="Cancelada",DATE(1900,1,1),IF(OR(tbMedições[[#This Row],[STATUS]]="Pago",tbMedições[[#This Row],[STATUS]]="Medido"),tbMedições[[#This Row],[DATA MEDIÇÃO]],tbMedições[[#This Row],[DATA PREVISTA]])) -> 46197 | J67: =TEXT(tbMedições[[#This Row],[DATA REFERÊNCIA]],"aa/mm") -> 26/06 | K67: =_xlfn.XLOOKUP(tbMedições[[#This Row],[CONTRATO_ID]],tbContratos[CONTRATO_ID],tbContratos[VALOR CONTRATO],"Não encontrado")*tbMedições[[#This Row],[PERCENTUAL]] -> 3600 | L67: Pago
A68: MED067 | B68: {=_xlfn.XLOOKUP(tbMedições[[#This Row],[EMPRESA]]&tbMedições[[#This Row],[OBRA]],tbContratos[EMPRESA]&tbContratos[OBRA],tbContratos[CONTRATO_ID],"Não localizado")} -> CT016 | C68: JP SERVIÇOS | D68: ALT | E68: Vigia para sondagem | F68: 1 | H68: 46170 | I68: =IF(tbMedições[[#This Row],[STATUS]]="Cancelada",DATE(1900,1,1),IF(OR(tbMedições[[#This Row],[STATUS]]="Pago",tbMedições[[#This Row],[STATUS]]="Medido"),tbMedições[[#This Row],[DATA MEDIÇÃO]],tbMedições[[#This Row],[DATA PREVISTA]])) -> 46170 | J68: =TEXT(tbMedições[[#This Row],[DATA REFERÊNCIA]],"aa/mm") -> 26/05 | K68: =_xlfn.XLOOKUP(tbMedições[[#This Row],[CONTRATO_ID]],tbContratos[CONTRATO_ID],tbContratos[VALOR CONTRATO],"Não encontrado")*tbMedições[[#This Row],[PERCENTUAL]] -> 2580 | L68: Pago
A69: MED068 | B69: {=_xlfn.XLOOKUP(tbMedições[[#This Row],[EMPRESA]]&tbMedições[[#This Row],[OBRA]],tbContratos[EMPRESA]&tbContratos[OBRA],tbContratos[CONTRATO_ID],"Não localizado")} -> CT017 | C69: JP SERVIÇOS | D69: GAL | E69: Vigia para sondagem | F69: 1 | H69: 46199 | I69: =IF(tbMedições[[#This Row],[STATUS]]="Cancelada",DATE(1900,1,1),IF(OR(tbMedições[[#This Row],[STATUS]]="Pago",tbMedições[[#This Row],[STATUS]]="Medido"),tbMedições[[#This Row],[DATA MEDIÇÃO]],tbMedições[[#This Row],[DATA PREVISTA]])) -> 46199 | J69: =TEXT(tbMedições[[#This Row],[DATA REFERÊNCIA]],"aa/mm") -> 26/06 | K69: =_xlfn.XLOOKUP(tbMedições[[#This Row],[CONTRATO_ID]],tbContratos[CONTRATO_ID],tbContratos[VALOR CONTRATO],"Não encontrado")*tbMedições[[#This Row],[PERCENTUAL]] -> 3640 | L69: Pago
A70: MED069 | B70: {=_xlfn.XLOOKUP(tbMedições[[#This Row],[EMPRESA]]&tbMedições[[#This Row],[OBRA]],tbContratos[EMPRESA]&tbContratos[OBRA],tbContratos[CONTRATO_ID],"Não localizado")} -> CT018 | C70: IDEAL | D70: ALT | E70: Levantamento + unificação | F70: 0.43956044 | H70: 45140 | I70: =IF(tbMedições[[#This Row],[STATUS]]="Cancelada",DATE(1900,1,1),IF(OR(tbMedições[[#This Row],[STATUS]]="Pago",tbMedições[[#This Row],[STATUS]]="Medido"),tbMedições[[#This Row],[DATA MEDIÇÃO]],tbMedições[[#This Row],[DATA PREVISTA]])) -> 45140 | J70: =TEXT(tbMedições[[#This Row],[DATA REFERÊNCIA]],"aa/mm") -> 23/08 | K70: =_xlfn.XLOOKUP(tbMedições[[#This Row],[CONTRATO_ID]],tbContratos[CONTRATO_ID],tbContratos[VALOR CONTRATO],"Não encontrado")*tbMedições[[#This Row],[PERCENTUAL]] -> 2000 | L70: Pago
A71: MED070 | B71: {=_xlfn.XLOOKUP(tbMedições[[#This Row],[EMPRESA]]&tbMedições[[#This Row],[OBRA]],tbContratos[EMPRESA]&tbContratos[OBRA],tbContratos[CONTRATO_ID],"Não localizado")} -> CT018 | C71: IDEAL | D71: ALT | E71: Levantamento + unificação | F71: 0.31868132 | H71: 45140 | I71: =IF(tbMedições[[#This Row],[STATUS]]="Cancelada",DATE(1900,1,1),IF(OR(tbMedições[[#This Row],[STATUS]]="Pago",tbMedições[[#This Row],[STATUS]]="Medido"),tbMedições[[#This Row],[DATA MEDIÇÃO]],tbMedições[[#This Row],[DATA PREVISTA]])) -> 45140 | J71: =TEXT(tbMedições[[#This Row],[DATA REFERÊNCIA]],"aa/mm") -> 23/08 | K71: =_xlfn.XLOOKUP(tbMedições[[#This Row],[CONTRATO_ID]],tbContratos[CONTRATO_ID],tbContratos[VALOR CONTRATO],"Não encontrado")*tbMedições[[#This Row],[PERCENTUAL]] -> 1450 | L71: Pago
A72: MED071 | B72: {=_xlfn.XLOOKUP(tbMedições[[#This Row],[EMPRESA]]&tbMedições[[#This Row],[OBRA]],tbContratos[EMPRESA]&tbContratos[OBRA],tbContratos[CONTRATO_ID],"Não localizado")} -> CT018 | C72: IDEAL | D72: ALT | E72: Levantamento + unificação | F72: 0.24175824 | H72: 45804 | I72: =IF(tbMedições[[#This Row],[STATUS]]="Cancelada",DATE(1900,1,1),IF(OR(tbMedições[[#This Row],[STATUS]]="Pago",tbMedições[[#This Row],[STATUS]]="Medido"),tbMedições[[#This Row],[DATA MEDIÇÃO]],tbMedições[[#This Row],[DATA PREVISTA]])) -> 45804 | J72: =TEXT(tbMedições[[#This Row],[DATA REFERÊNCIA]],"aa/mm") -> 25/05 | K72: =_xlfn.XLOOKUP(tbMedições[[#This Row],[CONTRATO_ID]],tbContratos[CONTRATO_ID],tbContratos[VALOR CONTRATO],"Não encontrado")*tbMedições[[#This Row],[PERCENTUAL]] -> 1100 | L72: Pago
A73: MED072 | B73: {=_xlfn.XLOOKUP(tbMedições[[#This Row],[EMPRESA]]&tbMedições[[#This Row],[OBRA]],tbContratos[EMPRESA]&tbContratos[OBRA],tbContratos[CONTRATO_ID],"Não localizado")} -> CT019 | C73: GEOMAP | D73: GAL | E73: Levantamento + unificação | F73: 1 | H73: 46072 | I73: =IF(tbMedições[[#This Row],[STATUS]]="Cancelada",DATE(1900,1,1),IF(OR(tbMedições[[#This Row],[STATUS]]="Pago",tbMedições[[#This Row],[STATUS]]="Medido"),tbMedições[[#This Row],[DATA MEDIÇÃO]],tbMedições[[#This Row],[DATA PREVISTA]])) -> 46072 | J73: =TEXT(tbMedições[[#This Row],[DATA REFERÊNCIA]],"aa/mm") -> 26/02 | K73: =_xlfn.XLOOKUP(tbMedições[[#This Row],[CONTRATO_ID]],tbContratos[CONTRATO_ID],tbContratos[VALOR CONTRATO],"Não encontrado")*tbMedições[[#This Row],[PERCENTUAL]] -> 2850 | L73: Pago
A74: MED073 | B74: {=_xlfn.XLOOKUP(tbMedições[[#This Row],[EMPRESA]]&tbMedições[[#This Row],[OBRA]],tbContratos[EMPRESA]&tbContratos[OBRA],tbContratos[CONTRATO_ID],"Não localizado")} -> CT020 | C74: GEOMAP | D74: PQSUL | E74: Levantamento | F74: 1 | H74: 46072 | I74: =IF(tbMedições[[#This Row],[STATUS]]="Cancelada",DATE(1900,1,1),IF(OR(tbMedições[[#This Row],[STATUS]]="Pago",tbMedições[[#This Row],[STATUS]]="Medido"),tbMedições[[#This Row],[DATA MEDIÇÃO]],tbMedições[[#This Row],[DATA PREVISTA]])) -> 46072 | J74: =TEXT(tbMedições[[#This Row],[DATA REFERÊNCIA]],"aa/mm") -> 26/02 | K74: =_xlfn.XLOOKUP(tbMedições[[#This Row],[CONTRATO_ID]],tbContratos[CONTRATO_ID],tbContratos[VALOR CONTRATO],"Não encontrado")*tbMedições[[#This Row],[PERCENTUAL]] -> 1300 | L74: Pago
A75: MED074 | B75: {=_xlfn.XLOOKUP(tbMedições[[#This Row],[EMPRESA]]&tbMedições[[#This Row],[OBRA]],tbContratos[EMPRESA]&tbContratos[OBRA],tbContratos[CONTRATO_ID],"Não localizado")} -> CT021 | C75: GEOMAP | D75: UNA | E75: Levantamento | F75: 1 | H75: 46072 | I75: =IF(tbMedições[[#This Row],[STATUS]]="Cancelada",DATE(1900,1,1),IF(OR(tbMedições[[#This Row],[STATUS]]="Pago",tbMedições[[#This Row],[STATUS]]="Medido"),tbMedições[[#This Row],[DATA MEDIÇÃO]],tbMedições[[#This Row],[DATA PREVISTA]])) -> 46072 | J75: =TEXT(tbMedições[[#This Row],[DATA REFERÊNCIA]],"aa/mm") -> 26/02 | K75: =_xlfn.XLOOKUP(tbMedições[[#This Row],[CONTRATO_ID]],tbContratos[CONTRATO_ID],tbContratos[VALOR CONTRATO],"Não encontrado")*tbMedições[[#This Row],[PERCENTUAL]] -> 1100 | L75: Pago
A76: MED075 | B76: {=_xlfn.XLOOKUP(tbMedições[[#This Row],[EMPRESA]]&tbMedições[[#This Row],[OBRA]],tbContratos[EMPRESA]&tbContratos[OBRA],tbContratos[CONTRATO_ID],"Não localizado")} -> CT022 | C76: GEOMAP | D76: STM | E76: Levantamento | F76: 1 | G76: 46254 | I76: =IF(tbMedições[[#This Row],[STATUS]]="Cancelada",DATE(1900,1,1),IF(OR(tbMedições[[#This Row],[STATUS]]="Pago",tbMedições[[#This Row],[STATUS]]="Medido"),tbMedições[[#This Row],[DATA MEDIÇÃO]],tbMedições[[#This Row],[DATA PREVISTA]])) -> 46254 | J76: =TEXT(tbMedições[[#This Row],[DATA REFERÊNCIA]],"aa/mm") -> 26/08 | K76: =_xlfn.XLOOKUP(tbMedições[[#This Row],[CONTRATO_ID]],tbContratos[CONTRATO_ID],tbContratos[VALOR CONTRATO],"Não encontrado")*tbMedições[[#This Row],[PERCENTUAL]] -> 2635 | L76: Em andamento
A77: MED076 | B77: {=_xlfn.XLOOKUP(tbMedições[[#This Row],[EMPRESA]]&tbMedições[[#This Row],[OBRA]],tbContratos[EMPRESA]&tbContratos[OBRA],tbContratos[CONTRATO_ID],"Não localizado")} -> CT023 | C77: GEOMAP | D77: SEFAZ | E77: Levantamento | F77: 1 | G77: 46285 | I77: =IF(tbMedições[[#This Row],[STATUS]]="Cancelada",DATE(1900,1,1),IF(OR(tbMedições[[#This Row],[STATUS]]="Pago",tbMedições[[#This Row],[STATUS]]="Medido"),tbMedições[[#This Row],[DATA MEDIÇÃO]],tbMedições[[#This Row],[DATA PREVISTA]])) -> 46285 | J77: =TEXT(tbMedições[[#This Row],[DATA REFERÊNCIA]],"aa/mm") -> 26/09 | K77: =_xlfn.XLOOKUP(tbMedições[[#This Row],[CONTRATO_ID]],tbContratos[CONTRATO_ID],tbContratos[VALOR CONTRATO],"Não encontrado")*tbMedições[[#This Row],[PERCENTUAL]] -> 1800 | L77: Em andamento
A78: MED077 | B78: {=_xlfn.XLOOKUP(tbMedições[[#This Row],[EMPRESA]]&tbMedições[[#This Row],[OBRA]],tbContratos[EMPRESA]&tbContratos[OBRA],tbContratos[CONTRATO_ID],"Não localizado")} -> CT024 | C78: GÊMEAS | D78: UNA | E78: Desenvolvimento PL | F78: 0.5 | H78: 46066 | I78: =IF(tbMedições[[#This Row],[STATUS]]="Cancelada",DATE(1900,1,1),IF(OR(tbMedições[[#This Row],[STATUS]]="Pago",tbMedições[[#This Row],[STATUS]]="Medido"),tbMedições[[#This Row],[DATA MEDIÇÃO]],tbMedições[[#This Row],[DATA PREVISTA]])) -> 46066 | J78: =TEXT(tbMedições[[#This Row],[DATA REFERÊNCIA]],"aa/mm") -> 26/02 | K78: =_xlfn.XLOOKUP(tbMedições[[#This Row],[CONTRATO_ID]],tbContratos[CONTRATO_ID],tbContratos[VALOR CONTRATO],"Não encontrado")*tbMedições[[#This Row],[PERCENTUAL]] -> 20000 | L78: Pago
A79: MED078 | B79: {=_xlfn.XLOOKUP(tbMedições[[#This Row],[EMPRESA]]&tbMedições[[#This Row],[OBRA]],tbContratos[EMPRESA]&tbContratos[OBRA],tbContratos[CONTRATO_ID],"Não localizado")} -> CT024 | C79: GÊMEAS | D79: UNA | E79: Acompanhamento PMU e Habite-se | F79: 0.5 | G79: 46285 | I79: =IF(tbMedições[[#This Row],[STATUS]]="Cancelada",DATE(1900,1,1),IF(OR(tbMedições[[#This Row],[STATUS]]="Pago",tbMedições[[#This Row],[STATUS]]="Medido"),tbMedições[[#This Row],[DATA MEDIÇÃO]],tbMedições[[#This Row],[DATA PREVISTA]])) -> 46285 | J79: =TEXT(tbMedições[[#This Row],[DATA REFERÊNCIA]],"aa/mm") -> 26/09 | K79: =_xlfn.XLOOKUP(tbMedições[[#This Row],[CONTRATO_ID]],tbContratos[CONTRATO_ID],tbContratos[VALOR CONTRATO],"Não encontrado")*tbMedições[[#This Row],[PERCENTUAL]] -> 20000 | L79: Em andamento
A80: MED079 | B80: {=_xlfn.XLOOKUP(tbMedições[[#This Row],[EMPRESA]]&tbMedições[[#This Row],[OBRA]],tbContratos[EMPRESA]&tbContratos[OBRA],tbContratos[CONTRATO_ID],"Não localizado")} -> CT025 | C80: EMMIG | D80: UNA | E80: Anteprojeto | F80: 0.5 | H80: 46038 | I80: =IF(tbMedições[[#This Row],[STATUS]]="Cancelada",DATE(1900,1,1),IF(OR(tbMedições[[#This Row],[STATUS]]="Pago",tbMedições[[#This Row],[STATUS]]="Medido"),tbMedições[[#This Row],[DATA MEDIÇÃO]],tbMedições[[#This Row],[DATA PREVISTA]])) -> 46038 | J80: =TEXT(tbMedições[[#This Row],[DATA REFERÊNCIA]],"aa/mm") -> 26/01 | K80: =_xlfn.XLOOKUP(tbMedições[[#This Row],[CONTRATO_ID]],tbContratos[CONTRATO_ID],tbContratos[VALOR CONTRATO],"Não encontrado")*tbMedições[[#This Row],[PERCENTUAL]] -> 6500 | L80: Pago
A81: MED080 | B81: {=_xlfn.XLOOKUP(tbMedições[[#This Row],[EMPRESA]]&tbMedições[[#This Row],[OBRA]],tbContratos[EMPRESA]&tbContratos[OBRA],tbContratos[CONTRATO_ID],"Não localizado")} -> CT025 | C81: EMMIG | D81: UNA | E81: Executivo | F81: 0.5 | G81: 46315 | I81: =IF(tbMedições[[#This Row],[STATUS]]="Cancelada",DATE(1900,1,1),IF(OR(tbMedições[[#This Row],[STATUS]]="Pago",tbMedições[[#This Row],[STATUS]]="Medido"),tbMedições[[#This Row],[DATA MEDIÇÃO]],tbMedições[[#This Row],[DATA PREVISTA]])) -> 46315 | J81: =TEXT(tbMedições[[#This Row],[DATA REFERÊNCIA]],"aa/mm") -> 26/10 | K81: =_xlfn.XLOOKUP(tbMedições[[#This Row],[CONTRATO_ID]],tbContratos[CONTRATO_ID],tbContratos[VALOR CONTRATO],"Não encontrado")*tbMedições[[#This Row],[PERCENTUAL]] -> 6500 | L81: Em andamento
A82: MED081 | B82: {=_xlfn.XLOOKUP(tbMedições[[#This Row],[EMPRESA]]&tbMedições[[#This Row],[OBRA]],tbContratos[EMPRESA]&tbContratos[OBRA],tbContratos[CONTRATO_ID],"Não localizado")} -> CT026 | C82: GEOMETRIA | D82: ALT | E82: Anteprojeto | F82: 0.5 | G82: 46315 | I82: =IF(tbMedições[[#This Row],[STATUS]]="Cancelada",DATE(1900,1,1),IF(OR(tbMedições[[#This Row],[STATUS]]="Pago",tbMedições[[#This Row],[STATUS]]="Medido"),tbMedições[[#This Row],[DATA MEDIÇÃO]],tbMedições[[#This Row],[DATA PREVISTA]])) -> 46315 | J82: =TEXT(tbMedições[[#This Row],[DATA REFERÊNCIA]],"aa/mm") -> 26/10 | K82: =_xlfn.XLOOKUP(tbMedições[[#This Row],[CONTRATO_ID]],tbContratos[CONTRATO_ID],tbContratos[VALOR CONTRATO],"Não encontrado")*tbMedições[[#This Row],[PERCENTUAL]] -> 12500 | L82: A fazer
A83: MED082 | B83: {=_xlfn.XLOOKUP(tbMedições[[#This Row],[EMPRESA]]&tbMedições[[#This Row],[OBRA]],tbContratos[EMPRESA]&tbContratos[OBRA],tbContratos[CONTRATO_ID],"Não localizado")} -> CT026 | C83: GEOMETRIA | D83: ALT | E83: Executivo | F83: 0.5 | G83: 46042 | I83: =IF(tbMedições[[#This Row],[STATUS]]="Cancelada",DATE(1900,1,1),IF(OR(tbMedições[[#This Row],[STATUS]]="Pago",tbMedições[[#This Row],[STATUS]]="Medido"),tbMedições[[#This Row],[DATA MEDIÇÃO]],tbMedições[[#This Row],[DATA PREVISTA]])) -> 46042 | J83: =TEXT(tbMedições[[#This Row],[DATA REFERÊNCIA]],"aa/mm") -> 26/01 | K83: =_xlfn.XLOOKUP(tbMedições[[#This Row],[CONTRATO_ID]],tbContratos[CONTRATO_ID],tbContratos[VALOR CONTRATO],"Não encontrado")*tbMedições[[#This Row],[PERCENTUAL]] -> 12500 | L83: A fazer
A84: MED083 | B84: {=_xlfn.XLOOKUP(tbMedições[[#This Row],[EMPRESA]]&tbMedições[[#This Row],[OBRA]],tbContratos[EMPRESA]&tbContratos[OBRA],tbContratos[CONTRATO_ID],"Não localizado")} -> CT028 | C84: GEOMETRIA | D84: PQSUL | E84: Anteprojeto | F84: 0.5 | G84: 46376 | I84: =IF(tbMedições[[#This Row],[STATUS]]="Cancelada",DATE(1900,1,1),IF(OR(tbMedições[[#This Row],[STATUS]]="Pago",tbMedições[[#This Row],[STATUS]]="Medido"),tbMedições[[#This Row],[DATA MEDIÇÃO]],tbMedições[[#This Row],[DATA PREVISTA]])) -> 46376 | J84: =TEXT(tbMedições[[#This Row],[DATA REFERÊNCIA]],"aa/mm") -> 26/12 | K84: =_xlfn.XLOOKUP(tbMedições[[#This Row],[CONTRATO_ID]],tbContratos[CONTRATO_ID],tbContratos[VALOR CONTRATO],"Não encontrado")*tbMedições[[#This Row],[PERCENTUAL]] -> 15000 | L84: A fazer
A85: MED084 | B85: {=_xlfn.XLOOKUP(tbMedições[[#This Row],[EMPRESA]]&tbMedições[[#This Row],[OBRA]],tbContratos[EMPRESA]&tbContratos[OBRA],tbContratos[CONTRATO_ID],"Não localizado")} -> CT028 | C85: GEOMETRIA | D85: PQSUL | E85: Executivo | F85: 0.5 | G85: 46466 | I85: =IF(tbMedições[[#This Row],[STATUS]]="Cancelada",DATE(1900,1,1),IF(OR(tbMedições[[#This Row],[STATUS]]="Pago",tbMedições[[#This Row],[STATUS]]="Medido"),tbMedições[[#This Row],[DATA MEDIÇÃO]],tbMedições[[#This Row],[DATA PREVISTA]])) -> 46466 | J85: =TEXT(tbMedições[[#This Row],[DATA REFERÊNCIA]],"aa/mm") -> 27/03 | K85: =_xlfn.XLOOKUP(tbMedições[[#This Row],[CONTRATO_ID]],tbContratos[CONTRATO_ID],tbContratos[VALOR CONTRATO],"Não encontrado")*tbMedições[[#This Row],[PERCENTUAL]] -> 15000 | L85: A fazer
A86: MED085 | B86: {=_xlfn.XLOOKUP(tbMedições[[#This Row],[EMPRESA]]&tbMedições[[#This Row],[OBRA]],tbContratos[EMPRESA]&tbContratos[OBRA],tbContratos[CONTRATO_ID],"Não localizado")} -> CT029 | C86: GEOMETRIA | D86: UNA | E86: Anteprojeto | F86: 0.5 | G86: 46315 | I86: =IF(tbMedições[[#This Row],[STATUS]]="Cancelada",DATE(1900,1,1),IF(OR(tbMedições[[#This Row],[STATUS]]="Pago",tbMedições[[#This Row],[STATUS]]="Medido"),tbMedições[[#This Row],[DATA MEDIÇÃO]],tbMedições[[#This Row],[DATA PREVISTA]])) -> 46315 | J86: =TEXT(tbMedições[[#This Row],[DATA REFERÊNCIA]],"aa/mm") -> 26/10 | K86: =_xlfn.XLOOKUP(tbMedições[[#This Row],[CONTRATO_ID]],tbContratos[CONTRATO_ID],tbContratos[VALOR CONTRATO],"Não encontrado")*tbMedições[[#This Row],[PERCENTUAL]] -> 5000 | L86: A fazer
A87: MED086 | B87: {=_xlfn.XLOOKUP(tbMedições[[#This Row],[EMPRESA]]&tbMedições[[#This Row],[OBRA]],tbContratos[EMPRESA]&tbContratos[OBRA],tbContratos[CONTRATO_ID],"Não localizado")} -> CT029 | C87: GEOMETRIA | D87: UNA | E87: Executivo | F87: 0.5 | G87: 46042 | I87: =IF(tbMedições[[#This Row],[STATUS]]="Cancelada",DATE(1900,1,1),IF(OR(tbMedições[[#This Row],[STATUS]]="Pago",tbMedições[[#This Row],[STATUS]]="Medido"),tbMedições[[#This Row],[DATA MEDIÇÃO]],tbMedições[[#This Row],[DATA PREVISTA]])) -> 46042 | J87: =TEXT(tbMedições[[#This Row],[DATA REFERÊNCIA]],"aa/mm") -> 26/01 | K87: =_xlfn.XLOOKUP(tbMedições[[#This Row],[CONTRATO_ID]],tbContratos[CONTRATO_ID],tbContratos[VALOR CONTRATO],"Não encontrado")*tbMedições[[#This Row],[PERCENTUAL]] -> 5000 | L87: A fazer
A88: MED087 | B88: {=_xlfn.XLOOKUP(tbMedições[[#This Row],[EMPRESA]]&tbMedições[[#This Row],[OBRA]],tbContratos[EMPRESA]&tbContratos[OBRA],tbContratos[CONTRATO_ID],"Não localizado")} -> CT030 | C88: VERTICAL | D88: ALT | E88: Anteprojeto + Executivo | F88: 1 | H88: 46006 | I88: =IF(tbMedições[[#This Row],[STATUS]]="Cancelada",DATE(1900,1,1),IF(OR(tbMedições[[#This Row],[STATUS]]="Pago",tbMedições[[#This Row],[STATUS]]="Medido"),tbMedições[[#This Row],[DATA MEDIÇÃO]],tbMedições[[#This Row],[DATA PREVISTA]])) -> 46006 | J88: =TEXT(tbMedições[[#This Row],[DATA REFERÊNCIA]],"aa/mm") -> 25/12 | K88: =_xlfn.XLOOKUP(tbMedições[[#This Row],[CONTRATO_ID]],tbContratos[CONTRATO_ID],tbContratos[VALOR CONTRATO],"Não encontrado")*tbMedições[[#This Row],[PERCENTUAL]] -> 9000 | L88: Pago
A89: MED088 | B89: {=_xlfn.XLOOKUP(tbMedições[[#This Row],[EMPRESA]]&tbMedições[[#This Row],[OBRA]],tbContratos[EMPRESA]&tbContratos[OBRA],tbContratos[CONTRATO_ID],"Não localizado")} -> CT031 | C89: VERTICAL | D89: GAL | E89: Anteprojeto | F89: 0.3 | H89: 46147 | I89: =IF(tbMedições[[#This Row],[STATUS]]="Cancelada",DATE(1900,1,1),IF(OR(tbMedições[[#This Row],[STATUS]]="Pago",tbMedições[[#This Row],[STATUS]]="Medido"),tbMedições[[#This Row],[DATA MEDIÇÃO]],tbMedições[[#This Row],[DATA PREVISTA]])) -> 46147 | J89: =TEXT(tbMedições[[#This Row],[DATA REFERÊNCIA]],"aa/mm") -> 26/05 | K89: =_xlfn.XLOOKUP(tbMedições[[#This Row],[CONTRATO_ID]],tbContratos[CONTRATO_ID],tbContratos[VALOR CONTRATO],"Não encontrado")*tbMedições[[#This Row],[PERCENTUAL]] -> 1874.493 | L89: Pago
A90: MED089 | B90: {=_xlfn.XLOOKUP(tbMedições[[#This Row],[EMPRESA]]&tbMedições[[#This Row],[OBRA]],tbContratos[EMPRESA]&tbContratos[OBRA],tbContratos[CONTRATO_ID],"Não localizado")} -> CT031 | C90: VERTICAL | D90: GAL | E90: Executivo | F90: 0.7 | G90: 46305 | I90: =IF(tbMedições[[#This Row],[STATUS]]="Cancelada",DATE(1900,1,1),IF(OR(tbMedições[[#This Row],[STATUS]]="Pago",tbMedições[[#This Row],[STATUS]]="Medido"),tbMedições[[#This Row],[DATA MEDIÇÃO]],tbMedições[[#This Row],[DATA PREVISTA]])) -> 46305 | J90: =TEXT(tbMedições[[#This Row],[DATA REFERÊNCIA]],"aa/mm") -> 26/10 | K90: =_xlfn.XLOOKUP(tbMedições[[#This Row],[CONTRATO_ID]],tbContratos[CONTRATO_ID],tbContratos[VALOR CONTRATO],"Não encontrado")*tbMedições[[#This Row],[PERCENTUAL]] -> 4373.817 | L90: Em andamento
A91: MED090 | B91: {=_xlfn.XLOOKUP(tbMedições[[#This Row],[EMPRESA]]&tbMedições[[#This Row],[OBRA]],tbContratos[EMPRESA]&tbContratos[OBRA],tbContratos[CONTRATO_ID],"Não localizado")} -> CT032 | C91: VERTICAL | D91: PQSUL | E91: Anteprojeto | F91: 0.3 | H91: 46147 | I91: =IF(tbMedições[[#This Row],[STATUS]]="Cancelada",DATE(1900,1,1),IF(OR(tbMedições[[#This Row],[STATUS]]="Pago",tbMedições[[#This Row],[STATUS]]="Medido"),tbMedições[[#This Row],[DATA MEDIÇÃO]],tbMedições[[#This Row],[DATA PREVISTA]])) -> 46147 | J91: =TEXT(tbMedições[[#This Row],[DATA REFERÊNCIA]],"aa/mm") -> 26/05 | K91: =_xlfn.XLOOKUP(tbMedições[[#This Row],[CONTRATO_ID]],tbContratos[CONTRATO_ID],tbContratos[VALOR CONTRATO],"Não encontrado")*tbMedições[[#This Row],[PERCENTUAL]] -> 3728.835 | L91: Pago
A92: MED091 | B92: {=_xlfn.XLOOKUP(tbMedições[[#This Row],[EMPRESA]]&tbMedições[[#This Row],[OBRA]],tbContratos[EMPRESA]&tbContratos[OBRA],tbContratos[CONTRATO_ID],"Não localizado")} -> CT032 | C92: VERTICAL | D92: PQSUL | E92: Executivo | F92: 0.7 | G92: 46305 | I92: =IF(tbMedições[[#This Row],[STATUS]]="Cancelada",DATE(1900,1,1),IF(OR(tbMedições[[#This Row],[STATUS]]="Pago",tbMedições[[#This Row],[STATUS]]="Medido"),tbMedições[[#This Row],[DATA MEDIÇÃO]],tbMedições[[#This Row],[DATA PREVISTA]])) -> 46305 | J92: =TEXT(tbMedições[[#This Row],[DATA REFERÊNCIA]],"aa/mm") -> 26/10 | K92: =_xlfn.XLOOKUP(tbMedições[[#This Row],[CONTRATO_ID]],tbContratos[CONTRATO_ID],tbContratos[VALOR CONTRATO],"Não encontrado")*tbMedições[[#This Row],[PERCENTUAL]] -> 8700.615 | L92: Em andamento
A93: MED092 | B93: {=_xlfn.XLOOKUP(tbMedições[[#This Row],[EMPRESA]]&tbMedições[[#This Row],[OBRA]],tbContratos[EMPRESA]&tbContratos[OBRA],tbContratos[CONTRATO_ID],"Não localizado")} -> CT033 | C93: VERTICAL | D93: LIB | E93: Anteprojeto | F93: 0.3 | H93: 46147 | I93: =IF(tbMedições[[#This Row],[STATUS]]="Cancelada",DATE(1900,1,1),IF(OR(tbMedições[[#This Row],[STATUS]]="Pago",tbMedições[[#This Row],[STATUS]]="Medido"),tbMedições[[#This Row],[DATA MEDIÇÃO]],tbMedições[[#This Row],[DATA PREVISTA]])) -> 46147 | J93: =TEXT(tbMedições[[#This Row],[DATA REFERÊNCIA]],"aa/mm") -> 26/05 | K93: =_xlfn.XLOOKUP(tbMedições[[#This Row],[CONTRATO_ID]],tbContratos[CONTRATO_ID],tbContratos[VALOR CONTRATO],"Não encontrado")*tbMedições[[#This Row],[PERCENTUAL]] -> 2420.133 | L93: Pago
A94: MED093 | B94: {=_xlfn.XLOOKUP(tbMedições[[#This Row],[EMPRESA]]&tbMedições[[#This Row],[OBRA]],tbContratos[EMPRESA]&tbContratos[OBRA],tbContratos[CONTRATO_ID],"Não localizado")} -> CT033 | C94: VERTICAL | D94: LIB | E94: Executivo | F94: 0.7 | G94: 46305 | I94: =IF(tbMedições[[#This Row],[STATUS]]="Cancelada",DATE(1900,1,1),IF(OR(tbMedições[[#This Row],[STATUS]]="Pago",tbMedições[[#This Row],[STATUS]]="Medido"),tbMedições[[#This Row],[DATA MEDIÇÃO]],tbMedições[[#This Row],[DATA PREVISTA]])) -> 46305 | J94: =TEXT(tbMedições[[#This Row],[DATA REFERÊNCIA]],"aa/mm") -> 26/10 | K94: =_xlfn.XLOOKUP(tbMedições[[#This Row],[CONTRATO_ID]],tbContratos[CONTRATO_ID],tbContratos[VALOR CONTRATO],"Não encontrado")*tbMedições[[#This Row],[PERCENTUAL]] -> 5646.977 | L94: Em andamento
A95: MED094 | B95: {=_xlfn.XLOOKUP(tbMedições[[#This Row],[EMPRESA]]&tbMedições[[#This Row],[OBRA]],tbContratos[EMPRESA]&tbContratos[OBRA],tbContratos[CONTRATO_ID],"Não localizado")} -> CT034 | C95: VERTICAL | D95: UNA | E95: Anteprojeto | F95: 0.3 | H95: 46147 | I95: =IF(tbMedições[[#This Row],[STATUS]]="Cancelada",DATE(1900,1,1),IF(OR(tbMedições[[#This Row],[STATUS]]="Pago",tbMedições[[#This Row],[STATUS]]="Medido"),tbMedições[[#This Row],[DATA MEDIÇÃO]],tbMedições[[#This Row],[DATA PREVISTA]])) -> 46147 | J95: =TEXT(tbMedições[[#This Row],[DATA REFERÊNCIA]],"aa/mm") -> 26/05 | K95: =_xlfn.XLOOKUP(tbMedições[[#This Row],[CONTRATO_ID]],tbContratos[CONTRATO_ID],tbContratos[VALOR CONTRATO],"Não encontrado")*tbMedições[[#This Row],[PERCENTUAL]] -> 2476.542 | L95: Pago
A96: MED095 | B96: {=_xlfn.XLOOKUP(tbMedições[[#This Row],[EMPRESA]]&tbMedições[[#This Row],[OBRA]],tbContratos[EMPRESA]&tbContratos[OBRA],tbContratos[CONTRATO_ID],"Não localizado")} -> CT034 | C96: VERTICAL | D96: UNA | E96: Executivo | F96: 0.7 | G96: 46305 | I96: =IF(tbMedições[[#This Row],[STATUS]]="Cancelada",DATE(1900,1,1),IF(OR(tbMedições[[#This Row],[STATUS]]="Pago",tbMedições[[#This Row],[STATUS]]="Medido"),tbMedições[[#This Row],[DATA MEDIÇÃO]],tbMedições[[#This Row],[DATA PREVISTA]])) -> 46305 | J96: =TEXT(tbMedições[[#This Row],[DATA REFERÊNCIA]],"aa/mm") -> 26/10 | K96: =_xlfn.XLOOKUP(tbMedições[[#This Row],[CONTRATO_ID]],tbContratos[CONTRATO_ID],tbContratos[VALOR CONTRATO],"Não encontrado")*tbMedições[[#This Row],[PERCENTUAL]] -> 5778.598 | L96: Em andamento
A97: MED096 | B97: {=_xlfn.XLOOKUP(tbMedições[[#This Row],[EMPRESA]]&tbMedições[[#This Row],[OBRA]],tbContratos[EMPRESA]&tbContratos[OBRA],tbContratos[CONTRATO_ID],"Não localizado")} -> CT035 | C97: BINV | D97: ALT | E97: Entrada | F97: 0.1 | H97: 46072 | I97: =IF(tbMedições[[#This Row],[STATUS]]="Cancelada",DATE(1900,1,1),IF(OR(tbMedições[[#This Row],[STATUS]]="Pago",tbMedições[[#This Row],[STATUS]]="Medido"),tbMedições[[#This Row],[DATA MEDIÇÃO]],tbMedições[[#This Row],[DATA PREVISTA]])) -> 46072 | J97: =TEXT(tbMedições[[#This Row],[DATA REFERÊNCIA]],"aa/mm") -> 26/02 | K97: =_xlfn.XLOOKUP(tbMedições[[#This Row],[CONTRATO_ID]],tbContratos[CONTRATO_ID],tbContratos[VALOR CONTRATO],"Não encontrado")*tbMedições[[#This Row],[PERCENTUAL]] -> 15000 | L97: Pago | Q97: =1-SUM(F97:F100) -> 0.55333333
A98: MED097 | B98: {=_xlfn.XLOOKUP(tbMedições[[#This Row],[EMPRESA]]&tbMedições[[#This Row],[OBRA]],tbContratos[EMPRESA]&tbContratos[OBRA],tbContratos[CONTRATO_ID],"Não localizado")} -> CT035 | C98: BINV | D98: ALT | E98: Estudo preliminar | F98: 0.2 | H98: 46072 | I98: =IF(tbMedições[[#This Row],[STATUS]]="Cancelada",DATE(1900,1,1),IF(OR(tbMedições[[#This Row],[STATUS]]="Pago",tbMedições[[#This Row],[STATUS]]="Medido"),tbMedições[[#This Row],[DATA MEDIÇÃO]],tbMedições[[#This Row],[DATA PREVISTA]])) -> 46072 | J98: =TEXT(tbMedições[[#This Row],[DATA REFERÊNCIA]],"aa/mm") -> 26/02 | K98: =_xlfn.XLOOKUP(tbMedições[[#This Row],[CONTRATO_ID]],tbContratos[CONTRATO_ID],tbContratos[VALOR CONTRATO],"Não encontrado")*tbMedições[[#This Row],[PERCENTUAL]] -> 30000 | L98: Pago
A99: MED098 | B99: {=_xlfn.XLOOKUP(tbMedições[[#This Row],[EMPRESA]]&tbMedições[[#This Row],[OBRA]],tbContratos[EMPRESA]&tbContratos[OBRA],tbContratos[CONTRATO_ID],"Não localizado")} -> CT035 | C99: BINV | D99: ALT | E99: Anteprojeto | F99: 0.1 | H99: 46154 | I99: =IF(tbMedições[[#This Row],[STATUS]]="Cancelada",DATE(1900,1,1),IF(OR(tbMedições[[#This Row],[STATUS]]="Pago",tbMedições[[#This Row],[STATUS]]="Medido"),tbMedições[[#This Row],[DATA MEDIÇÃO]],tbMedições[[#This Row],[DATA PREVISTA]])) -> 46154 | J99: =TEXT(tbMedições[[#This Row],[DATA REFERÊNCIA]],"aa/mm") -> 26/05 | K99: =_xlfn.XLOOKUP(tbMedições[[#This Row],[CONTRATO_ID]],tbContratos[CONTRATO_ID],tbContratos[VALOR CONTRATO],"Não encontrado")*tbMedições[[#This Row],[PERCENTUAL]] -> 15000 | L99: Pago
A100: MED099 | B100: {=_xlfn.XLOOKUP(tbMedições[[#This Row],[EMPRESA]]&tbMedições[[#This Row],[OBRA]],tbContratos[EMPRESA]&tbContratos[OBRA],tbContratos[CONTRATO_ID],"Não localizado")} -> CT035 | C100: BINV | D100: ALT | E100: Executivo | F100: 0.046666667 | H100: 46185 | I100: =IF(tbMedições[[#This Row],[STATUS]]="Cancelada",DATE(1900,1,1),IF(OR(tbMedições[[#This Row],[STATUS]]="Pago",tbMedições[[#This Row],[STATUS]]="Medido"),tbMedições[[#This Row],[DATA MEDIÇÃO]],tbMedições[[#This Row],[DATA PREVISTA]])) -> 46185 | J100: =TEXT(tbMedições[[#This Row],[DATA REFERÊNCIA]],"aa/mm") -> 26/06 | K100: =_xlfn.XLOOKUP(tbMedições[[#This Row],[CONTRATO_ID]],tbContratos[CONTRATO_ID],tbContratos[VALOR CONTRATO],"Não encontrado")*tbMedições[[#This Row],[PERCENTUAL]] -> 7000 | L100: Pago
...

Sheet Planilha1
E3: Vertical
E4: NF | F4: VALOR | G4: OBRA | H4: CONTRATO | I4: MED2 | J4: NF 06/08 | K4: DIFF MED2 e NF 06/08 | L4: PERCENTUAL DE DESCONTO | M4: CONTRATO DESCONTADO
E5: 268 | F5: 1874.49 | G5: 65 | H5: 6458.72 | I5: =H5-F5 -> 4584.23 | J5: 4373.82 | K5: =I5-J5 -> 210.41 | L5: =K5/H5 -> 0.032577662 | M5: =H5*(1-L5) -> 6248.31 | N5: =M5-F5 -> 4373.82 | O5: =F5/M5 -> 0.29999952
E6: 269 | F6: 3728.84 | G6: 71 | H6: 12849.7 | I6: =H6-F6 -> 9120.86 | J6: 8700.61 | K6: =I6-J6 -> 420.25 | L6: =K6/H6 -> 0.032705044 | M6: =H6*(1-L6) -> 12429.45
E7: 267 | F7: 2420.13 | G7: 77 | H7: 8339.15 | I7: =H7-F7 -> 5919.02 | J7: 5646.98 | K7: =I7-J7 -> 272.04 | L7: =K7/H7 -> 0.03262203 | M7: =H7*(1-L7) -> 8067.11
E8: 266 | F8: 2476.54 | G8: 82 | H8: 8533.49 | I8: =H8-F8 -> 6056.95 | J8: 5778.6 | K8: =I8-J8 -> 278.35 | L8: =K8/H8 -> 0.032618542 | M8: =H8*(1-L8) -> 8255.14
F9: =SUM(F5:F8) -> 10500 | H9: =SUM(H5:H8) -> 36181.06
E11: nf
E12: 411 | F12: 5778.6
E13: 412 | F13: 4373.82
E14: 413 | F14: 5646.98
E15: 414 | F15: 8700.61
E19: NUM SIENGE | F19: EMPRESA | G19: OBRA | H19: DISCIPLINA | I19: SUBDISCIPLINA | J19: VALOR CONTRATO | K19: VALOR MEDIDO | L19: SALDO A MEDIR | M19: PERCENTUAL MEDIDO
E20: 95 | F20: SOMA | G20: ALT | H20: ARQUITETURA | I20: ARQUITERURA LEGAL | J20: 108000 | K20: 102600 | L20: 5400 | M20: 0.95
E21: 240 | F21: MBUIATE | G21: ALT | H21: ESTRUTURA | I21: ESTRUTURA DE CONCRETO | J21: 90000 | K21: 18000 | L21: 72000 | M21: 0.2
E22: 310 | F22: KARINA | G22: ALT | H22: INTERIORES | I22: INTERIORES | J22: 39500 | K22: 20700 | L22: 18800 | M22: 0.52405063
E23: 451 | F23: GEOMETA | G23: ALT | H23: SONDAGEM | I23: SONDAGEM | J23: 17500.65 | K23: 17500.65 | L23: 0 | M23: 1
E24: 476 | F24: VANIA | G24: ALT | H24: SONDAGEM | I24: SONDAGEM | J24: 1800 | K24: 1800 | L24: 0 | M24: 1
E25: 475 | F25: JP SERVIÇOS | G25: ALT | H25: SONDAGEM | I25: SONDAGEM | J25: 2580 | K25: 2580 | L25: 0 | M25: 1
F26: IDEAL | G26: ALT | H26: PLANIALTIMÉTRICO | I26: PLANIALTIMÉTRICO | J26: 4550 | K26: 4550 | L26: 0 | M26: 1
E27: 349 | F27: GEOMETRIA | G27: ALT | H27: FUNDAÇÃO | I27: FUNDAÇÃO PROFUNDA | J27: 25000 | K27: 0 | L27: 25000 | M27: 0
E28: 265 | F28: VERTICAL | G28: ALT | H28: ORÇAMENTO | I28: PARAMÉTRICO | J28: 9000 | K28: 9000 | L28: 0 | M28: 1
E29: 345 | F29: BINV | G29: ALT | H29: COMPLEMENTARES | I29: COMPLEMENTARES | J29: 150000 | K29: 67000 | L29: 83000 | M29: 0.44666667
E30: 528 | F30: ARCIS | G30: ALT | H30: COMPLEMENTARES | I30: COMPLEMENTARES | J30: 140000 | K30: 42000 | L30: 98000 | M30: 0.3
E31: 431 | F31: DOMANI | G31: ALT | H31: DESEMPENHO | I31: DESEMPENHO | J31: 5000 | K31: 0 | L31: 5000 | M31: 0
E32: 382 | F32: THAIS | G32: ALT | H32: LEGALIZAÇÃO | I32: LEGALIZAÇÃO | J32: 14250 | K32: 7125 | L32: 7125 | M32: 0.5
E33: 385 | F33: COSTA | G33: ALT | H33: LEGALIZAÇÃO | I33: LEGALIZAÇÃO | J33: 600 | K33: 600 | L33: 0 | M33: 1
F34: TAXAS | G34: ALT | H34: LEGALIZAÇÃO | I34: LEGALIZAÇÃO | J34: 513436.4 | K34: 6060.03 | L34: 507376.37 | M34: 0.011802883
